[
  {
    "slug": "will-there-be-another-us-government-shutdown-by-january-31",
    "ticker": "will-there-be-another-us-government-shutdown-by-january-31",
    "question": "US government shutdown Saturday?",
    "eventTitle": "US government shutdown Saturday?",
    "prices": "Yes: 99.9% | No: 0.1%",
    "volume": 81971329,
    "liquidity": 5395150,
    "endDate": "2026-01-31",
    "dayChange": "0.40%",
    "vol24h": 30630341,
    "updatedAt": "2026-02-01T10:43:22.218762Z",
    "category": "POLITICS",
    "strategy_tags": [
      "TAIL_RISK",
      "HIGH_CERTAINTY"
    ]
  },
  {
    "slug": "who-will-trump-nominate-as-fed-chair",
    "ticker": "will-trump-nominate-judy-shelton-as-the-next-fed-chair",
    "question": "Judy Shelton",
    "eventTitle": "Who will Trump nominate as Fed Chair?",
    "prices": "Yes: 0.9% | No: 99.1%",
    "volume": 36349245,
    "liquidity": 1221284,
    "endDate": "2026-12-31",
    "dayChange": "-0.50%",
    "vol24h": 4181961,
    "updatedAt": "2026-02-01T10:43:40.980145Z",
    "category": "POLITICS",
    "strategy_tags": [
      "TAIL_RISK",
      "HIGH_CERTAINTY"
    ]
  },
  {
    "slug": "tesla-launches-unsupervised-full-self-driving-fsd-by",
    "ticker": "tesla-launches-unsupervised-full-self-driving-fsd-by-october-31-717-337",
    "question": "June 30, 2026",
    "eventTitle": "Tesla launches unsupervised full self driving (FSD) by...?",
    "prices": "Yes: 100.0% | No: 0.1%",
    "volume": 11081924,
    "liquidity": 1182087,
    "endDate": "2026-06-30",
    "dayChange": "0.10%",
    "vol24h": 2019913,
    "updatedAt": "2026-02-01T10:43:44.424435Z",
    "category": "TECH",
    "strategy_tags": [
      "TAIL_RISK",
      "HIGH_CERTAINTY"
    ]
  },
  {
    "slug": "democratic-presidential-nominee-2028",
    "ticker": "will-bernie-sanders-win-the-2028-democratic-presidential-nomination-879",
    "question": "Bernie Sanders",
    "eventTitle": "Democratic Presidential Nominee 2028",
    "prices": "Yes: 0.9% | No: 99.2%",
    "volume": 27338000,
    "liquidity": 1312843,
    "endDate": "2028-11-07",
    "dayChange": "0.00%",
    "vol24h": 1745303,
    "updatedAt": "2026-02-01T10:43:09.370975Z",
    "category": "POLITICS",
    "strategy_tags": [
      "TAIL_RISK",
      "HIGH_CERTAINTY"
    ]
  },
  {
    "slug": "us-strikes-iran-by",
    "ticker": "us-strikes-iran-by-february-1-2026",
    "question": "February 1",
    "eventTitle": "US strikes Iran by...?",
    "prices": "Yes: 1.3% | No: 98.8%",
    "volume": 3089432,
    "liquidity": 406992,
    "endDate": "2026-02-01",
    "dayChange": "-8.25%",
    "vol24h": 1684163,
    "updatedAt": "2026-02-01T10:43:36.547628Z",
    "category": "POLITICS | GEOPOLITICS | WORLD",
    "strategy_tags": [
      "TAIL_RISK",
      "REFLEXIVITY_TREND",
      "HIGH_CERTAINTY"
    ]
  },
  {
    "slug": "who-will-trump-nominate-as-fed-chair",
    "ticker": "will-trump-nominate-kevin-warsh-as-the-next-fed-chair",
    "question": "Kevin Warsh",
    "eventTitle": "Who will Trump nominate as Fed Chair?",
    "prices": "Yes: 98.6% | No: 1.5%",
    "volume": 23193971,
    "liquidity": 705305,
    "endDate": "2026-12-31",
    "dayChange": "0.70%",
    "vol24h": 1505279,
    "updatedAt": "2026-02-01T10:43:08.610413Z",
    "category": "POLITICS",
    "strategy_tags": [
      "TAIL_RISK",
      "HIGH_CERTAINTY"
    ]
  },
  {
    "slug": "human-moon-landing-in-2026",
    "ticker": "human-moon-landing-in-2026",
    "question": "Human moon landing in 2026?",
    "eventTitle": "Human moon landing in 2026?",
    "prices": "Yes: 6.6% | No: 93.5%",
    "volume": 1357413,
    "liquidity": 29459,
    "endDate": "2026-12-31",
    "dayChange": "0.90%",
    "vol24h": 1316613,
    "updatedAt": "2026-02-01T10:43:23.58747Z",
    "category": "TECH | CLIMATE-SCIENCE",
    "strategy_tags": [
      "HIGH_CERTAINTY"
    ]
  },
  {
    "slug": "who-will-trump-nominate-as-fed-chair",
    "ticker": "will-trump-nominate-jerome-powell-as-the-next-fed-chair",
    "question": "Jerome Powell",
    "eventTitle": "Who will Trump nominate as Fed Chair?",
    "prices": "Yes: 0.1% | No: 99.9%",
    "volume": 20470407,
    "liquidity": 2986731,
    "endDate": "2026-12-31",
    "dayChange": "0.00%",
    "vol24h": 1147985,
    "updatedAt": "2026-02-01T10:43:34.453984Z",
    "category": "POLITICS",
    "strategy_tags": [
      "TAIL_RISK",
      "HIGH_CERTAINTY"
    ]
  },
  {
    "slug": "republican-presidential-nominee-2028",
    "ticker": "will-mike-pence-win-the-2028-republican-presidential-nomination",
    "question": "Mike Pence",
    "eventTitle": "Republican Presidential Nominee 2028",
    "prices": "Yes: 0.8% | No: 99.3%",
    "volume": 18860933,
    "liquidity": 593568,
    "endDate": "2028-11-07",
    "dayChange": "0.00%",
    "vol24h": 1041947,
    "updatedAt": "2026-02-01T10:43:42.911555Z",
    "category": "POLITICS",
    "strategy_tags": [
      "TAIL_RISK",
      "HIGH_CERTAINTY"
    ]
  },
  {
    "slug": "who-will-trump-nominate-as-fed-chair",
    "ticker": "will-trump-nominate-michelle-bowman-as-the-next-fed-chair",
    "question": "Michelle Bowman",
    "eventTitle": "Who will Trump nominate as Fed Chair?",
    "prices": "Yes: 0.1% | No: 99.9%",
    "volume": 13390501,
    "liquidity": 264709,
    "endDate": "2026-12-31",
    "dayChange": "0.00%",
    "vol24h": 965239,
    "updatedAt": "2026-02-01T10:43:34.305283Z",
    "category": "POLITICS",
    "strategy_tags": [
      "TAIL_RISK",
      "HIGH_CERTAINTY"
    ]
  },
  {
    "slug": "who-will-trump-nominate-as-fed-chair",
    "ticker": "will-trump-nominate-christopher-waller-as-the-next-fed-chair",
    "question": "Christopher Waller",
    "eventTitle": "Who will Trump nominate as Fed Chair?",
    "prices": "Yes: 0.1% | No: 100.0%",
    "volume": 14478494,
    "liquidity": 433456,
    "endDate": "2026-12-31",
    "dayChange": "-0.25%",
    "vol24h": 942660,
    "updatedAt": "2026-02-01T10:43:11.715632Z",
    "category": "POLITICS",
    "strategy_tags": [
      "TAIL_RISK",
      "HIGH_CERTAINTY"
    ]
  },
  {
    "slug": "israel-strikes-iran-by-january-31-2026",
    "ticker": "israel-strikes-iran-by-january-31-2026-894-994-453",
    "question": "January 31",
    "eventTitle": "Israel strikes Iran by January 31, 2026?",
    "prices": "Yes: 0.1% | No: 100.0%",
    "volume": 16897091,
    "liquidity": 165292,
    "endDate": "2026-01-31",
    "dayChange": "-1.80%",
    "vol24h": 874218,
    "updatedAt": "2026-02-01T10:43:19.261625Z",
    "category": "POLITICS | GEOPOLITICS",
    "strategy_tags": [
      "TAIL_RISK",
      "HIGH_CERTAINTY"
    ]
  },
  {
    "slug": "how-long-will-the-next-government-shutdown-last",
    "ticker": "will-the-government-shutdown-last-3-days-or-more",
    "question": "3+ days",
    "eventTitle": "How long will the Government Shutdown last?",
    "prices": "Yes: 99.9% | No: 0.1%",
    "volume": 1643916,
    "liquidity": 469931,
    "endDate": "2026-03-31",
    "dayChange": "1.30%",
    "vol24h": 743608,
    "updatedAt": "2026-02-01T10:43:33.265813Z",
    "category": "POLITICS | ECONOMY",
    "strategy_tags": [
      "TAIL_RISK",
      "HIGH_CERTAINTY"
    ]
  },
  {
    "slug": "who-will-trump-nominate-as-fed-chair",
    "ticker": "will-trump-nominate-kevin-hassett-as-the-next-fed-chair",
    "question": "Kevin Hassett",
    "eventTitle": "Who will Trump nominate as Fed Chair?",
    "prices": "Yes: 0.1% | No: 100.0%",
    "volume": 20538753,
    "liquidity": 656932,
    "endDate": "2026-12-31",
    "dayChange": "0.00%",
    "vol24h": 645100,
    "updatedAt": "2026-02-01T10:43:34.655418Z",
    "category": "POLITICS",
    "strategy_tags": [
      "TAIL_RISK",
      "HIGH_CERTAINTY"
    ]
  },
  {
    "slug": "how-long-will-the-next-government-shutdown-last",
    "ticker": "will-the-government-shutdown-last-4-days-or-more-831",
    "question": "4+ days",
    "eventTitle": "How long will the Government Shutdown last?",
    "prices": "Yes: 96.0% | No: 4.0%",
    "volume": 709680,
    "liquidity": 83746,
    "endDate": "2026-03-31",
    "dayChange": "62.70%",
    "vol24h": 601881,
    "updatedAt": "2026-02-01T10:43:30.402602Z",
    "category": "POLITICS | ECONOMY",
    "strategy_tags": [
      "TAIL_RISK",
      "REFLEXIVITY_TREND",
      "HIGH_CERTAINTY"
    ]
  },
  {
    "slug": "democratic-presidential-nominee-2028",
    "ticker": "will-mrbeast-win-the-2028-democratic-presidential-nomination",
    "question": "MrBeast",
    "eventTitle": "Democratic Presidential Nominee 2028",
    "prices": "Yes: 0.9% | No: 99.1%",
    "volume": 27876430,
    "liquidity": 1114225,
    "endDate": "2028-11-07",
    "dayChange": "0.10%",
    "vol24h": 567601,
    "updatedAt": "2026-02-01T10:43:33.198569Z",
    "category": "POLITICS",
    "strategy_tags": [
      "TAIL_RISK",
      "HIGH_CERTAINTY"
    ]
  },
  {
    "slug": "us-next-strikes-iran-on",
    "ticker": "will-the-us-next-strike-iran-on-january-31-2026-et-836",
    "question": "January 31",
    "eventTitle": "US next strikes Iran on...?",
    "prices": "Yes: 0.1% | No: 99.9%",
    "volume": 2456965,
    "liquidity": 82083,
    "endDate": "2026-01-31",
    "dayChange": "-4.40%",
    "vol24h": 539202,
    "updatedAt": "2026-02-01T10:43:07.737584Z",
    "category": "POLITICS | GEOPOLITICS | WORLD",
    "strategy_tags": [
      "TAIL_RISK",
      "HIGH_CERTAINTY"
    ]
  },
  {
    "slug": "presidential-election-winner-2028",
    "ticker": "will-kim-kardashian-win-the-2028-us-presidential-election",
    "question": "Kim Kardashian",
    "eventTitle": "Presidential Election Winner 2028",
    "prices": "Yes: 0.8% | No: 99.3%",
    "volume": 14973034,
    "liquidity": 1133650,
    "endDate": "2028-11-07",
    "dayChange": "0.00%",
    "vol24h": 519332,
    "updatedAt": "2026-02-01T10:43:11.895418Z",
    "category": "POLITICS",
    "strategy_tags": [
      "TAIL_RISK",
      "HIGH_CERTAINTY"
    ]
  },
  {
    "slug": "who-will-trump-nominate-as-fed-chair",
    "ticker": "will-trump-nominate-rick-rieder-as-the-next-fed-chair",
    "question": "Rick Rieder",
    "eventTitle": "Who will Trump nominate as Fed Chair?",
    "prices": "Yes: 0.2% | No: 99.8%",
    "volume": 16694912,
    "liquidity": 191499,
    "endDate": "2026-12-31",
    "dayChange": "0.15%",
    "vol24h": 514030,
    "updatedAt": "2026-02-01T10:43:16.54319Z",
    "category": "POLITICS",
    "strategy_tags": [
      "TAIL_RISK",
      "HIGH_CERTAINTY"
    ]
  },
  {
    "slug": "presidential-election-winner-2028",
    "ticker": "will-zohran-mamdani-win-the-2028-us-presidential-election",
    "question": "Zohran Mamdani",
    "eventTitle": "Presidential Election Winner 2028",
    "prices": "Yes: 0.8% | No: 99.3%",
    "volume": 6641238,
    "liquidity": 724239,
    "endDate": "2028-11-07",
    "dayChange": "0.20%",
    "vol24h": 513315,
    "updatedAt": "2026-02-01T10:43:33.06994Z",
    "category": "POLITICS",
    "strategy_tags": [
      "TAIL_RISK",
      "HIGH_CERTAINTY"
    ]
  },
  {
    "slug": "presidential-election-winner-2028",
    "ticker": "will-greg-abbott-win-the-2028-us-presidential-election",
    "question": "Greg Abbott",
    "eventTitle": "Presidential Election Winner 2028",
    "prices": "Yes: 0.7% | No: 99.4%",
    "volume": 21181784,
    "liquidity": 1182079,
    "endDate": "2028-11-07",
    "dayChange": "0.00%",
    "vol24h": 488628,
    "updatedAt": "2026-02-01T10:43:24.118539Z",
    "category": "POLITICS",
    "strategy_tags": [
      "TAIL_RISK",
      "HIGH_CERTAINTY"
    ]
  },
  {
    "slug": "us-strikes-iran-by",
    "ticker": "us-strikes-iran-by-february-28-2026-227-967-547-688-589-491-592-418-452-924-384-915-464-672-196",
    "question": "February 28",
    "eventTitle": "US strikes Iran by...?",
    "prices": "Yes: 41.5% | No: 58.5%",
    "volume": 4923007,
    "liquidity": 158234,
    "endDate": "2026-01-31",
    "dayChange": "-16.00%",
    "vol24h": 482223,
    "updatedAt": "2026-02-01T10:43:42.647116Z",
    "category": "POLITICS | GEOPOLITICS | WORLD",
    "strategy_tags": [
      "REFLEXIVITY_TREND"
    ]
  },
  {
    "slug": "democratic-presidential-nominee-2028",
    "ticker": "will-gina-raimondo-win-the-2028-democratic-presidential-nomination-676",
    "question": "Gina Raimondo",
    "eventTitle": "Democratic Presidential Nominee 2028",
    "prices": "Yes: 0.9% | No: 99.1%",
    "volume": 20139594,
    "liquidity": 1082131,
    "endDate": "2028-11-07",
    "dayChange": "0.00%",
    "vol24h": 451492,
    "updatedAt": "2026-02-01T10:43:12.91224Z",
    "category": "POLITICS",
    "strategy_tags": [
      "TAIL_RISK",
      "HIGH_CERTAINTY"
    ]
  },
  {
    "slug": "who-will-trump-talk-to-in-january",
    "ticker": "will-trump-talk-to-vladimir-putin-in-january",
    "question": "Vladimir Putin",
    "eventTitle": "Who will Trump talk to in January?",
    "prices": "Yes: 17.6% | No: 82.4%",
    "volume": 1069111,
    "liquidity": 36457,
    "endDate": "2026-01-31",
    "dayChange": "-21.55%",
    "vol24h": 446018,
    "updatedAt": "2026-02-01T10:43:40.327939Z",
    "category": "POLITICS | GEOPOLITICS",
    "strategy_tags": [
      "REFLEXIVITY_TREND"
    ]
  },
  {
    "slug": "bitcoin-up-or-down-on-february-1",
    "ticker": "bitcoin-up-or-down-on-february-1",
    "question": "Bitcoin Up or Down on February 1?",
    "eventTitle": "Bitcoin Up or Down on February 1?",
    "prices": "Up: 3.5% | Down: 96.5%",
    "volume": 556637,
    "liquidity": 30476,
    "endDate": "2026-02-01",
    "dayChange": "-47.30%",
    "vol24h": 440189,
    "updatedAt": "2026-02-01T10:43:17.282529Z",
    "category": "CRYPTO",
    "strategy_tags": [
      "TAIL_RISK",
      "REFLEXIVITY_TREND",
      "HIGH_CERTAINTY"
    ]
  },
  {
    "slug": "presidential-election-winner-2028",
    "ticker": "will-tulsi-gabbard-win-the-2028-us-presidential-election",
    "question": "Tulsi Gabbard",
    "eventTitle": "Presidential Election Winner 2028",
    "prices": "Yes: 0.8% | No: 99.3%",
    "volume": 18144833,
    "liquidity": 981812,
    "endDate": "2028-11-07",
    "dayChange": "0.00%",
    "vol24h": 427047,
    "updatedAt": "2026-02-01T10:43:41.461367Z",
    "category": "POLITICS",
    "strategy_tags": [
      "TAIL_RISK",
      "HIGH_CERTAINTY"
    ]
  },
  {
    "slug": "khamenei-out-as-supreme-leader-of-iran-by-february-28",
    "ticker": "khamenei-out-as-supreme-leader-of-iran-by-february-28",
    "question": "Khamenei out as Supreme Leader of Iran by February 28?",
    "eventTitle": "Khamenei out as Supreme Leader of Iran by February 28?",
    "prices": "Yes: 13.5% | No: 86.5%",
    "volume": 3734360,
    "liquidity": 597541,
    "endDate": "2026-02-28",
    "dayChange": "-8.00%",
    "vol24h": 425274,
    "updatedAt": "2026-02-01T10:43:19.479407Z",
    "category": "GEOPOLITICS",
    "strategy_tags": [
      "REFLEXIVITY_TREND"
    ]
  },
  {
    "slug": "us-next-strikes-iran-on",
    "ticker": "will-the-us-not-strike-iran-by-january-31-2026-314",
    "question": "No strike by January 31",
    "eventTitle": "US next strikes Iran on...?",
    "prices": "Yes: 99.9% | No: 0.1%",
    "volume": 3250001,
    "liquidity": 37242,
    "endDate": "2026-01-31",
    "dayChange": "5.35%",
    "vol24h": 415453,
    "updatedAt": "2026-02-01T10:43:03.059758Z",
    "category": "POLITICS | GEOPOLITICS | WORLD",
    "strategy_tags": [
      "TAIL_RISK",
      "REFLEXIVITY_TREND",
      "HIGH_CERTAINTY"
    ]
  },
  {
    "slug": "presidential-election-winner-2028",
    "ticker": "will-michelle-obama-win-the-2028-us-presidential-election",
    "question": "Michelle Obama",
    "eventTitle": "Presidential Election Winner 2028",
    "prices": "Yes: 0.8% | No: 99.3%",
    "volume": 7553921,
    "liquidity": 870063,
    "endDate": "2028-11-07",
    "dayChange": "0.00%",
    "vol24h": 405958,
    "updatedAt": "2026-02-01T10:43:32.497715Z",
    "category": "POLITICS",
    "strategy_tags": [
      "TAIL_RISK",
      "HIGH_CERTAINTY"
    ]
  },
  {
    "slug": "democratic-presidential-nominee-2028",
    "ticker": "will-mark-cuban-win-the-2028-democratic-presidential-nomination-329",
    "question": "Mark Cuban",
    "eventTitle": "Democratic Presidential Nominee 2028",
    "prices": "Yes: 0.9% | No: 99.1%",
    "volume": 10586552,
    "liquidity": 886623,
    "endDate": "2028-11-07",
    "dayChange": "0.10%",
    "vol24h": 378667,
    "updatedAt": "2026-02-01T10:43:22.270806Z",
    "category": "POLITICS",
    "strategy_tags": [
      "TAIL_RISK",
      "HIGH_CERTAINTY"
    ]
  },
  {
    "slug": "what-price-will-bitcoin-hit-january-26-1",
    "ticker": "will-bitcoin-dip-to-74k-january-26-1",
    "question": "↓ 74,000",
    "eventTitle": "What price will Bitcoin hit January 26-February 1?",
    "prices": "Yes: 7.1% | No: 92.9%",
    "volume": 428230,
    "liquidity": 25315,
    "endDate": "2026-02-02",
    "dayChange": "5.35%",
    "vol24h": 210379,
    "updatedAt": "2026-02-01T10:43:34.896369Z",
    "category": "CRYPTO",
    "strategy_tags": [
      "REFLEXIVITY_TREND"
    ]
  },
  {
    "slug": "how-long-will-the-next-government-shutdown-last",
    "ticker": "will-the-government-shutdown-last-7-days-or-more-188-769-669",
    "question": "7+ days",
    "eventTitle": "How long will the Government Shutdown last?",
    "prices": "Yes: 19.5% | No: 80.5%",
    "volume": 653993,
    "liquidity": 41899,
    "endDate": "2026-03-31",
    "dayChange": "6.50%",
    "vol24h": 199456,
    "updatedAt": "2026-02-01T10:43:06.801792Z",
    "category": "POLITICS | ECONOMY",
    "strategy_tags": [
      "REFLEXIVITY_TREND"
    ]
  },
  {
    "slug": "which-companies-will-be-acquired-before-2027",
    "ticker": "will-zoom-video-communications-be-acquired-before-2027-486",
    "question": "Zoom Video Communications",
    "eventTitle": "Which companies will be acquired before 2027?",
    "prices": "Yes: 6.8% | No: 93.2%",
    "volume": 289647,
    "liquidity": 1895,
    "endDate": "2026-12-31",
    "dayChange": "-1.85%",
    "vol24h": 191503,
    "updatedAt": "2026-02-01T10:43:14.119319Z",
    "category": "TECH | FINANCE",
    "strategy_tags": [
      "HIGH_CERTAINTY"
    ]
  },
  {
    "slug": "ethereum-up-or-down-on-february-1",
    "ticker": "ethereum-up-or-down-on-february-1",
    "question": "Ethereum Up or Down on February 1?",
    "eventTitle": "Ethereum Up or Down on February 1?",
    "prices": "Up: 2.5% | Down: 97.5%",
    "volume": 183633,
    "liquidity": 12160,
    "endDate": "2026-02-01",
    "dayChange": "-47.50%",
    "vol24h": 148533,
    "updatedAt": "2026-02-01T10:43:37.233813Z",
    "category": "CRYPTO",
    "strategy_tags": [
      "TAIL_RISK",
      "REFLEXIVITY_TREND"
    ]
  },
  {
    "slug": "microstrategy-sell-any-bitcoin-in-2025",
    "ticker": "microstrategy-sells-any-bitcoin-by-march-31-2026",
    "question": "March 31, 2026",
    "eventTitle": "MicroStrategy sells any Bitcoin by ___ ?",
    "prices": "Yes: 5.1% | No: 95.0%",
    "volume": 1093087,
    "liquidity": 75413,
    "endDate": "N/A",
    "dayChange": "0.80%",
    "vol24h": 47917,
    "updatedAt": "2026-02-01T10:43:07.127519Z",
    "category": "ECONOMY | CRYPTO | FINANCE",
    "strategy_tags": [
      "HIGH_CERTAINTY"
    ]
  },
  {
    "slug": "largest-company-end-of-march-588",
    "ticker": "will-amazon-be-the-largest-company-in-the-world-by-market-cap-on-march-31-453",
    "question": "Amazon",
    "eventTitle": "Largest Company end of March?",
    "prices": "Yes: 0.2% | No: 99.8%",
    "volume": 200316,
    "liquidity": 63111,
    "endDate": "2026-03-31",
    "dayChange": "0.00%",
    "vol24h": 30352,
    "updatedAt": "2026-02-01T10:43:41.550284Z",
    "category": "ECONOMY | TECH | FINANCE",
    "strategy_tags": [
      "TAIL_RISK",
      "HIGH_CERTAINTY"
    ]
  },
  {
    "slug": "largest-company-end-of-march-588",
    "ticker": "will-tesla-be-the-largest-company-in-the-world-by-market-cap-on-march-31",
    "question": "Tesla",
    "eventTitle": "Largest Company end of March?",
    "prices": "Yes: 0.2% | No: 99.8%",
    "volume": 294946,
    "liquidity": 64285,
    "endDate": "2026-03-31",
    "dayChange": "0.00%",
    "vol24h": 14527,
    "updatedAt": "2026-02-01T10:43:04.200822Z",
    "category": "ECONOMY | TECH | FINANCE",
    "strategy_tags": [
      "TAIL_RISK",
      "HIGH_CERTAINTY"
    ]
  },
  {
    "slug": "spacex-ipo-closing-market-cap",
    "ticker": "will-spacexs-market-cap-be-greater-than-1t-at-market-close-on-ipo-day",
    "question": "1T+",
    "eventTitle": "SpaceX IPO Closing Market Cap",
    "prices": "Yes: 73.0% | No: 27.0%",
    "volume": 326814,
    "liquidity": 25800,
    "endDate": "2027-12-31",
    "dayChange": "-0.50%",
    "vol24h": 8751,
    "updatedAt": "2026-02-01T10:43:06.082045Z",
    "category": "TECH | CLIMATE-SCIENCE",
    "strategy_tags": [
      "RAW_MARKET"
    ]
  },
  {
    "slug": "january-2026-temperature-increase-c",
    "ticker": "will-global-temperature-increase-by-less-than-1pt00c-in-january-2026",
    "question": "<1.00ºC",
    "eventTitle": "January 2026 Temperature Increase (ºC)",
    "prices": "Yes: 0.9% | No: 99.1%",
    "volume": 52016,
    "liquidity": 20301,
    "endDate": "2026-02-10",
    "dayChange": "-0.85%",
    "vol24h": 4153,
    "updatedAt": "2026-02-01T10:43:27.697279Z",
    "category": "CLIMATE-SCIENCE",
    "strategy_tags": [
      "TAIL_RISK",
      "HIGH_CERTAINTY"
    ]
  }
]