[
  {
    "slug": "fed-decision-in-march-885",
    "ticker": "will-the-fed-increase-interest-rates-by-25-bps-after-the-march-2026-meeting",
    "question": "25+ bps increase",
    "eventTitle": "Fed decision in March?",
    "prices": "Yes: 1.9% | No: 98.0%",
    "volume": 22496342,
    "liquidity": 816068,
    "endDate": "2026-03-18",
    "dayChange": "0.40%",
    "vol24h": 1908214,
    "spread": "0.10%",
    "sortOrder": 3,
    "updatedAt": "2026-02-03T16:01:03.705865Z",
    "engine": "sniper",
    "core_topic": "Fed decision in {month}?",
    "category": "ECONOMY",
    "url": "https://polymarket.com/event/fed-decision-in-march-885",
    "strategy_tags": [
      "TAIL_RISK",
      "HIGH_CERTAINTY"
    ]
  },
  {
    "slug": "fed-decision-in-march-885",
    "ticker": "will-the-fed-decrease-interest-rates-by-50-bps-after-the-march-2026-meeting",
    "question": "50+ bps decrease",
    "eventTitle": "Fed decision in March?",
    "prices": "Yes: 0.9% | No: 99.1%",
    "volume": 20093496,
    "liquidity": 1833853,
    "endDate": "2026-03-18",
    "dayChange": "-0.30%",
    "vol24h": 4883860,
    "spread": "0.10%",
    "sortOrder": 0,
    "updatedAt": "2026-02-03T16:01:44.993893Z",
    "engine": "sniper",
    "core_topic": "Fed decision in {month}?",
    "category": "ECONOMY",
    "url": "https://polymarket.com/event/fed-decision-in-march-885",
    "strategy_tags": [
      "TAIL_RISK",
      "HIGH_CERTAINTY"
    ]
  },
  {
    "slug": "fed-decision-in-march-885",
    "ticker": "will-there-be-no-change-in-fed-interest-rates-after-the-march-2026-meeting",
    "question": "No change",
    "eventTitle": "Fed decision in March?",
    "prices": "Yes: 90.5% | No: 9.5%",
    "volume": 5234851,
    "liquidity": 1295926,
    "endDate": "2026-03-18",
    "dayChange": "1.00%",
    "vol24h": 563892,
    "spread": "1.00%",
    "sortOrder": 2,
    "updatedAt": "2026-02-03T16:02:02.631374Z",
    "engine": "sniper",
    "core_topic": "Fed decision in {month}?",
    "category": "ECONOMY",
    "url": "https://polymarket.com/event/fed-decision-in-march-885",
    "strategy_tags": [
      "RAW_MARKET"
    ]
  },
  {
    "slug": "fed-decision-in-march-885",
    "ticker": "will-the-fed-decrease-interest-rates-by-25-bps-after-the-march-2026-meeting",
    "question": "25 bps decrease",
    "eventTitle": "Fed decision in March?",
    "prices": "Yes: 6.5% | No: 93.5%",
    "volume": 4594534,
    "liquidity": 877303,
    "endDate": "2026-03-18",
    "dayChange": "-1.00%",
    "vol24h": 434144,
    "spread": "1.00%",
    "sortOrder": 1,
    "updatedAt": "2026-02-03T16:02:02.43235Z",
    "engine": "sniper",
    "core_topic": "Fed decision in {month}?",
    "category": "ECONOMY",
    "url": "https://polymarket.com/event/fed-decision-in-march-885",
    "strategy_tags": [
      "RAW_MARKET"
    ]
  },
  {
    "slug": "what-price-will-bitcoin-hit-in-february-2026",
    "ticker": "will-bitcoin-reach-150k-in-february-2026",
    "question": "↑ 150,000",
    "eventTitle": "What price will Bitcoin hit in February?",
    "prices": "Yes: 0.4% | No: 99.6%",
    "volume": 1913932,
    "liquidity": 655427,
    "endDate": "2026-03-01",
    "dayChange": "0.00%",
    "vol24h": 1128650,
    "spread": "0.10%",
    "sortOrder": 0,
    "updatedAt": "2026-02-03T16:01:42.674345Z",
    "engine": "sniper",
    "core_topic": "What price will Bitcoin hit in {month}?",
    "category": "CRYPTO",
    "url": "https://polymarket.com/event/what-price-will-bitcoin-hit-in-february-2026",
    "strategy_tags": [
      "TAIL_RISK",
      "HIGH_CERTAINTY"
    ]
  },
  {
    "slug": "bitcoin-above-on-february-3",
    "ticker": "bitcoin-above-90k-on-february-3",
    "question": "90,000",
    "eventTitle": "Bitcoin above ___ on February 3?",
    "prices": "Yes: 0.1% | No: 100.0%",
    "volume": 1453385,
    "liquidity": 136680,
    "endDate": "2026-02-03",
    "dayChange": "-0.25%",
    "vol24h": 1379676,
    "spread": "0.10%",
    "sortOrder": 6,
    "updatedAt": "2026-02-03T16:05:18.838958Z",
    "engine": "sniper",
    "core_topic": "Bitcoin above ___ on {date}?",
    "category": "CRYPTO",
    "url": "https://polymarket.com/event/bitcoin-above-on-february-3",
    "strategy_tags": [
      "TAIL_RISK",
      "HIGH_CERTAINTY"
    ]
  },
  {
    "slug": "bitcoin-above-on-february-3",
    "ticker": "bitcoin-above-78k-on-february-3",
    "question": "78,000",
    "eventTitle": "Bitcoin above ___ on February 3?",
    "prices": "Yes: 45.8% | No: 54.2%",
    "volume": 1040731,
    "liquidity": 33363,
    "endDate": "2026-02-03",
    "dayChange": "-11.10%",
    "vol24h": 360156,
    "spread": "1.20%",
    "sortOrder": 0,
    "updatedAt": "2026-02-03T16:04:32.865315Z",
    "engine": "sniper",
    "core_topic": "Bitcoin above ___ on {date}?",
    "category": "CRYPTO",
    "url": "https://polymarket.com/event/bitcoin-above-on-february-3",
    "strategy_tags": [
      "REFLEXIVITY_TREND"
    ]
  },
  {
    "slug": "bitcoin-above-on-february-3",
    "ticker": "bitcoin-above-86k-on-february-3",
    "question": "86,000",
    "eventTitle": "Bitcoin above ___ on February 3?",
    "prices": "Yes: 0.1% | No: 100.0%",
    "volume": 973205,
    "liquidity": 139479,
    "endDate": "2026-02-03",
    "dayChange": "-0.95%",
    "vol24h": 651813,
    "spread": "0.10%",
    "sortOrder": 4,
    "updatedAt": "2026-02-03T16:04:30.232586Z",
    "engine": "sniper",
    "core_topic": "Bitcoin above ___ on {date}?",
    "category": "CRYPTO",
    "url": "https://polymarket.com/event/bitcoin-above-on-february-3",
    "strategy_tags": [
      "TAIL_RISK",
      "HIGH_CERTAINTY"
    ]
  },
  {
    "slug": "bitcoin-all-time-high-by",
    "ticker": "bitcoin-all-time-high-by-march-31-2026",
    "question": "March 31, 2026",
    "eventTitle": "Bitcoin all time high by ___?",
    "prices": "Yes: 2.9% | No: 97.2%",
    "volume": 962484,
    "liquidity": 65138,
    "endDate": "2026-04-01",
    "dayChange": "-1.10%",
    "vol24h": 16897,
    "spread": "0.10%",
    "sortOrder": 0,
    "updatedAt": "2026-02-03T16:01:33.682384Z",
    "engine": "sniper",
    "core_topic": "Bitcoin all time high by ___?",
    "category": "CRYPTO",
    "url": "https://polymarket.com/event/bitcoin-all-time-high-by",
    "strategy_tags": [
      "TAIL_RISK",
      "HIGH_CERTAINTY"
    ]
  },
  {
    "slug": "bitcoin-above-on-february-3",
    "ticker": "bitcoin-above-80k-on-february-3",
    "question": "80,000",
    "eventTitle": "Bitcoin above ___ on February 3?",
    "prices": "Yes: 1.1% | No: 98.9%",
    "volume": 790443,
    "liquidity": 56704,
    "endDate": "2026-02-03",
    "dayChange": "-31.30%",
    "vol24h": 227811,
    "spread": "0.40%",
    "sortOrder": 1,
    "updatedAt": "2026-02-03T16:04:48.91181Z",
    "engine": "sniper",
    "core_topic": "Bitcoin above ___ on {date}?",
    "category": "CRYPTO",
    "url": "https://polymarket.com/event/bitcoin-above-on-february-3",
    "strategy_tags": [
      "TAIL_RISK",
      "REFLEXIVITY_TREND",
      "HIGH_CERTAINTY"
    ]
  },
  {
    "slug": "what-price-will-bitcoin-hit-in-february-2026",
    "ticker": "will-bitcoin-dip-to-70k-in-february-2026",
    "question": "↓ 70,000",
    "eventTitle": "What price will Bitcoin hit in February?",
    "prices": "Yes: 44.5% | No: 55.5%",
    "volume": 716161,
    "liquidity": 107411,
    "endDate": "2026-03-01",
    "dayChange": "8.00%",
    "vol24h": 258775,
    "spread": "1.00%",
    "sortOrder": 12,
    "updatedAt": "2026-02-03T16:01:40.455704Z",
    "engine": "sniper",
    "core_topic": "What price will Bitcoin hit in {month}?",
    "category": "CRYPTO",
    "url": "https://polymarket.com/event/what-price-will-bitcoin-hit-in-february-2026",
    "strategy_tags": [
      "REFLEXIVITY_TREND"
    ]
  },
  {
    "slug": "how-many-fed-rate-cuts-in-2026",
    "ticker": "will-no-fed-rate-cuts-happen-in-2026",
    "question": "0 (0 bps)",
    "eventTitle": "How many Fed rate cuts in 2026?",
    "prices": "Yes: 7.5% | No: 92.5%",
    "volume": 687722,
    "liquidity": 104356,
    "endDate": "2026-12-31",
    "dayChange": "1.25%",
    "vol24h": 41305,
    "spread": "0.20%",
    "sortOrder": 0,
    "updatedAt": "2026-02-03T16:01:51.334188Z",
    "engine": "sniper",
    "core_topic": "How many Fed rate cuts in {year}?",
    "category": "ECONOMY",
    "url": "https://polymarket.com/event/how-many-fed-rate-cuts-in-2026",
    "strategy_tags": [
      "HIGH_CERTAINTY"
    ]
  },
  {
    "slug": "bitcoin-above-on-february-3",
    "ticker": "bitcoin-above-82k-on-february-3",
    "question": "82,000",
    "eventTitle": "Bitcoin above ___ on February 3?",
    "prices": "Yes: 0.1% | No: 100.0%",
    "volume": 658736,
    "liquidity": 66827,
    "endDate": "2026-02-03",
    "dayChange": "-12.50%",
    "vol24h": 219134,
    "spread": "0.10%",
    "sortOrder": 2,
    "updatedAt": "2026-02-03T16:04:44.222988Z",
    "engine": "sniper",
    "core_topic": "Bitcoin above ___ on {date}?",
    "category": "CRYPTO",
    "url": "https://polymarket.com/event/bitcoin-above-on-february-3",
    "strategy_tags": [
      "TAIL_RISK",
      "REFLEXIVITY_TREND",
      "HIGH_CERTAINTY"
    ]
  },
  {
    "slug": "bitcoin-above-on-february-3",
    "ticker": "bitcoin-above-84k-on-february-3",
    "question": "84,000",
    "eventTitle": "Bitcoin above ___ on February 3?",
    "prices": "Yes: 0.1% | No: 100.0%",
    "volume": 658437,
    "liquidity": 47895,
    "endDate": "2026-02-03",
    "dayChange": "-3.95%",
    "vol24h": 190968,
    "spread": "0.10%",
    "sortOrder": 3,
    "updatedAt": "2026-02-03T16:04:57.188075Z",
    "engine": "sniper",
    "core_topic": "Bitcoin above ___ on {date}?",
    "category": "CRYPTO",
    "url": "https://polymarket.com/event/bitcoin-above-on-february-3",
    "strategy_tags": [
      "TAIL_RISK",
      "HIGH_CERTAINTY"
    ]
  },
  {
    "slug": "bitcoin-above-on-february-5",
    "ticker": "bitcoin-above-76k-on-february-5",
    "question": "76,000",
    "eventTitle": "Bitcoin above ___ on February 5?",
    "prices": "Yes: 76.0% | No: 23.9%",
    "volume": 623381,
    "liquidity": 16012,
    "endDate": "2026-02-05",
    "dayChange": "-0.55%",
    "vol24h": 566664,
    "spread": "1.70%",
    "sortOrder": 0,
    "updatedAt": "2026-02-03T16:01:40.515943Z",
    "engine": "sniper",
    "core_topic": "Bitcoin above ___ on {date}?",
    "category": "CRYPTO",
    "url": "https://polymarket.com/event/bitcoin-above-on-february-5",
    "strategy_tags": [
      "RAW_MARKET"
    ]
  },
  {
    "slug": "what-price-will-bitcoin-hit-in-february-2026",
    "ticker": "will-bitcoin-reach-100k-in-february-2026",
    "question": "↑ 100,000",
    "eventTitle": "What price will Bitcoin hit in February?",
    "prices": "Yes: 5.1% | No: 94.8%",
    "volume": 600862,
    "liquidity": 98095,
    "endDate": "2026-03-01",
    "dayChange": "-1.10%",
    "vol24h": 177453,
    "spread": "0.10%",
    "sortOrder": 6,
    "updatedAt": "2026-02-03T16:01:53.874367Z",
    "engine": "sniper",
    "core_topic": "What price will Bitcoin hit in {month}?",
    "category": "CRYPTO",
    "url": "https://polymarket.com/event/what-price-will-bitcoin-hit-in-february-2026",
    "strategy_tags": [
      "HIGH_CERTAINTY"
    ]
  },
  {
    "slug": "bitcoin-above-on-february-3",
    "ticker": "bitcoin-above-88k-on-february-3",
    "question": "88,000",
    "eventTitle": "Bitcoin above ___ on February 3?",
    "prices": "Yes: 0.1% | No: 100.0%",
    "volume": 515469,
    "liquidity": 99348,
    "endDate": "2026-02-03",
    "dayChange": "-0.55%",
    "vol24h": 339024,
    "spread": "0.10%",
    "sortOrder": 5,
    "updatedAt": "2026-02-03T16:04:45.944804Z",
    "engine": "sniper",
    "core_topic": "Bitcoin above ___ on {date}?",
    "category": "CRYPTO",
    "url": "https://polymarket.com/event/bitcoin-above-on-february-3",
    "strategy_tags": [
      "TAIL_RISK",
      "HIGH_CERTAINTY"
    ]
  },
  {
    "slug": "what-price-will-bitcoin-hit-in-february-2026",
    "ticker": "will-bitcoin-reach-85k-in-february-2026",
    "question": "↑ 85,000",
    "eventTitle": "What price will Bitcoin hit in February?",
    "prices": "Yes: 49.5% | No: 50.5%",
    "volume": 502650,
    "liquidity": 75512,
    "endDate": "2026-03-01",
    "dayChange": "-4.00%",
    "vol24h": 185861,
    "spread": "1.00%",
    "sortOrder": 9,
    "updatedAt": "2026-02-03T16:01:42.359128Z",
    "engine": "sniper",
    "core_topic": "What price will Bitcoin hit in {month}?",
    "category": "CRYPTO",
    "url": "https://polymarket.com/event/what-price-will-bitcoin-hit-in-february-2026",
    "strategy_tags": [
      "RAW_MARKET"
    ]
  },
  {
    "slug": "what-price-will-bitcoin-hit-in-february-2026",
    "ticker": "will-bitcoin-reach-90k-in-february-2026",
    "question": "↑ 90,000",
    "eventTitle": "What price will Bitcoin hit in February?",
    "prices": "Yes: 23.5% | No: 76.5%",
    "volume": 486312,
    "liquidity": 146833,
    "endDate": "2026-03-01",
    "dayChange": "-4.50%",
    "vol24h": 158410,
    "spread": "1.00%",
    "sortOrder": 8,
    "updatedAt": "2026-02-03T16:01:29.94899Z",
    "engine": "sniper",
    "core_topic": "What price will Bitcoin hit in {month}?",
    "category": "CRYPTO",
    "url": "https://polymarket.com/event/what-price-will-bitcoin-hit-in-february-2026",
    "strategy_tags": [
      "RAW_MARKET"
    ]
  },
  {
    "slug": "what-price-will-bitcoin-hit-in-february-2026",
    "ticker": "will-bitcoin-reach-125k-in-february-2026",
    "question": "↑ 125,000",
    "eventTitle": "What price will Bitcoin hit in February?",
    "prices": "Yes: 0.4% | No: 99.6%",
    "volume": 479004,
    "liquidity": 209754,
    "endDate": "2026-03-01",
    "dayChange": "-0.10%",
    "vol24h": 229270,
    "spread": "0.10%",
    "sortOrder": 1,
    "updatedAt": "2026-02-03T16:01:33.545552Z",
    "engine": "sniper",
    "core_topic": "What price will Bitcoin hit in {month}?",
    "category": "CRYPTO",
    "url": "https://polymarket.com/event/what-price-will-bitcoin-hit-in-february-2026",
    "strategy_tags": [
      "TAIL_RISK",
      "HIGH_CERTAINTY"
    ]
  },
  {
    "slug": "what-price-will-bitcoin-hit-in-february-2026",
    "ticker": "will-bitcoin-dip-to-60k-in-february-2026",
    "question": "↓ 60,000",
    "eventTitle": "What price will Bitcoin hit in February?",
    "prices": "Yes: 11.0% | No: 89.0%",
    "volume": 477467,
    "liquidity": 53264,
    "endDate": "2026-03-01",
    "dayChange": "0.50%",
    "vol24h": 115624,
    "spread": "2.00%",
    "sortOrder": 14,
    "updatedAt": "2026-02-03T16:01:46.362563Z",
    "engine": "sniper",
    "core_topic": "What price will Bitcoin hit in {month}?",
    "category": "CRYPTO",
    "url": "https://polymarket.com/event/what-price-will-bitcoin-hit-in-february-2026",
    "strategy_tags": [
      "RAW_MARKET"
    ]
  },
  {
    "slug": "what-price-will-bitcoin-hit-in-february-2026",
    "ticker": "will-bitcoin-reach-95k-in-february-2026",
    "question": "↑ 95,000",
    "eventTitle": "What price will Bitcoin hit in February?",
    "prices": "Yes: 10.5% | No: 89.5%",
    "volume": 428214,
    "liquidity": 93777,
    "endDate": "2026-03-01",
    "dayChange": "-2.00%",
    "vol24h": 115576,
    "spread": "1.00%",
    "sortOrder": 7,
    "updatedAt": "2026-02-03T16:01:57.26803Z",
    "engine": "sniper",
    "core_topic": "What price will Bitcoin hit in {month}?",
    "category": "CRYPTO",
    "url": "https://polymarket.com/event/what-price-will-bitcoin-hit-in-february-2026",
    "strategy_tags": [
      "RAW_MARKET"
    ]
  },
  {
    "slug": "what-price-will-bitcoin-hit-in-february-2026",
    "ticker": "will-bitcoin-dip-to-55k-in-february-2026",
    "question": "↓ 55,000",
    "eventTitle": "What price will Bitcoin hit in February?",
    "prices": "Yes: 4.8% | No: 95.3%",
    "volume": 408550,
    "liquidity": 74356,
    "endDate": "2026-03-01",
    "dayChange": "-1.15%",
    "vol24h": 157298,
    "spread": "0.10%",
    "sortOrder": 15,
    "updatedAt": "2026-02-03T16:01:44.673948Z",
    "engine": "sniper",
    "core_topic": "What price will Bitcoin hit in {month}?",
    "category": "CRYPTO",
    "url": "https://polymarket.com/event/what-price-will-bitcoin-hit-in-february-2026",
    "strategy_tags": [
      "TAIL_RISK",
      "HIGH_CERTAINTY"
    ]
  },
  {
    "slug": "what-will-gold-gc-hit-by-end-of-february",
    "ticker": "will-gold-gc-hit-high-5500-by-end-of-february-743-796-985-593-523-417-437",
    "question": "↑ $5,500",
    "eventTitle": "What will Gold (GC) hit__ by end of February?",
    "prices": "Yes: 35.4% | No: 64.6%",
    "volume": 377925,
    "liquidity": 29325,
    "endDate": "2026-02-28",
    "dayChange": "7.15%",
    "vol24h": 61937,
    "spread": "0.80%",
    "sortOrder": 7,
    "updatedAt": "2026-02-03T16:01:49.389065Z",
    "engine": "sniper",
    "core_topic": "What will Gold (GC) hit__ by end of {month}?",
    "category": "FINANCE",
    "url": "https://polymarket.com/event/what-will-gold-gc-hit-by-end-of-february",
    "strategy_tags": [
      "REFLEXIVITY_TREND",
      "HIGH_CERTAINTY"
    ]
  },
  {
    "slug": "what-price-will-bitcoin-hit-in-february-2026",
    "ticker": "will-bitcoin-reach-110k-in-february-2026",
    "question": "↑ 110,000",
    "eventTitle": "What price will Bitcoin hit in February?",
    "prices": "Yes: 1.4% | No: 98.7%",
    "volume": 369376,
    "liquidity": 158912,
    "endDate": "2026-03-01",
    "dayChange": "-0.85%",
    "vol24h": 96245,
    "spread": "0.10%",
    "sortOrder": 4,
    "updatedAt": "2026-02-03T16:01:38.971269Z",
    "engine": "sniper",
    "core_topic": "What price will Bitcoin hit in {month}?",
    "category": "CRYPTO",
    "url": "https://polymarket.com/event/what-price-will-bitcoin-hit-in-february-2026",
    "strategy_tags": [
      "TAIL_RISK",
      "HIGH_CERTAINTY"
    ]
  },
  {
    "slug": "what-price-will-bitcoin-hit-in-february-2026",
    "ticker": "will-bitcoin-dip-to-50k-in-february-2026",
    "question": "↓ 50,000",
    "eventTitle": "What price will Bitcoin hit in February?",
    "prices": "Yes: 1.8% | No: 98.2%",
    "volume": 360048,
    "liquidity": 101120,
    "endDate": "2026-03-01",
    "dayChange": "-0.40%",
    "vol24h": 92482,
    "spread": "0.10%",
    "sortOrder": 16,
    "updatedAt": "2026-02-03T16:01:46.843307Z",
    "engine": "sniper",
    "core_topic": "What price will Bitcoin hit in {month}?",
    "category": "CRYPTO",
    "url": "https://polymarket.com/event/what-price-will-bitcoin-hit-in-february-2026",
    "strategy_tags": [
      "TAIL_RISK",
      "HIGH_CERTAINTY"
    ]
  },
  {
    "slug": "how-many-fed-rate-cuts-in-2026",
    "ticker": "will-1-fed-rate-cut-happen-in-2026",
    "question": "1 (25 bps)",
    "eventTitle": "How many Fed rate cuts in 2026?",
    "prices": "Yes: 13.0% | No: 87.0%",
    "volume": 350922,
    "liquidity": 60862,
    "endDate": "2026-12-31",
    "dayChange": "0.00%",
    "vol24h": 20954,
    "spread": "2.00%",
    "sortOrder": 1,
    "updatedAt": "2026-02-03T16:01:14.869241Z",
    "engine": "sniper",
    "core_topic": "How many Fed rate cuts in {year}?",
    "category": "ECONOMY",
    "url": "https://polymarket.com/event/how-many-fed-rate-cuts-in-2026",
    "strategy_tags": [
      "RAW_MARKET"
    ]
  },
  {
    "slug": "how-many-fed-rate-cuts-in-2026",
    "ticker": "will-2-fed-rate-cuts-happen-in-2026",
    "question": "2 (50 bps)",
    "eventTitle": "How many Fed rate cuts in 2026?",
    "prices": "Yes: 23.5% | No: 76.5%",
    "volume": 338727,
    "liquidity": 79616,
    "endDate": "2026-12-31",
    "dayChange": "0.00%",
    "vol24h": 465,
    "spread": "1.00%",
    "sortOrder": 2,
    "updatedAt": "2026-02-03T16:01:52.071882Z",
    "engine": "sniper",
    "core_topic": "How many Fed rate cuts in {year}?",
    "category": "ECONOMY",
    "url": "https://polymarket.com/event/how-many-fed-rate-cuts-in-2026",
    "strategy_tags": [
      "RAW_MARKET"
    ]
  },
  {
    "slug": "how-many-fed-rate-cuts-in-2026",
    "ticker": "will-8-fed-rate-cuts-happen-in-2026",
    "question": "8 (200 bps)",
    "eventTitle": "How many Fed rate cuts in 2026?",
    "prices": "Yes: 1.6% | No: 98.4%",
    "volume": 315082,
    "liquidity": 53915,
    "endDate": "2026-12-31",
    "dayChange": "0.00%",
    "vol24h": 492,
    "spread": "0.20%",
    "sortOrder": 8,
    "updatedAt": "2026-02-03T16:01:49.182992Z",
    "engine": "sniper",
    "core_topic": "How many Fed rate cuts in {year}?",
    "category": "ECONOMY",
    "url": "https://polymarket.com/event/how-many-fed-rate-cuts-in-2026",
    "strategy_tags": [
      "TAIL_RISK",
      "HIGH_CERTAINTY"
    ]
  },
  {
    "slug": "what-price-will-bitcoin-hit-in-february-2026",
    "ticker": "will-bitcoin-reach-105k-in-february-2026",
    "question": "↑ 105,000",
    "eventTitle": "What price will Bitcoin hit in February?",
    "prices": "Yes: 2.3% | No: 97.8%",
    "volume": 309439,
    "liquidity": 109575,
    "endDate": "2026-03-01",
    "dayChange": "-0.60%",
    "vol24h": 102222,
    "spread": "0.10%",
    "sortOrder": 5,
    "updatedAt": "2026-02-03T16:01:10.772745Z",
    "engine": "sniper",
    "core_topic": "What price will Bitcoin hit in {month}?",
    "category": "CRYPTO",
    "url": "https://polymarket.com/event/what-price-will-bitcoin-hit-in-february-2026",
    "strategy_tags": [
      "TAIL_RISK",
      "HIGH_CERTAINTY"
    ]
  },
  {
    "slug": "how-many-fed-rate-cuts-in-2026",
    "ticker": "will-12-or-more-fed-rate-cuts-happen-in-2026",
    "question": "12+ (300+ bps)",
    "eventTitle": "How many Fed rate cuts in 2026?",
    "prices": "Yes: 2.1% | No: 98.0%",
    "volume": 294966,
    "liquidity": 48540,
    "endDate": "2026-12-31",
    "dayChange": "0.00%",
    "vol24h": 3001,
    "spread": "0.10%",
    "sortOrder": 12,
    "updatedAt": "2026-02-03T16:02:03.869072Z",
    "engine": "sniper",
    "core_topic": "How many Fed rate cuts in {year}?",
    "category": "ECONOMY",
    "url": "https://polymarket.com/event/how-many-fed-rate-cuts-in-2026",
    "strategy_tags": [
      "TAIL_RISK",
      "HIGH_CERTAINTY"
    ]
  },
  {
    "slug": "how-many-fed-rate-cuts-in-2026",
    "ticker": "will-6-fed-rate-cuts-happen-in-2026",
    "question": "6 (150 bps)",
    "eventTitle": "How many Fed rate cuts in 2026?",
    "prices": "Yes: 3.5% | No: 96.5%",
    "volume": 294464,
    "liquidity": 45220,
    "endDate": "2026-12-31",
    "dayChange": "-0.70%",
    "vol24h": 10587,
    "spread": "0.10%",
    "sortOrder": 6,
    "updatedAt": "2026-02-03T16:01:52.039681Z",
    "engine": "sniper",
    "core_topic": "How many Fed rate cuts in {year}?",
    "category": "ECONOMY",
    "url": "https://polymarket.com/event/how-many-fed-rate-cuts-in-2026",
    "strategy_tags": [
      "TAIL_RISK",
      "HIGH_CERTAINTY"
    ]
  },
  {
    "slug": "how-many-fed-rate-cuts-in-2026",
    "ticker": "will-11-fed-rate-cuts-happen-in-2026",
    "question": "11 (275 bps)",
    "eventTitle": "How many Fed rate cuts in 2026?",
    "prices": "Yes: 0.6% | No: 99.4%",
    "volume": 290860,
    "liquidity": 65965,
    "endDate": "2026-12-31",
    "dayChange": "-0.10%",
    "vol24h": 772,
    "spread": "0.20%",
    "sortOrder": 11,
    "updatedAt": "2026-02-03T16:01:13.125814Z",
    "engine": "sniper",
    "core_topic": "How many Fed rate cuts in {year}?",
    "category": "ECONOMY",
    "url": "https://polymarket.com/event/how-many-fed-rate-cuts-in-2026",
    "strategy_tags": [
      "TAIL_RISK",
      "HIGH_CERTAINTY"
    ]
  },
  {
    "slug": "what-price-will-bitcoin-hit-in-february-2026",
    "ticker": "will-bitcoin-reach-120k-in-february-2026",
    "question": "↑ 120,000",
    "eventTitle": "What price will Bitcoin hit in February?",
    "prices": "Yes: 0.4% | No: 99.6%",
    "volume": 289271,
    "liquidity": 198752,
    "endDate": "2026-03-01",
    "dayChange": "-0.10%",
    "vol24h": 122915,
    "spread": "0.10%",
    "sortOrder": 2,
    "updatedAt": "2026-02-03T16:01:36.962166Z",
    "engine": "sniper",
    "core_topic": "What price will Bitcoin hit in {month}?",
    "category": "CRYPTO",
    "url": "https://polymarket.com/event/what-price-will-bitcoin-hit-in-february-2026",
    "strategy_tags": [
      "TAIL_RISK",
      "HIGH_CERTAINTY"
    ]
  },
  {
    "slug": "what-will-gold-gc-hit-by-end-of-february",
    "ticker": "will-gold-gc-hit-high-10000-by-end-of-february",
    "question": "↑ $10,000",
    "eventTitle": "What will Gold (GC) hit__ by end of February?",
    "prices": "Yes: 0.8% | No: 99.3%",
    "volume": 286052,
    "liquidity": 97078,
    "endDate": "2026-02-28",
    "dayChange": "0.20%",
    "vol24h": 80976,
    "spread": "0.10%",
    "sortOrder": 0,
    "updatedAt": "2026-02-03T16:04:31.413223Z",
    "engine": "sniper",
    "core_topic": "What will Gold (GC) hit__ by end of {month}?",
    "category": "FINANCE",
    "url": "https://polymarket.com/event/what-will-gold-gc-hit-by-end-of-february",
    "strategy_tags": [
      "TAIL_RISK",
      "HIGH_CERTAINTY"
    ]
  },
  {
    "slug": "what-price-will-bitcoin-hit-in-february-2026",
    "ticker": "will-bitcoin-dip-to-65k-in-february-2026",
    "question": "↓ 65,000",
    "eventTitle": "What price will Bitcoin hit in February?",
    "prices": "Yes: 21.5% | No: 78.5%",
    "volume": 272348,
    "liquidity": 163505,
    "endDate": "2026-03-01",
    "dayChange": "2.50%",
    "vol24h": 57481,
    "spread": "1.00%",
    "sortOrder": 13,
    "updatedAt": "2026-02-03T16:01:39.287299Z",
    "engine": "sniper",
    "core_topic": "What price will Bitcoin hit in {month}?",
    "category": "CRYPTO",
    "url": "https://polymarket.com/event/what-price-will-bitcoin-hit-in-february-2026",
    "strategy_tags": [
      "RAW_MARKET"
    ]
  },
  {
    "slug": "what-price-will-bitcoin-hit-in-february-2026",
    "ticker": "will-bitcoin-reach-115k-in-february-2026",
    "question": "↑ 115,000",
    "eventTitle": "What price will Bitcoin hit in February?",
    "prices": "Yes: 0.9% | No: 99.2%",
    "volume": 266097,
    "liquidity": 140246,
    "endDate": "2026-03-01",
    "dayChange": "0.00%",
    "vol24h": 132463,
    "spread": "0.10%",
    "sortOrder": 3,
    "updatedAt": "2026-02-03T16:01:33.771125Z",
    "engine": "sniper",
    "core_topic": "What price will Bitcoin hit in {month}?",
    "category": "CRYPTO",
    "url": "https://polymarket.com/event/what-price-will-bitcoin-hit-in-february-2026",
    "strategy_tags": [
      "TAIL_RISK",
      "HIGH_CERTAINTY"
    ]
  },
  {
    "slug": "how-many-fed-rate-cuts-in-2026",
    "ticker": "will-10-fed-rate-cuts-happen-in-2026",
    "question": "10 (250 bps)",
    "eventTitle": "How many Fed rate cuts in 2026?",
    "prices": "Yes: 0.7% | No: 99.4%",
    "volume": 260850,
    "liquidity": 48536,
    "endDate": "2026-12-31",
    "dayChange": "0.00%",
    "vol24h": 7295,
    "spread": "0.10%",
    "sortOrder": 10,
    "updatedAt": "2026-02-03T16:02:03.951965Z",
    "engine": "sniper",
    "core_topic": "How many Fed rate cuts in {year}?",
    "category": "ECONOMY",
    "url": "https://polymarket.com/event/how-many-fed-rate-cuts-in-2026",
    "strategy_tags": [
      "TAIL_RISK",
      "HIGH_CERTAINTY"
    ]
  },
  {
    "slug": "how-many-fed-rate-cuts-in-2026",
    "ticker": "will-3-fed-rate-cuts-happen-in-2026",
    "question": "3 (75 bps)",
    "eventTitle": "How many Fed rate cuts in 2026?",
    "prices": "Yes: 26.0% | No: 74.0%",
    "volume": 251859,
    "liquidity": 73820,
    "endDate": "2026-12-31",
    "dayChange": "0.50%",
    "vol24h": 5082,
    "spread": "2.00%",
    "sortOrder": 3,
    "updatedAt": "2026-02-03T16:00:55.451093Z",
    "engine": "sniper",
    "core_topic": "How many Fed rate cuts in {year}?",
    "category": "ECONOMY",
    "url": "https://polymarket.com/event/how-many-fed-rate-cuts-in-2026",
    "strategy_tags": [
      "RAW_MARKET"
    ]
  },
  {
    "slug": "what-price-will-bitcoin-hit-in-february-2026",
    "ticker": "will-bitcoin-dip-to-35k-in-february-2026",
    "question": "↓ 35,000",
    "eventTitle": "What price will Bitcoin hit in February?",
    "prices": "Yes: 0.5% | No: 99.5%",
    "volume": 249132,
    "liquidity": 117382,
    "endDate": "2026-03-01",
    "dayChange": "0.10%",
    "vol24h": 116676,
    "spread": "0.30%",
    "sortOrder": 19,
    "updatedAt": "2026-02-03T16:01:37.065732Z",
    "engine": "sniper",
    "core_topic": "What price will Bitcoin hit in {month}?",
    "category": "CRYPTO",
    "url": "https://polymarket.com/event/what-price-will-bitcoin-hit-in-february-2026",
    "strategy_tags": [
      "TAIL_RISK",
      "HIGH_CERTAINTY"
    ]
  },
  {
    "slug": "how-many-fed-rate-cuts-in-2026",
    "ticker": "will-7-fed-rate-cuts-happen-in-2026",
    "question": "7 (175 bps)",
    "eventTitle": "How many Fed rate cuts in 2026?",
    "prices": "Yes: 1.8% | No: 98.2%",
    "volume": 241291,
    "liquidity": 59007,
    "endDate": "2026-12-31",
    "dayChange": "-0.20%",
    "vol24h": 8176,
    "spread": "0.10%",
    "sortOrder": 7,
    "updatedAt": "2026-02-03T16:01:07.589869Z",
    "engine": "sniper",
    "core_topic": "How many Fed rate cuts in {year}?",
    "category": "ECONOMY",
    "url": "https://polymarket.com/event/how-many-fed-rate-cuts-in-2026",
    "strategy_tags": [
      "TAIL_RISK",
      "HIGH_CERTAINTY"
    ]
  },
  {
    "slug": "how-many-fed-rate-cuts-in-2026",
    "ticker": "will-9-fed-rate-cuts-happen-in-2026",
    "question": "9 (225 bps)",
    "eventTitle": "How many Fed rate cuts in 2026?",
    "prices": "Yes: 0.8% | No: 99.3%",
    "volume": 240122,
    "liquidity": 49216,
    "endDate": "2026-12-31",
    "dayChange": "0.00%",
    "vol24h": 496,
    "spread": "0.10%",
    "sortOrder": 9,
    "updatedAt": "2026-02-03T16:01:44.777014Z",
    "engine": "sniper",
    "core_topic": "How many Fed rate cuts in {year}?",
    "category": "ECONOMY",
    "url": "https://polymarket.com/event/how-many-fed-rate-cuts-in-2026",
    "strategy_tags": [
      "TAIL_RISK",
      "HIGH_CERTAINTY"
    ]
  },
  {
    "slug": "how-many-fed-rate-cuts-in-2026",
    "ticker": "will-5-fed-rate-cuts-happen-in-2026",
    "question": "5 (125 bps)",
    "eventTitle": "How many Fed rate cuts in 2026?",
    "prices": "Yes: 5.5% | No: 94.5%",
    "volume": 234186,
    "liquidity": 81785,
    "endDate": "2026-12-31",
    "dayChange": "-0.50%",
    "vol24h": 759,
    "spread": "1.00%",
    "sortOrder": 5,
    "updatedAt": "2026-02-03T16:01:53.011696Z",
    "engine": "sniper",
    "core_topic": "How many Fed rate cuts in {year}?",
    "category": "ECONOMY",
    "url": "https://polymarket.com/event/how-many-fed-rate-cuts-in-2026",
    "strategy_tags": [
      "RAW_MARKET"
    ]
  },
  {
    "slug": "what-price-will-bitcoin-hit-in-february-2026",
    "ticker": "will-bitcoin-dip-to-45k-in-february-2026",
    "question": "↓ 45,000",
    "eventTitle": "What price will Bitcoin hit in February?",
    "prices": "Yes: 1.1% | No: 98.9%",
    "volume": 224693,
    "liquidity": 82910,
    "endDate": "2026-03-01",
    "dayChange": "-0.35%",
    "vol24h": 47702,
    "spread": "0.10%",
    "sortOrder": 17,
    "updatedAt": "2026-02-03T16:01:36.710554Z",
    "engine": "sniper",
    "core_topic": "What price will Bitcoin hit in {month}?",
    "category": "CRYPTO",
    "url": "https://polymarket.com/event/what-price-will-bitcoin-hit-in-february-2026",
    "strategy_tags": [
      "TAIL_RISK",
      "HIGH_CERTAINTY"
    ]
  },
  {
    "slug": "how-many-fed-rate-cuts-in-2026",
    "ticker": "will-4-fed-rate-cuts-happen-in-2026",
    "question": "4 (100 bps)",
    "eventTitle": "How many Fed rate cuts in 2026?",
    "prices": "Yes: 15.0% | No: 85.0%",
    "volume": 222002,
    "liquidity": 81984,
    "endDate": "2026-12-31",
    "dayChange": "-1.50%",
    "vol24h": 1397,
    "spread": "2.00%",
    "sortOrder": 4,
    "updatedAt": "2026-02-03T16:01:26.493968Z",
    "engine": "sniper",
    "core_topic": "How many Fed rate cuts in {year}?",
    "category": "ECONOMY",
    "url": "https://polymarket.com/event/how-many-fed-rate-cuts-in-2026",
    "strategy_tags": [
      "RAW_MARKET"
    ]
  },
  {
    "slug": "bitcoin-all-time-high-by",
    "ticker": "bitcoin-all-time-high-by-december-31-2026",
    "question": "December 31, 2026",
    "eventTitle": "Bitcoin all time high by ___?",
    "prices": "Yes: 29.0% | No: 71.0%",
    "volume": 219596,
    "liquidity": 30481,
    "endDate": "2027-01-01",
    "dayChange": "-5.00%",
    "vol24h": 3551,
    "spread": "2.00%",
    "sortOrder": 3,
    "updatedAt": "2026-02-03T16:01:51.07386Z",
    "engine": "sniper",
    "core_topic": "Bitcoin all time high by ___?",
    "category": "CRYPTO",
    "url": "https://polymarket.com/event/bitcoin-all-time-high-by",
    "strategy_tags": [
      "RAW_MARKET"
    ]
  },
  {
    "slug": "bitcoin-above-on-february-3",
    "ticker": "bitcoin-above-98k-on-february-3",
    "question": "98,000",
    "eventTitle": "Bitcoin above ___ on February 3?",
    "prices": "Yes: 0.1% | No: 100.0%",
    "volume": 198932,
    "liquidity": 114274,
    "endDate": "2026-02-03",
    "dayChange": "0.00%",
    "vol24h": 5000,
    "spread": "0.10%",
    "sortOrder": 10,
    "updatedAt": "2026-02-03T16:04:44.233267Z",
    "engine": "sniper",
    "core_topic": "Bitcoin above ___ on {date}?",
    "category": "CRYPTO",
    "url": "https://polymarket.com/event/bitcoin-above-on-february-3",
    "strategy_tags": [
      "TAIL_RISK",
      "HIGH_CERTAINTY"
    ]
  },
  {
    "slug": "bitcoin-price-on-february-3",
    "ticker": "will-the-price-of-bitcoin-be-less-than-80000-on-february-3",
    "question": "<80,000",
    "eventTitle": "Bitcoin price on February 3?",
    "prices": "Yes: 98.8% | No: 1.3%",
    "volume": 191158,
    "liquidity": 12462,
    "endDate": "2026-02-03",
    "dayChange": "31.15%",
    "vol24h": 62928,
    "spread": "0.50%",
    "sortOrder": 0,
    "updatedAt": "2026-02-03T16:01:55.763827Z",
    "engine": "sniper",
    "core_topic": "Bitcoin price on {date}?",
    "category": "CRYPTO",
    "url": "https://polymarket.com/event/bitcoin-price-on-february-3",
    "strategy_tags": [
      "TAIL_RISK",
      "REFLEXIVITY_TREND",
      "HIGH_CERTAINTY"
    ]
  },
  {
    "slug": "bitcoin-all-time-high-by",
    "ticker": "bitcoin-all-time-high-by-june-30-2026",
    "question": "June 30, 2026",
    "eventTitle": "Bitcoin all time high by ___?",
    "prices": "Yes: 12.0% | No: 88.0%",
    "volume": 186563,
    "liquidity": 21341,
    "endDate": "2026-07-01",
    "dayChange": "-2.00%",
    "vol24h": 7999,
    "spread": "2.00%",
    "sortOrder": 1,
    "updatedAt": "2026-02-03T16:01:33.199505Z",
    "engine": "sniper",
    "core_topic": "Bitcoin all time high by ___?",
    "category": "CRYPTO",
    "url": "https://polymarket.com/event/bitcoin-all-time-high-by",
    "strategy_tags": [
      "RAW_MARKET"
    ]
  },
  {
    "slug": "bitcoin-above-on-february-4",
    "ticker": "bitcoin-above-80k-on-february-4",
    "question": "80,000",
    "eventTitle": "Bitcoin above ___ on February 4?",
    "prices": "Yes: 19.0% | No: 81.0%",
    "volume": 185738,
    "liquidity": 17703,
    "endDate": "2026-02-04",
    "dayChange": "-16.15%",
    "vol24h": 64791,
    "spread": "2.00%",
    "sortOrder": 0,
    "updatedAt": "2026-02-03T16:02:04.403882Z",
    "engine": "sniper",
    "core_topic": "Bitcoin above ___ on {date}?",
    "category": "CRYPTO",
    "url": "https://polymarket.com/event/bitcoin-above-on-february-4",
    "strategy_tags": [
      "REFLEXIVITY_TREND"
    ]
  },
  {
    "slug": "bitcoin-price-on-february-3",
    "ticker": "will-the-price-of-bitcoin-be-between-84000-86000-on-february-3",
    "question": "84,000-86,000",
    "eventTitle": "Bitcoin price on February 3?",
    "prices": "Yes: 0.1% | No: 100.0%",
    "volume": 178198,
    "liquidity": 37009,
    "endDate": "2026-02-03",
    "dayChange": "-2.95%",
    "vol24h": 65403,
    "spread": "0.10%",
    "sortOrder": 3,
    "updatedAt": "2026-02-03T16:01:58.709044Z",
    "engine": "sniper",
    "core_topic": "Bitcoin price on {date}?",
    "category": "CRYPTO",
    "url": "https://polymarket.com/event/bitcoin-price-on-february-3",
    "strategy_tags": [
      "TAIL_RISK",
      "HIGH_CERTAINTY"
    ]
  },
  {
    "slug": "bitcoin-price-on-february-3",
    "ticker": "will-the-price-of-bitcoin-be-between-86000-88000-on-february-3",
    "question": "86,000-88,000",
    "eventTitle": "Bitcoin price on February 3?",
    "prices": "Yes: 0.1% | No: 100.0%",
    "volume": 174567,
    "liquidity": 106274,
    "endDate": "2026-02-03",
    "dayChange": "-1.15%",
    "vol24h": 129825,
    "spread": "0.10%",
    "sortOrder": 4,
    "updatedAt": "2026-02-03T16:01:46.834896Z",
    "engine": "sniper",
    "core_topic": "Bitcoin price on {date}?",
    "category": "CRYPTO",
    "url": "https://polymarket.com/event/bitcoin-price-on-february-3",
    "strategy_tags": [
      "TAIL_RISK",
      "HIGH_CERTAINTY"
    ]
  },
  {
    "slug": "what-price-will-bitcoin-hit-in-february-2026",
    "ticker": "will-bitcoin-dip-to-40k-in-february-2026",
    "question": "↓ 40,000",
    "eventTitle": "What price will Bitcoin hit in February?",
    "prices": "Yes: 0.9% | No: 99.1%",
    "volume": 152890,
    "liquidity": 86275,
    "endDate": "2026-03-01",
    "dayChange": "-0.05%",
    "vol24h": 42618,
    "spread": "0.10%",
    "sortOrder": 18,
    "updatedAt": "2026-02-03T16:01:32.053187Z",
    "engine": "sniper",
    "core_topic": "What price will Bitcoin hit in {month}?",
    "category": "CRYPTO",
    "url": "https://polymarket.com/event/what-price-will-bitcoin-hit-in-february-2026",
    "strategy_tags": [
      "TAIL_RISK",
      "HIGH_CERTAINTY"
    ]
  },
  {
    "slug": "what-will-gold-gc-hit-by-end-of-february",
    "ticker": "will-gold-gc-hit-low-3000-by-end-of-february-957-911-432-757-792-499",
    "question": "↓ $3,000",
    "eventTitle": "What will Gold (GC) hit__ by end of February?",
    "prices": "Yes: 1.1% | No: 99.0%",
    "volume": 151615,
    "liquidity": 69530,
    "endDate": "2026-02-28",
    "dayChange": "-1.65%",
    "vol24h": 61530,
    "spread": "0.10%",
    "sortOrder": 19,
    "updatedAt": "2026-02-03T16:04:35.708443Z",
    "engine": "sniper",
    "core_topic": "What will Gold (GC) hit__ by end of {month}?",
    "category": "FINANCE",
    "url": "https://polymarket.com/event/what-will-gold-gc-hit-by-end-of-february",
    "strategy_tags": [
      "TAIL_RISK",
      "HIGH_CERTAINTY"
    ]
  },
  {
    "slug": "bitcoin-above-on-february-3",
    "ticker": "bitcoin-above-92k-on-february-3",
    "question": "92,000",
    "eventTitle": "Bitcoin above ___ on February 3?",
    "prices": "Yes: 0.1% | No: 100.0%",
    "volume": 144119,
    "liquidity": 102665,
    "endDate": "2026-02-03",
    "dayChange": "-0.10%",
    "vol24h": 107158,
    "spread": "0.10%",
    "sortOrder": 7,
    "updatedAt": "2026-02-03T16:04:59.664965Z",
    "engine": "sniper",
    "core_topic": "Bitcoin above ___ on {date}?",
    "category": "CRYPTO",
    "url": "https://polymarket.com/event/bitcoin-above-on-february-3",
    "strategy_tags": [
      "TAIL_RISK",
      "HIGH_CERTAINTY"
    ]
  },
  {
    "slug": "what-will-gold-gc-hit-by-end-of-february",
    "ticker": "will-gold-gc-hit-high-6400-by-end-of-february-581-221-834-595-555",
    "question": "↑ $6,400",
    "eventTitle": "What will Gold (GC) hit__ by end of February?",
    "prices": "Yes: 4.0% | No: 96.0%",
    "volume": 138207,
    "liquidity": 44887,
    "endDate": "2026-02-28",
    "dayChange": "0.75%",
    "vol24h": 28993,
    "spread": "0.10%",
    "sortOrder": 3,
    "updatedAt": "2026-02-03T16:04:37.183671Z",
    "engine": "sniper",
    "core_topic": "What will Gold (GC) hit__ by end of {month}?",
    "category": "FINANCE",
    "url": "https://polymarket.com/event/what-will-gold-gc-hit-by-end-of-february",
    "strategy_tags": [
      "TAIL_RISK",
      "HIGH_CERTAINTY"
    ]
  },
  {
    "slug": "what-will-gold-gc-hit-by-end-of-february",
    "ticker": "will-gold-gc-hit-high-6000-by-end-of-february-957-635-788-121-773-745-586",
    "question": "↑ $6,000",
    "eventTitle": "What will Gold (GC) hit__ by end of February?",
    "prices": "Yes: 9.5% | No: 90.5%",
    "volume": 130821,
    "liquidity": 111627,
    "endDate": "2026-02-28",
    "dayChange": "0.50%",
    "vol24h": 28859,
    "spread": "1.00%",
    "sortOrder": 5,
    "updatedAt": "2026-02-03T16:04:38.946919Z",
    "engine": "sniper",
    "core_topic": "What will Gold (GC) hit__ by end of {month}?",
    "category": "FINANCE",
    "url": "https://polymarket.com/event/what-will-gold-gc-hit-by-end-of-february",
    "strategy_tags": [
      "RAW_MARKET"
    ]
  },
  {
    "slug": "bitcoin-above-on-february-4",
    "ticker": "bitcoin-above-82k-on-february-4",
    "question": "82,000",
    "eventTitle": "Bitcoin above ___ on February 4?",
    "prices": "Yes: 4.9% | No: 95.2%",
    "volume": 126596,
    "liquidity": 17345,
    "endDate": "2026-02-04",
    "dayChange": "-12.25%",
    "vol24h": 41981,
    "spread": "0.70%",
    "sortOrder": 1,
    "updatedAt": "2026-02-03T16:01:30.221163Z",
    "engine": "sniper",
    "core_topic": "Bitcoin above ___ on {date}?",
    "category": "CRYPTO",
    "url": "https://polymarket.com/event/bitcoin-above-on-february-4",
    "strategy_tags": [
      "TAIL_RISK",
      "REFLEXIVITY_TREND",
      "HIGH_CERTAINTY"
    ]
  },
  {
    "slug": "what-will-gold-gc-hit-by-end-of-february",
    "ticker": "will-gold-gc-hit-high-7000-by-end-of-february-271-168-354-381-713",
    "question": "↑ $7,000",
    "eventTitle": "What will Gold (GC) hit__ by end of February?",
    "prices": "Yes: 1.3% | No: 98.8%",
    "volume": 120224,
    "liquidity": 77816,
    "endDate": "2026-02-28",
    "dayChange": "-0.65%",
    "vol24h": 37813,
    "spread": "0.10%",
    "sortOrder": 1,
    "updatedAt": "2026-02-03T16:04:35.71067Z",
    "engine": "sniper",
    "core_topic": "What will Gold (GC) hit__ by end of {month}?",
    "category": "FINANCE",
    "url": "https://polymarket.com/event/what-will-gold-gc-hit-by-end-of-february",
    "strategy_tags": [
      "TAIL_RISK",
      "HIGH_CERTAINTY"
    ]
  },
  {
    "slug": "bitcoin-above-on-february-5",
    "ticker": "bitcoin-above-80k-on-february-5",
    "question": "80,000",
    "eventTitle": "Bitcoin above ___ on February 5?",
    "prices": "Yes: 26.5% | No: 73.5%",
    "volume": 116258,
    "liquidity": 15626,
    "endDate": "2026-02-05",
    "dayChange": "-13.00%",
    "vol24h": 38719,
    "spread": "3.00%",
    "sortOrder": 2,
    "updatedAt": "2026-02-03T16:01:44.57985Z",
    "engine": "sniper",
    "core_topic": "Bitcoin above ___ on {date}?",
    "category": "CRYPTO",
    "url": "https://polymarket.com/event/bitcoin-above-on-february-5",
    "strategy_tags": [
      "REFLEXIVITY_TREND"
    ]
  },
  {
    "slug": "bitcoin-price-on-february-3",
    "ticker": "will-the-price-of-bitcoin-be-between-80000-82000-on-february-3",
    "question": "80,000-82,000",
    "eventTitle": "Bitcoin price on February 3?",
    "prices": "Yes: 1.3% | No: 98.8%",
    "volume": 109469,
    "liquidity": 14290,
    "endDate": "2026-02-03",
    "dayChange": "-19.85%",
    "vol24h": 46352,
    "spread": "1.50%",
    "sortOrder": 1,
    "updatedAt": "2026-02-03T16:01:29.276018Z",
    "engine": "sniper",
    "core_topic": "Bitcoin price on {date}?",
    "category": "CRYPTO",
    "url": "https://polymarket.com/event/bitcoin-price-on-february-3",
    "strategy_tags": [
      "TAIL_RISK",
      "REFLEXIVITY_TREND"
    ]
  },
  {
    "slug": "bitcoin-above-on-february-4",
    "ticker": "bitcoin-above-92k-on-february-4",
    "question": "92,000",
    "eventTitle": "Bitcoin above ___ on February 4?",
    "prices": "Yes: 0.1% | No: 99.9%",
    "volume": 107456,
    "liquidity": 30401,
    "endDate": "2026-02-04",
    "dayChange": "-0.40%",
    "vol24h": 87209,
    "spread": "0.20%",
    "sortOrder": 6,
    "updatedAt": "2026-02-03T16:02:02.837963Z",
    "engine": "sniper",
    "core_topic": "Bitcoin above ___ on {date}?",
    "category": "CRYPTO",
    "url": "https://polymarket.com/event/bitcoin-above-on-february-4",
    "strategy_tags": [
      "TAIL_RISK",
      "HIGH_CERTAINTY"
    ]
  },
  {
    "slug": "bitcoin-above-on-february-4",
    "ticker": "bitcoin-above-94k-on-february-4",
    "question": "94,000",
    "eventTitle": "Bitcoin above ___ on February 4?",
    "prices": "Yes: 0.1% | No: 100.0%",
    "volume": 96991,
    "liquidity": 49831,
    "endDate": "2026-02-04",
    "dayChange": "-0.25%",
    "vol24h": 86956,
    "spread": "0.10%",
    "sortOrder": 7,
    "updatedAt": "2026-02-03T16:02:02.075539Z",
    "engine": "sniper",
    "core_topic": "Bitcoin above ___ on {date}?",
    "category": "CRYPTO",
    "url": "https://polymarket.com/event/bitcoin-above-on-february-4",
    "strategy_tags": [
      "TAIL_RISK",
      "HIGH_CERTAINTY"
    ]
  },
  {
    "slug": "bitcoin-all-time-high-by",
    "ticker": "bitcoin-all-time-high-by-september-30-2026",
    "question": "September 30, 2026",
    "eventTitle": "Bitcoin all time high by ___?",
    "prices": "Yes: 17.0% | No: 83.0%",
    "volume": 95571,
    "liquidity": 19027,
    "endDate": "2026-10-01",
    "dayChange": "-1.50%",
    "vol24h": 1170,
    "spread": "2.00%",
    "sortOrder": 2,
    "updatedAt": "2026-02-03T16:01:26.078055Z",
    "engine": "sniper",
    "core_topic": "Bitcoin all time high by ___?",
    "category": "CRYPTO",
    "url": "https://polymarket.com/event/bitcoin-all-time-high-by",
    "strategy_tags": [
      "RAW_MARKET"
    ]
  },
  {
    "slug": "what-will-gold-gc-hit-by-end-of-february",
    "ticker": "will-gold-gc-hit-low-4600-by-end-of-february-292-259-212-256-398-758-656-625",
    "question": "↓ $4,600",
    "eventTitle": "What will Gold (GC) hit__ by end of February?",
    "prices": "Yes: 50.4% | No: 49.6%",
    "volume": 94023,
    "liquidity": 5599,
    "endDate": "2026-02-28",
    "dayChange": "-33.65%",
    "vol24h": 24294,
    "spread": "0.80%",
    "sortOrder": 14,
    "updatedAt": "2026-02-03T16:02:04.839256Z",
    "engine": "sniper",
    "core_topic": "What will Gold (GC) hit__ by end of {month}?",
    "category": "FINANCE",
    "url": "https://polymarket.com/event/what-will-gold-gc-hit-by-end-of-february",
    "strategy_tags": [
      "REFLEXIVITY_TREND",
      "HIGH_CERTAINTY"
    ]
  },
  {
    "slug": "what-will-gold-gc-hit-by-end-of-february",
    "ticker": "will-gold-gc-hit-high-5800-by-end-of-february-759-378-429-713-662-579",
    "question": "↑ $5,800",
    "eventTitle": "What will Gold (GC) hit__ by end of February?",
    "prices": "Yes: 14.5% | No: 85.5%",
    "volume": 88515,
    "liquidity": 46354,
    "endDate": "2026-02-28",
    "dayChange": "5.00%",
    "vol24h": 18991,
    "spread": "1.00%",
    "sortOrder": 6,
    "updatedAt": "2026-02-03T16:01:47.637035Z",
    "engine": "sniper",
    "core_topic": "What will Gold (GC) hit__ by end of {month}?",
    "category": "FINANCE",
    "url": "https://polymarket.com/event/what-will-gold-gc-hit-by-end-of-february",
    "strategy_tags": [
      "RAW_MARKET"
    ]
  },
  {
    "slug": "bitcoin-above-on-february-3",
    "ticker": "bitcoin-above-94k-on-february-3",
    "question": "94,000",
    "eventTitle": "Bitcoin above ___ on February 3?",
    "prices": "Yes: 0.1% | No: 100.0%",
    "volume": 85701,
    "liquidity": 96732,
    "endDate": "2026-02-03",
    "dayChange": "0.00%",
    "vol24h": 31640,
    "spread": "0.10%",
    "sortOrder": 8,
    "updatedAt": "2026-02-03T16:04:53.433527Z",
    "engine": "sniper",
    "core_topic": "Bitcoin above ___ on {date}?",
    "category": "CRYPTO",
    "url": "https://polymarket.com/event/bitcoin-above-on-february-3",
    "strategy_tags": [
      "TAIL_RISK",
      "HIGH_CERTAINTY"
    ]
  },
  {
    "slug": "bitcoin-above-on-february-4",
    "ticker": "bitcoin-above-84k-on-february-4",
    "question": "84,000",
    "eventTitle": "Bitcoin above ___ on February 4?",
    "prices": "Yes: 1.6% | No: 98.4%",
    "volume": 85267,
    "liquidity": 21478,
    "endDate": "2026-02-04",
    "dayChange": "-5.65%",
    "vol24h": 35882,
    "spread": "0.20%",
    "sortOrder": 2,
    "updatedAt": "2026-02-03T16:01:57.277209Z",
    "engine": "sniper",
    "core_topic": "Bitcoin above ___ on {date}?",
    "category": "CRYPTO",
    "url": "https://polymarket.com/event/bitcoin-above-on-february-4",
    "strategy_tags": [
      "TAIL_RISK",
      "REFLEXIVITY_TREND",
      "HIGH_CERTAINTY"
    ]
  },
  {
    "slug": "bitcoin-above-on-february-4",
    "ticker": "bitcoin-above-90k-on-february-4",
    "question": "90,000",
    "eventTitle": "Bitcoin above ___ on February 4?",
    "prices": "Yes: 0.1% | No: 99.9%",
    "volume": 84013,
    "liquidity": 44782,
    "endDate": "2026-02-04",
    "dayChange": "-0.70%",
    "vol24h": 14064,
    "spread": "0.10%",
    "sortOrder": 5,
    "updatedAt": "2026-02-03T16:01:26.107834Z",
    "engine": "sniper",
    "core_topic": "Bitcoin above ___ on {date}?",
    "category": "CRYPTO",
    "url": "https://polymarket.com/event/bitcoin-above-on-february-4",
    "strategy_tags": [
      "TAIL_RISK",
      "HIGH_CERTAINTY"
    ]
  },
  {
    "slug": "bitcoin-above-on-february-5",
    "ticker": "bitcoin-above-96k-on-february-5",
    "question": "96,000",
    "eventTitle": "Bitcoin above ___ on February 5?",
    "prices": "Yes: 0.2% | No: 99.8%",
    "volume": 81392,
    "liquidity": 18416,
    "endDate": "2026-02-05",
    "dayChange": "-0.10%",
    "vol24h": 74570,
    "spread": "0.20%",
    "sortOrder": 10,
    "updatedAt": "2026-02-03T16:01:53.844282Z",
    "engine": "sniper",
    "core_topic": "Bitcoin above ___ on {date}?",
    "category": "CRYPTO",
    "url": "https://polymarket.com/event/bitcoin-above-on-february-5",
    "strategy_tags": [
      "TAIL_RISK",
      "HIGH_CERTAINTY"
    ]
  },
  {
    "slug": "bitcoin-price-on-february-3",
    "ticker": "will-the-price-of-bitcoin-be-between-88000-90000-on-february-3",
    "question": "88,000-90,000",
    "eventTitle": "Bitcoin price on February 3?",
    "prices": "Yes: 0.1% | No: 100.0%",
    "volume": 81056,
    "liquidity": 79035,
    "endDate": "2026-02-03",
    "dayChange": "-0.60%",
    "vol24h": 56222,
    "spread": "0.10%",
    "sortOrder": 5,
    "updatedAt": "2026-02-03T16:01:40.915605Z",
    "engine": "sniper",
    "core_topic": "Bitcoin price on {date}?",
    "category": "CRYPTO",
    "url": "https://polymarket.com/event/bitcoin-price-on-february-3",
    "strategy_tags": [
      "TAIL_RISK",
      "HIGH_CERTAINTY"
    ]
  },
  {
    "slug": "bitcoin-price-on-february-3",
    "ticker": "will-the-price-of-bitcoin-be-between-82000-84000-on-february-3",
    "question": "82,000-84,000",
    "eventTitle": "Bitcoin price on February 3?",
    "prices": "Yes: 0.2% | No: 99.8%",
    "volume": 80812,
    "liquidity": 31756,
    "endDate": "2026-02-03",
    "dayChange": "-8.35%",
    "vol24h": 35119,
    "spread": "0.20%",
    "sortOrder": 2,
    "updatedAt": "2026-02-03T16:01:57.241468Z",
    "engine": "sniper",
    "core_topic": "Bitcoin price on {date}?",
    "category": "CRYPTO",
    "url": "https://polymarket.com/event/bitcoin-price-on-february-3",
    "strategy_tags": [
      "TAIL_RISK",
      "REFLEXIVITY_TREND",
      "HIGH_CERTAINTY"
    ]
  },
  {
    "slug": "bitcoin-price-on-february-3",
    "ticker": "will-the-price-of-bitcoin-be-between-90000-92000-on-february-3",
    "question": "90,000-92,000",
    "eventTitle": "Bitcoin price on February 3?",
    "prices": "Yes: 0.1% | No: 100.0%",
    "volume": 71028,
    "liquidity": 102528,
    "endDate": "2026-02-03",
    "dayChange": "0.00%",
    "vol24h": 56350,
    "spread": "0.10%",
    "sortOrder": 6,
    "updatedAt": "2026-02-03T16:01:59.039035Z",
    "engine": "sniper",
    "core_topic": "Bitcoin price on {date}?",
    "category": "CRYPTO",
    "url": "https://polymarket.com/event/bitcoin-price-on-february-3",
    "strategy_tags": [
      "TAIL_RISK",
      "HIGH_CERTAINTY"
    ]
  },
  {
    "slug": "bitcoin-above-on-february-5",
    "ticker": "bitcoin-above-84k-on-february-5",
    "question": "84,000",
    "eventTitle": "Bitcoin above ___ on February 5?",
    "prices": "Yes: 2.0% | No: 98.0%",
    "volume": 68362,
    "liquidity": 19310,
    "endDate": "2026-02-05",
    "dayChange": "-8.90%",
    "vol24h": 11806,
    "spread": "0.40%",
    "sortOrder": 4,
    "updatedAt": "2026-02-03T16:01:31.750847Z",
    "engine": "sniper",
    "core_topic": "Bitcoin above ___ on {date}?",
    "category": "CRYPTO",
    "url": "https://polymarket.com/event/bitcoin-above-on-february-5",
    "strategy_tags": [
      "TAIL_RISK",
      "REFLEXIVITY_TREND",
      "HIGH_CERTAINTY"
    ]
  },
  {
    "slug": "bitcoin-price-on-february-4",
    "ticker": "will-the-price-of-bitcoin-be-less-than-80000-on-february-4",
    "question": "<80,000",
    "eventTitle": "Bitcoin price on February 4?",
    "prices": "Yes: 82.0% | No: 18.0%",
    "volume": 66392,
    "liquidity": 9867,
    "endDate": "2026-02-04",
    "dayChange": "18.60%",
    "vol24h": 28540,
    "spread": "2.20%",
    "sortOrder": 0,
    "updatedAt": "2026-02-03T16:04:50.698886Z",
    "engine": "sniper",
    "core_topic": "Bitcoin price on {date}?",
    "category": "CRYPTO",
    "url": "https://polymarket.com/event/bitcoin-price-on-february-4",
    "strategy_tags": [
      "REFLEXIVITY_TREND"
    ]
  },
  {
    "slug": "what-will-gold-gc-hit-by-end-of-february",
    "ticker": "will-gold-gc-hit-high-6600-by-end-of-february-828-163-164-179-126-514",
    "question": "↑ $6,600",
    "eventTitle": "What will Gold (GC) hit__ by end of February?",
    "prices": "Yes: 2.7% | No: 97.3%",
    "volume": 65903,
    "liquidity": 48141,
    "endDate": "2026-02-28",
    "dayChange": "-0.05%",
    "vol24h": 15878,
    "spread": "0.40%",
    "sortOrder": 2,
    "updatedAt": "2026-02-03T16:01:51.675376Z",
    "engine": "sniper",
    "core_topic": "What will Gold (GC) hit__ by end of {month}?",
    "category": "FINANCE",
    "url": "https://polymarket.com/event/what-will-gold-gc-hit-by-end-of-february",
    "strategy_tags": [
      "TAIL_RISK",
      "HIGH_CERTAINTY"
    ]
  },
  {
    "slug": "bitcoin-above-on-february-4",
    "ticker": "bitcoin-above-86k-on-february-4",
    "question": "86,000",
    "eventTitle": "Bitcoin above ___ on February 4?",
    "prices": "Yes: 0.4% | No: 99.7%",
    "volume": 65883,
    "liquidity": 24529,
    "endDate": "2026-02-04",
    "dayChange": "-2.95%",
    "vol24h": 10843,
    "spread": "0.30%",
    "sortOrder": 3,
    "updatedAt": "2026-02-03T16:01:39.196405Z",
    "engine": "sniper",
    "core_topic": "Bitcoin above ___ on {date}?",
    "category": "CRYPTO",
    "url": "https://polymarket.com/event/bitcoin-above-on-february-4",
    "strategy_tags": [
      "TAIL_RISK",
      "HIGH_CERTAINTY"
    ]
  },
  {
    "slug": "bitcoin-above-on-february-3",
    "ticker": "bitcoin-above-96k-on-february-3",
    "question": "96,000",
    "eventTitle": "Bitcoin above ___ on February 3?",
    "prices": "Yes: 0.1% | No: 100.0%",
    "volume": 62574,
    "liquidity": 88901,
    "endDate": "2026-02-03",
    "dayChange": "0.00%",
    "vol24h": 0,
    "spread": "0.10%",
    "sortOrder": 9,
    "updatedAt": "2026-02-03T16:04:50.573846Z",
    "engine": "sniper",
    "core_topic": "Bitcoin above ___ on {date}?",
    "category": "CRYPTO",
    "url": "https://polymarket.com/event/bitcoin-above-on-february-3",
    "strategy_tags": [
      "TAIL_RISK",
      "HIGH_CERTAINTY"
    ]
  },
  {
    "slug": "bitcoin-above-on-february-5",
    "ticker": "bitcoin-above-78k-on-february-5",
    "question": "78,000",
    "eventTitle": "Bitcoin above ___ on February 5?",
    "prices": "Yes: 51.5% | No: 48.5%",
    "volume": 57407,
    "liquidity": 16578,
    "endDate": "2026-02-05",
    "dayChange": "-8.00%",
    "vol24h": 11089,
    "spread": "1.00%",
    "sortOrder": 1,
    "updatedAt": "2026-02-03T16:01:56.429441Z",
    "engine": "sniper",
    "core_topic": "Bitcoin above ___ on {date}?",
    "category": "CRYPTO",
    "url": "https://polymarket.com/event/bitcoin-above-on-february-5",
    "strategy_tags": [
      "REFLEXIVITY_TREND"
    ]
  },
  {
    "slug": "what-will-gold-gc-hit-by-end-of-february",
    "ticker": "will-gold-gc-hit-low-4450-by-end-of-february-844-276-171-389-959-616-957-814",
    "question": "↓ $4,450",
    "eventTitle": "What will Gold (GC) hit__ by end of February?",
    "prices": "Yes: 31.0% | No: 69.0%",
    "volume": 56548,
    "liquidity": 9807,
    "endDate": "2026-02-28",
    "dayChange": "-22.00%",
    "vol24h": 14273,
    "spread": "2.00%",
    "sortOrder": 15,
    "updatedAt": "2026-02-03T16:04:37.779096Z",
    "engine": "sniper",
    "core_topic": "What will Gold (GC) hit__ by end of {month}?",
    "category": "FINANCE",
    "url": "https://polymarket.com/event/what-will-gold-gc-hit-by-end-of-february",
    "strategy_tags": [
      "REFLEXIVITY_TREND"
    ]
  },
  {
    "slug": "gc-settle-jun-2026",
    "ticker": "gc-settle-above-6200-jun-2026",
    "question": ">$6,200",
    "eventTitle": "What will Gold (GC) settle at in June?",
    "prices": "Yes: 24.5% | No: 75.5%",
    "volume": 55393,
    "liquidity": 12084,
    "endDate": "2026-06-30",
    "dayChange": "6.10%",
    "vol24h": 2908,
    "spread": "0.80%",
    "sortOrder": 7,
    "updatedAt": "2026-02-03T16:04:33.070085Z",
    "engine": "sniper",
    "core_topic": "What will Gold (GC) settle at in {month}?",
    "category": "FINANCE",
    "url": "https://polymarket.com/event/gc-settle-jun-2026",
    "strategy_tags": [
      "HIGH_CERTAINTY"
    ]
  },
  {
    "slug": "what-will-gold-gc-hit-by-end-of-february",
    "ticker": "will-gold-gc-hit-low-3600-by-end-of-february-767-713-548-338-651-365-876-463",
    "question": "↓ $3,600",
    "eventTitle": "What will Gold (GC) hit__ by end of February?",
    "prices": "Yes: 3.1% | No: 96.9%",
    "volume": 50918,
    "liquidity": 26801,
    "endDate": "2026-02-28",
    "dayChange": "-2.85%",
    "vol24h": 15745,
    "spread": "0.20%",
    "sortOrder": 18,
    "updatedAt": "2026-02-03T16:04:30.897022Z",
    "engine": "sniper",
    "core_topic": "What will Gold (GC) hit__ by end of {month}?",
    "category": "FINANCE",
    "url": "https://polymarket.com/event/what-will-gold-gc-hit-by-end-of-february",
    "strategy_tags": [
      "TAIL_RISK",
      "HIGH_CERTAINTY"
    ]
  },
  {
    "slug": "bitcoin-above-on-february-5",
    "ticker": "bitcoin-above-82k-on-february-5",
    "question": "82,000",
    "eventTitle": "Bitcoin above ___ on February 5?",
    "prices": "Yes: 9.5% | No: 90.5%",
    "volume": 50820,
    "liquidity": 15523,
    "endDate": "2026-02-05",
    "dayChange": "-12.50%",
    "vol24h": 10292,
    "spread": "1.00%",
    "sortOrder": 3,
    "updatedAt": "2026-02-03T16:01:31.561939Z",
    "engine": "sniper",
    "core_topic": "Bitcoin above ___ on {date}?",
    "category": "CRYPTO",
    "url": "https://polymarket.com/event/bitcoin-above-on-february-5",
    "strategy_tags": [
      "REFLEXIVITY_TREND"
    ]
  },
  {
    "slug": "bitcoin-above-on-february-4",
    "ticker": "bitcoin-above-88k-on-february-4",
    "question": "88,000",
    "eventTitle": "Bitcoin above ___ on February 4?",
    "prices": "Yes: 0.3% | No: 99.8%",
    "volume": 46357,
    "liquidity": 28418,
    "endDate": "2026-02-04",
    "dayChange": "-2.25%",
    "vol24h": 7357,
    "spread": "0.10%",
    "sortOrder": 4,
    "updatedAt": "2026-02-03T16:01:39.315683Z",
    "engine": "sniper",
    "core_topic": "Bitcoin above ___ on {date}?",
    "category": "CRYPTO",
    "url": "https://polymarket.com/event/bitcoin-above-on-february-4",
    "strategy_tags": [
      "TAIL_RISK"
    ]
  },
  {
    "slug": "bitcoin-price-on-february-4",
    "ticker": "will-the-price-of-bitcoin-be-between-92000-94000-on-february-4",
    "question": "92,000-94,000",
    "eventTitle": "Bitcoin price on February 4?",
    "prices": "Yes: 0.1% | No: 99.9%",
    "volume": 43723,
    "liquidity": 32595,
    "endDate": "2026-02-04",
    "dayChange": "-0.20%",
    "vol24h": 19000,
    "spread": "0.10%",
    "sortOrder": 7,
    "updatedAt": "2026-02-03T16:02:04.311295Z",
    "engine": "sniper",
    "core_topic": "Bitcoin price on {date}?",
    "category": "CRYPTO",
    "url": "https://polymarket.com/event/bitcoin-price-on-february-4",
    "strategy_tags": [
      "TAIL_RISK"
    ]
  },
  {
    "slug": "bitcoin-above-on-february-5",
    "ticker": "bitcoin-above-86k-on-february-5",
    "question": "86,000",
    "eventTitle": "Bitcoin above ___ on February 5?",
    "prices": "Yes: 1.3% | No: 98.8%",
    "volume": 41848,
    "liquidity": 18505,
    "endDate": "2026-02-05",
    "dayChange": "-4.50%",
    "vol24h": 7734,
    "spread": "0.70%",
    "sortOrder": 5,
    "updatedAt": "2026-02-03T16:04:29.265031Z",
    "engine": "sniper",
    "core_topic": "Bitcoin above ___ on {date}?",
    "category": "CRYPTO",
    "url": "https://polymarket.com/event/bitcoin-above-on-february-5",
    "strategy_tags": [
      "TAIL_RISK"
    ]
  },
  {
    "slug": "what-will-gold-gc-hit-by-end-of-february",
    "ticker": "will-gold-gc-hit-high-6200-by-end-of-february-882-138-877-117-343-764-976",
    "question": "↑ $6,200",
    "eventTitle": "What will Gold (GC) hit__ by end of February?",
    "prices": "Yes: 6.4% | No: 93.6%",
    "volume": 41710,
    "liquidity": 28274,
    "endDate": "2026-02-28",
    "dayChange": "0.55%",
    "vol24h": 13498,
    "spread": "0.40%",
    "sortOrder": 4,
    "updatedAt": "2026-02-03T16:02:03.888652Z",
    "engine": "sniper",
    "core_topic": "What will Gold (GC) hit__ by end of {month}?",
    "category": "FINANCE",
    "url": "https://polymarket.com/event/what-will-gold-gc-hit-by-end-of-february",
    "strategy_tags": [
      "RAW_MARKET"
    ]
  },
  {
    "slug": "gc-settle-jun-2026",
    "ticker": "gc-settle-below-3800-jun-2026",
    "question": "<$3,800",
    "eventTitle": "What will Gold (GC) settle at in June?",
    "prices": "Yes: 9.2% | No: 90.8%",
    "volume": 40602,
    "liquidity": 11099,
    "endDate": "2026-06-30",
    "dayChange": "-4.60%",
    "vol24h": 5090,
    "spread": "0.30%",
    "sortOrder": 0,
    "updatedAt": "2026-02-03T16:04:32.817716Z",
    "engine": "sniper",
    "core_topic": "What will Gold (GC) settle at in {month}?",
    "category": "FINANCE",
    "url": "https://polymarket.com/event/gc-settle-jun-2026",
    "strategy_tags": [
      "RAW_MARKET"
    ]
  },
  {
    "slug": "bitcoin-above-on-february-5",
    "ticker": "bitcoin-above-92k-on-february-5",
    "question": "92,000",
    "eventTitle": "Bitcoin above ___ on February 5?",
    "prices": "Yes: 0.3% | No: 99.7%",
    "volume": 35561,
    "liquidity": 18800,
    "endDate": "2026-02-05",
    "dayChange": "-0.10%",
    "vol24h": 9024,
    "spread": "0.20%",
    "sortOrder": 8,
    "updatedAt": "2026-02-03T16:01:42.595946Z",
    "engine": "sniper",
    "core_topic": "Bitcoin above ___ on {date}?",
    "category": "CRYPTO",
    "url": "https://polymarket.com/event/bitcoin-above-on-february-5",
    "strategy_tags": [
      "TAIL_RISK"
    ]
  },
  {
    "slug": "bitcoin-above-on-february-5",
    "ticker": "bitcoin-above-90k-on-february-5",
    "question": "90,000",
    "eventTitle": "Bitcoin above ___ on February 5?",
    "prices": "Yes: 0.6% | No: 99.4%",
    "volume": 35379,
    "liquidity": 16791,
    "endDate": "2026-02-05",
    "dayChange": "-0.40%",
    "vol24h": 7199,
    "spread": "0.40%",
    "sortOrder": 7,
    "updatedAt": "2026-02-03T16:04:39.763837Z",
    "engine": "sniper",
    "core_topic": "Bitcoin above ___ on {date}?",
    "category": "CRYPTO",
    "url": "https://polymarket.com/event/bitcoin-above-on-february-5",
    "strategy_tags": [
      "TAIL_RISK"
    ]
  },
  {
    "slug": "bitcoin-above-on-february-4",
    "ticker": "bitcoin-above-100k-on-february-4",
    "question": "100,000",
    "eventTitle": "Bitcoin above ___ on February 4?",
    "prices": "Yes: 0.1% | No: 100.0%",
    "volume": 28986,
    "liquidity": 35863,
    "endDate": "2026-02-04",
    "dayChange": "-0.10%",
    "vol24h": 20219,
    "spread": "0.10%",
    "sortOrder": 10,
    "updatedAt": "2026-02-03T16:01:29.988771Z",
    "engine": "sniper",
    "core_topic": "Bitcoin above ___ on {date}?",
    "category": "CRYPTO",
    "url": "https://polymarket.com/event/bitcoin-above-on-february-4",
    "strategy_tags": [
      "TAIL_RISK"
    ]
  },
  {
    "slug": "bitcoin-price-on-february-4",
    "ticker": "will-the-price-of-bitcoin-be-greater-than-98000-on-february-4",
    "question": ">98,000",
    "eventTitle": "Bitcoin price on February 4?",
    "prices": "Yes: 0.1% | No: 100.0%",
    "volume": 28313,
    "liquidity": 21402,
    "endDate": "2026-02-04",
    "dayChange": "-0.10%",
    "vol24h": 23947,
    "spread": "0.10%",
    "sortOrder": 10,
    "updatedAt": "2026-02-03T16:04:58.824603Z",
    "engine": "sniper",
    "core_topic": "Bitcoin price on {date}?",
    "category": "CRYPTO",
    "url": "https://polymarket.com/event/bitcoin-price-on-february-4",
    "strategy_tags": [
      "TAIL_RISK"
    ]
  },
  {
    "slug": "bitcoin-above-on-february-4",
    "ticker": "bitcoin-above-96k-on-february-4",
    "question": "96,000",
    "eventTitle": "Bitcoin above ___ on February 4?",
    "prices": "Yes: 0.1% | No: 100.0%",
    "volume": 27995,
    "liquidity": 31118,
    "endDate": "2026-02-04",
    "dayChange": "-0.10%",
    "vol24h": 17949,
    "spread": "0.10%",
    "sortOrder": 8,
    "updatedAt": "2026-02-03T16:01:31.648102Z",
    "engine": "sniper",
    "core_topic": "Bitcoin above ___ on {date}?",
    "category": "CRYPTO",
    "url": "https://polymarket.com/event/bitcoin-above-on-february-4",
    "strategy_tags": [
      "TAIL_RISK"
    ]
  },
  {
    "slug": "bitcoin-price-on-february-5",
    "ticker": "will-the-price-of-bitcoin-be-less-than-76000-on-february-5",
    "question": "<76,000",
    "eventTitle": "Bitcoin price on February 5?",
    "prices": "Yes: 25.1% | No: 74.9%",
    "volume": 27622,
    "liquidity": 9469,
    "endDate": "2026-02-05",
    "dayChange": "3.40%",
    "vol24h": 2988,
    "spread": "1.80%",
    "sortOrder": 0,
    "updatedAt": "2026-02-03T16:01:39.008707Z",
    "engine": "sniper",
    "core_topic": "Bitcoin price on {date}?",
    "category": "CRYPTO",
    "url": "https://polymarket.com/event/bitcoin-price-on-february-5",
    "strategy_tags": [
      "RAW_MARKET"
    ]
  },
  {
    "slug": "bitcoin-above-on-february-4",
    "ticker": "bitcoin-above-98k-on-february-4",
    "question": "98,000",
    "eventTitle": "Bitcoin above ___ on February 4?",
    "prices": "Yes: 0.1% | No: 100.0%",
    "volume": 27147,
    "liquidity": 27270,
    "endDate": "2026-02-04",
    "dayChange": "-0.10%",
    "vol24h": 12857,
    "spread": "0.10%",
    "sortOrder": 9,
    "updatedAt": "2026-02-03T16:01:55.149194Z",
    "engine": "sniper",
    "core_topic": "Bitcoin above ___ on {date}?",
    "category": "CRYPTO",
    "url": "https://polymarket.com/event/bitcoin-above-on-february-4",
    "strategy_tags": [
      "TAIL_RISK"
    ]
  },
  {
    "slug": "what-will-gold-gc-hit-by-end-of-february",
    "ticker": "will-gold-gc-hit-low-4000-by-end-of-february-542-564-882-215-825-637-559-654-593",
    "question": "↓ $4,000",
    "eventTitle": "What will Gold (GC) hit__ by end of February?",
    "prices": "Yes: 9.2% | No: 90.8%",
    "volume": 26939,
    "liquidity": 11441,
    "endDate": "2026-02-28",
    "dayChange": "-11.30%",
    "vol24h": 8547,
    "spread": "0.10%",
    "sortOrder": 17,
    "updatedAt": "2026-02-03T16:02:04.016501Z",
    "engine": "sniper",
    "core_topic": "What will Gold (GC) hit__ by end of {month}?",
    "category": "FINANCE",
    "url": "https://polymarket.com/event/what-will-gold-gc-hit-by-end-of-february",
    "strategy_tags": [
      "RAW_MARKET"
    ]
  },
  {
    "slug": "bitcoin-price-on-february-4",
    "ticker": "will-the-price-of-bitcoin-be-between-82000-84000-on-february-4",
    "question": "82,000-84,000",
    "eventTitle": "Bitcoin price on February 4?",
    "prices": "Yes: 2.9% | No: 97.0%",
    "volume": 26451,
    "liquidity": 13082,
    "endDate": "2026-02-04",
    "dayChange": "-8.00%",
    "vol24h": 9611,
    "spread": "0.70%",
    "sortOrder": 2,
    "updatedAt": "2026-02-03T16:04:48.186142Z",
    "engine": "sniper",
    "core_topic": "Bitcoin price on {date}?",
    "category": "CRYPTO",
    "url": "https://polymarket.com/event/bitcoin-price-on-february-4",
    "strategy_tags": [
      "TAIL_RISK"
    ]
  },
  {
    "slug": "gc-settle-jun-2026",
    "ticker": "gc-settle-5800-6200-jun-2026",
    "question": "$5,800-$6,200",
    "eventTitle": "What will Gold (GC) settle at in June?",
    "prices": "Yes: 8.4% | No: 91.6%",
    "volume": 25251,
    "liquidity": 3189,
    "endDate": "2026-06-30",
    "dayChange": "-2.60%",
    "vol24h": 762,
    "spread": "2.80%",
    "sortOrder": 6,
    "updatedAt": "2026-02-03T16:01:51.369133Z",
    "engine": "sniper",
    "core_topic": "What will Gold (GC) settle at in {month}?",
    "category": "FINANCE",
    "url": "https://polymarket.com/event/gc-settle-jun-2026",
    "strategy_tags": [
      "RAW_MARKET"
    ]
  },
  {
    "slug": "what-will-gold-gc-hit-by-end-of-february",
    "ticker": "will-gold-gc-hit-low-4200-by-end-of-february-891-227-734-585-416-787-933-185-752",
    "question": "↓ $4,200",
    "eventTitle": "What will Gold (GC) hit__ by end of February?",
    "prices": "Yes: 16.5% | No: 83.5%",
    "volume": 25222,
    "liquidity": 9415,
    "endDate": "2026-02-28",
    "dayChange": "-19.00%",
    "vol24h": 6178,
    "spread": "1.00%",
    "sortOrder": 16,
    "updatedAt": "2026-02-03T16:04:37.270786Z",
    "engine": "sniper",
    "core_topic": "What will Gold (GC) hit__ by end of {month}?",
    "category": "FINANCE",
    "url": "https://polymarket.com/event/what-will-gold-gc-hit-by-end-of-february",
    "strategy_tags": [
      "RAW_MARKET"
    ]
  },
  {
    "slug": "gc-settle-jun-2026",
    "ticker": "gc-settle-5000-5400-jun-2026",
    "question": "$5,000-$5,400",
    "eventTitle": "What will Gold (GC) settle at in June?",
    "prices": "Yes: 13.8% | No: 86.3%",
    "volume": 23955,
    "liquidity": 7168,
    "endDate": "2026-06-30",
    "dayChange": "0.35%",
    "vol24h": 134,
    "spread": "1.70%",
    "sortOrder": 4,
    "updatedAt": "2026-02-03T16:01:47.166265Z",
    "engine": "sniper",
    "core_topic": "What will Gold (GC) settle at in {month}?",
    "category": "FINANCE",
    "url": "https://polymarket.com/event/gc-settle-jun-2026",
    "strategy_tags": [
      "RAW_MARKET"
    ]
  },
  {
    "slug": "bitcoin-price-on-february-3",
    "ticker": "will-the-price-of-bitcoin-be-between-92000-94000-on-february-3",
    "question": "92,000-94,000",
    "eventTitle": "Bitcoin price on February 3?",
    "prices": "Yes: 0.1% | No: 100.0%",
    "volume": 21889,
    "liquidity": 80453,
    "endDate": "2026-02-03",
    "dayChange": "0.00%",
    "vol24h": 6652,
    "spread": "0.10%",
    "sortOrder": 7,
    "updatedAt": "2026-02-03T16:01:29.162851Z",
    "engine": "sniper",
    "core_topic": "Bitcoin price on {date}?",
    "category": "CRYPTO",
    "url": "https://polymarket.com/event/bitcoin-price-on-february-3",
    "strategy_tags": [
      "TAIL_RISK"
    ]
  },
  {
    "slug": "bitcoin-price-on-february-3",
    "ticker": "will-the-price-of-bitcoin-be-between-94000-96000-on-february-3",
    "question": "94,000-96,000",
    "eventTitle": "Bitcoin price on February 3?",
    "prices": "Yes: 0.1% | No: 100.0%",
    "volume": 20341,
    "liquidity": 79721,
    "endDate": "2026-02-03",
    "dayChange": "0.00%",
    "vol24h": 10829,
    "spread": "0.10%",
    "sortOrder": 8,
    "updatedAt": "2026-02-03T16:01:43.530795Z",
    "engine": "sniper",
    "core_topic": "Bitcoin price on {date}?",
    "category": "CRYPTO",
    "url": "https://polymarket.com/event/bitcoin-price-on-february-3",
    "strategy_tags": [
      "TAIL_RISK"
    ]
  },
  {
    "slug": "gc-settle-jun-2026",
    "ticker": "gc-settle-4600-5000-jun-2026",
    "question": "$4,600-$5,000",
    "eventTitle": "What will Gold (GC) settle at in June?",
    "prices": "Yes: 13.5% | No: 86.5%",
    "volume": 20285,
    "liquidity": 8402,
    "endDate": "2026-06-30",
    "dayChange": "0.50%",
    "vol24h": 222,
    "spread": "1.00%",
    "sortOrder": 3,
    "updatedAt": "2026-02-03T16:02:03.71514Z",
    "engine": "sniper",
    "core_topic": "What will Gold (GC) settle at in {month}?",
    "category": "FINANCE",
    "url": "https://polymarket.com/event/gc-settle-jun-2026",
    "strategy_tags": [
      "RAW_MARKET"
    ]
  },
  {
    "slug": "bitcoin-price-on-february-4",
    "ticker": "will-the-price-of-bitcoin-be-between-80000-82000-on-february-4",
    "question": "80,000-82,000",
    "eventTitle": "Bitcoin price on February 4?",
    "prices": "Yes: 13.5% | No: 86.5%",
    "volume": 20123,
    "liquidity": 11535,
    "endDate": "2026-02-04",
    "dayChange": "-4.50%",
    "vol24h": 6096,
    "spread": "3.00%",
    "sortOrder": 1,
    "updatedAt": "2026-02-03T16:04:47.446536Z",
    "engine": "sniper",
    "core_topic": "Bitcoin price on {date}?",
    "category": "CRYPTO",
    "url": "https://polymarket.com/event/bitcoin-price-on-february-4",
    "strategy_tags": [
      "RAW_MARKET"
    ]
  },
  {
    "slug": "bitcoin-price-on-february-5",
    "ticker": "will-the-price-of-bitcoin-be-between-76000-78000-on-february-5",
    "question": "76,000-78,000",
    "eventTitle": "Bitcoin price on February 5?",
    "prices": "Yes: 23.8% | No: 76.3%",
    "volume": 19437,
    "liquidity": 10061,
    "endDate": "2026-02-05",
    "dayChange": "6.10%",
    "vol24h": 1841,
    "spread": "2.70%",
    "sortOrder": 1,
    "updatedAt": "2026-02-03T16:01:29.406635Z",
    "engine": "sniper",
    "core_topic": "Bitcoin price on {date}?",
    "category": "CRYPTO",
    "url": "https://polymarket.com/event/bitcoin-price-on-february-5",
    "strategy_tags": [
      "RAW_MARKET"
    ]
  },
  {
    "slug": "gc-settle-jun-2026",
    "ticker": "gc-settle-3800-4200-jun-2026",
    "question": "$3,800-$4,200",
    "eventTitle": "What will Gold (GC) settle at in June?",
    "prices": "Yes: 9.0% | No: 91.0%",
    "volume": 19036,
    "liquidity": 6757,
    "endDate": "2026-06-30",
    "dayChange": "0.55%",
    "vol24h": 323,
    "spread": "0.40%",
    "sortOrder": 1,
    "updatedAt": "2026-02-03T16:04:42.206292Z",
    "engine": "sniper",
    "core_topic": "What will Gold (GC) settle at in {month}?",
    "category": "FINANCE",
    "url": "https://polymarket.com/event/gc-settle-jun-2026",
    "strategy_tags": [
      "RAW_MARKET"
    ]
  },
  {
    "slug": "gc-settle-jun-2026",
    "ticker": "gc-settle-4200-4600-jun-2026",
    "question": "$4,200-$4,600",
    "eventTitle": "What will Gold (GC) settle at in June?",
    "prices": "Yes: 11.8% | No: 88.3%",
    "volume": 18721,
    "liquidity": 3811,
    "endDate": "2026-06-30",
    "dayChange": "0.95%",
    "vol24h": 85,
    "spread": "0.50%",
    "sortOrder": 2,
    "updatedAt": "2026-02-03T16:04:37.425937Z",
    "engine": "sniper",
    "core_topic": "What will Gold (GC) settle at in {month}?",
    "category": "FINANCE",
    "url": "https://polymarket.com/event/gc-settle-jun-2026",
    "strategy_tags": [
      "RAW_MARKET"
    ]
  },
  {
    "slug": "gc-settle-jun-2026",
    "ticker": "gc-settle-5400-5800-jun-2026",
    "question": "$5,400-$5,800",
    "eventTitle": "What will Gold (GC) settle at in June?",
    "prices": "Yes: 10.0% | No: 90.0%",
    "volume": 18288,
    "liquidity": 3956,
    "endDate": "2026-06-30",
    "dayChange": "-1.00%",
    "vol24h": 40,
    "spread": "2.00%",
    "sortOrder": 5,
    "updatedAt": "2026-02-03T16:01:54.489588Z",
    "engine": "sniper",
    "core_topic": "What will Gold (GC) settle at in {month}?",
    "category": "FINANCE",
    "url": "https://polymarket.com/event/gc-settle-jun-2026",
    "strategy_tags": [
      "RAW_MARKET"
    ]
  },
  {
    "slug": "bitcoin-price-on-february-3",
    "ticker": "will-the-price-of-bitcoin-be-greater-than-98000-on-february-3",
    "question": ">98,000",
    "eventTitle": "Bitcoin price on February 3?",
    "prices": "Yes: 0.1% | No: 100.0%",
    "volume": 17039,
    "liquidity": 80895,
    "endDate": "2026-02-03",
    "dayChange": "0.00%",
    "vol24h": 0,
    "spread": "0.10%",
    "sortOrder": 10,
    "updatedAt": "2026-02-03T16:01:37.790344Z",
    "engine": "sniper",
    "core_topic": "Bitcoin price on {date}?",
    "category": "CRYPTO",
    "url": "https://polymarket.com/event/bitcoin-price-on-february-3",
    "strategy_tags": [
      "TAIL_RISK"
    ]
  },
  {
    "slug": "bitcoin-price-on-february-4",
    "ticker": "will-the-price-of-bitcoin-be-between-96000-98000-on-february-4",
    "question": "96,000-98,000",
    "eventTitle": "Bitcoin price on February 4?",
    "prices": "Yes: 0.1% | No: 100.0%",
    "volume": 17031,
    "liquidity": 19933,
    "endDate": "2026-02-04",
    "dayChange": "-0.25%",
    "vol24h": 15380,
    "spread": "0.10%",
    "sortOrder": 9,
    "updatedAt": "2026-02-03T16:01:54.939966Z",
    "engine": "sniper",
    "core_topic": "Bitcoin price on {date}?",
    "category": "CRYPTO",
    "url": "https://polymarket.com/event/bitcoin-price-on-february-4",
    "strategy_tags": [
      "TAIL_RISK"
    ]
  },
  {
    "slug": "bitcoin-price-on-february-4",
    "ticker": "will-the-price-of-bitcoin-be-between-84000-86000-on-february-4",
    "question": "84,000-86,000",
    "eventTitle": "Bitcoin price on February 4?",
    "prices": "Yes: 0.9% | No: 99.1%",
    "volume": 16491,
    "liquidity": 13614,
    "endDate": "2026-02-04",
    "dayChange": "-3.60%",
    "vol24h": 4327,
    "spread": "0.60%",
    "sortOrder": 3,
    "updatedAt": "2026-02-03T16:04:53.942162Z",
    "engine": "sniper",
    "core_topic": "Bitcoin price on {date}?",
    "category": "CRYPTO",
    "url": "https://polymarket.com/event/bitcoin-price-on-february-4",
    "strategy_tags": [
      "TAIL_RISK"
    ]
  },
  {
    "slug": "bitcoin-price-on-february-5",
    "ticker": "will-the-price-of-bitcoin-be-between-78000-80000-on-february-5",
    "question": "78,000-80,000",
    "eventTitle": "Bitcoin price on February 5?",
    "prices": "Yes: 26.0% | No: 74.0%",
    "volume": 15948,
    "liquidity": 10094,
    "endDate": "2026-02-05",
    "dayChange": "5.00%",
    "vol24h": 1704,
    "spread": "2.00%",
    "sortOrder": 2,
    "updatedAt": "2026-02-03T16:02:04.714249Z",
    "engine": "sniper",
    "core_topic": "Bitcoin price on {date}?",
    "category": "CRYPTO",
    "url": "https://polymarket.com/event/bitcoin-price-on-february-5",
    "strategy_tags": [
      "RAW_MARKET"
    ]
  },
  {
    "slug": "bitcoin-price-on-february-4",
    "ticker": "will-the-price-of-bitcoin-be-between-86000-88000-on-february-4",
    "question": "86,000-88,000",
    "eventTitle": "Bitcoin price on February 4?",
    "prices": "Yes: 0.3% | No: 99.8%",
    "volume": 15497,
    "liquidity": 12636,
    "endDate": "2026-02-04",
    "dayChange": "-1.50%",
    "vol24h": 1228,
    "spread": "0.10%",
    "sortOrder": 4,
    "updatedAt": "2026-02-03T16:04:32.279752Z",
    "engine": "sniper",
    "core_topic": "Bitcoin price on {date}?",
    "category": "CRYPTO",
    "url": "https://polymarket.com/event/bitcoin-price-on-february-4",
    "strategy_tags": [
      "TAIL_RISK"
    ]
  },
  {
    "slug": "bitcoin-above-on-february-5",
    "ticker": "bitcoin-above-88k-on-february-5",
    "question": "88,000",
    "eventTitle": "Bitcoin above ___ on February 5?",
    "prices": "Yes: 1.1% | No: 99.0%",
    "volume": 15397,
    "liquidity": 18510,
    "endDate": "2026-02-05",
    "dayChange": "-1.00%",
    "vol24h": 1986,
    "spread": "0.30%",
    "sortOrder": 6,
    "updatedAt": "2026-02-03T16:04:31.653476Z",
    "engine": "sniper",
    "core_topic": "Bitcoin above ___ on {date}?",
    "category": "CRYPTO",
    "url": "https://polymarket.com/event/bitcoin-above-on-february-5",
    "strategy_tags": [
      "TAIL_RISK"
    ]
  },
  {
    "slug": "bitcoin-price-on-february-4",
    "ticker": "will-the-price-of-bitcoin-be-between-94000-96000-on-february-4",
    "question": "94,000-96,000",
    "eventTitle": "Bitcoin price on February 4?",
    "prices": "Yes: 0.1% | No: 99.9%",
    "volume": 14100,
    "liquidity": 20999,
    "endDate": "2026-02-04",
    "dayChange": "0.00%",
    "vol24h": 7206,
    "spread": "0.10%",
    "sortOrder": 8,
    "updatedAt": "2026-02-03T16:04:47.588902Z",
    "engine": "sniper",
    "core_topic": "Bitcoin price on {date}?",
    "category": "CRYPTO",
    "url": "https://polymarket.com/event/bitcoin-price-on-february-4",
    "strategy_tags": [
      "TAIL_RISK"
    ]
  },
  {
    "slug": "bitcoin-price-on-february-5",
    "ticker": "will-the-price-of-bitcoin-be-greater-than-94000-on-february-5",
    "question": ">94,000",
    "eventTitle": "Bitcoin price on February 5?",
    "prices": "Yes: 0.1% | No: 99.9%",
    "volume": 13761,
    "liquidity": 13003,
    "endDate": "2026-02-05",
    "dayChange": "-0.40%",
    "vol24h": 7576,
    "spread": "0.10%",
    "sortOrder": 10,
    "updatedAt": "2026-02-03T16:01:37.195974Z",
    "engine": "sniper",
    "core_topic": "Bitcoin price on {date}?",
    "category": "CRYPTO",
    "url": "https://polymarket.com/event/bitcoin-price-on-february-5",
    "strategy_tags": [
      "TAIL_RISK"
    ]
  },
  {
    "slug": "bitcoin-price-on-february-4",
    "ticker": "will-the-price-of-bitcoin-be-between-90000-92000-on-february-4",
    "question": "90,000-92,000",
    "eventTitle": "Bitcoin price on February 4?",
    "prices": "Yes: 0.1% | No: 99.9%",
    "volume": 13228,
    "liquidity": 13430,
    "endDate": "2026-02-04",
    "dayChange": "-0.20%",
    "vol24h": 1211,
    "spread": "0.10%",
    "sortOrder": 6,
    "updatedAt": "2026-02-03T16:01:53.201335Z",
    "engine": "sniper",
    "core_topic": "Bitcoin price on {date}?",
    "category": "CRYPTO",
    "url": "https://polymarket.com/event/bitcoin-price-on-february-4",
    "strategy_tags": [
      "TAIL_RISK"
    ]
  },
  {
    "slug": "bitcoin-price-on-february-3",
    "ticker": "will-the-price-of-bitcoin-be-between-96000-98000-on-february-3",
    "question": "96,000-98,000",
    "eventTitle": "Bitcoin price on February 3?",
    "prices": "Yes: 0.1% | No: 100.0%",
    "volume": 12097,
    "liquidity": 80262,
    "endDate": "2026-02-03",
    "dayChange": "-0.05%",
    "vol24h": 0,
    "spread": "0.10%",
    "sortOrder": 9,
    "updatedAt": "2026-02-03T16:01:53.393363Z",
    "engine": "sniper",
    "core_topic": "Bitcoin price on {date}?",
    "category": "CRYPTO",
    "url": "https://polymarket.com/event/bitcoin-price-on-february-3",
    "strategy_tags": [
      "TAIL_RISK"
    ]
  },
  {
    "slug": "bitcoin-above-on-february-5",
    "ticker": "bitcoin-above-94k-on-february-5",
    "question": "94,000",
    "eventTitle": "Bitcoin above ___ on February 5?",
    "prices": "Yes: 0.3% | No: 99.7%",
    "volume": 8937,
    "liquidity": 15263,
    "endDate": "2026-02-05",
    "dayChange": "0.05%",
    "vol24h": 965,
    "spread": "0.40%",
    "sortOrder": 9,
    "updatedAt": "2026-02-03T16:01:28.733491Z",
    "engine": "sniper",
    "core_topic": "Bitcoin above ___ on {date}?",
    "category": "CRYPTO",
    "url": "https://polymarket.com/event/bitcoin-above-on-february-5",
    "strategy_tags": [
      "TAIL_RISK"
    ]
  },
  {
    "slug": "bitcoin-price-on-february-4",
    "ticker": "will-the-price-of-bitcoin-be-between-88000-90000-on-february-4",
    "question": "88,000-90,000",
    "eventTitle": "Bitcoin price on February 4?",
    "prices": "Yes: 0.3% | No: 99.8%",
    "volume": 7676,
    "liquidity": 13217,
    "endDate": "2026-02-04",
    "dayChange": "-0.75%",
    "vol24h": 2272,
    "spread": "0.10%",
    "sortOrder": 5,
    "updatedAt": "2026-02-03T16:04:41.004676Z",
    "engine": "sniper",
    "core_topic": "Bitcoin price on {date}?",
    "category": "CRYPTO",
    "url": "https://polymarket.com/event/bitcoin-price-on-february-4",
    "strategy_tags": [
      "TAIL_RISK"
    ]
  },
  {
    "slug": "bitcoin-price-on-february-5",
    "ticker": "will-the-price-of-bitcoin-be-between-84000-86000-on-february-5",
    "question": "84,000-86,000",
    "eventTitle": "Bitcoin price on February 5?",
    "prices": "Yes: 2.0% | No: 98.0%",
    "volume": 6083,
    "liquidity": 10274,
    "endDate": "2026-02-05",
    "dayChange": "-4.70%",
    "vol24h": 2804,
    "spread": "1.40%",
    "sortOrder": 5,
    "updatedAt": "2026-02-03T16:01:41.726363Z",
    "engine": "sniper",
    "core_topic": "Bitcoin price on {date}?",
    "category": "CRYPTO",
    "url": "https://polymarket.com/event/bitcoin-price-on-february-5",
    "strategy_tags": [
      "TAIL_RISK"
    ]
  },
  {
    "slug": "bitcoin-price-on-february-5",
    "ticker": "will-the-price-of-bitcoin-be-between-90000-92000-on-february-5",
    "question": "90,000-92,000",
    "eventTitle": "Bitcoin price on February 5?",
    "prices": "Yes: 0.4% | No: 99.6%",
    "volume": 5800,
    "liquidity": 10489,
    "endDate": "2026-02-05",
    "dayChange": "-0.15%",
    "vol24h": 2752,
    "spread": "0.40%",
    "sortOrder": 8,
    "updatedAt": "2026-02-03T16:01:39.089275Z",
    "engine": "sniper",
    "core_topic": "Bitcoin price on {date}?",
    "category": "CRYPTO",
    "url": "https://polymarket.com/event/bitcoin-price-on-february-5",
    "strategy_tags": [
      "TAIL_RISK"
    ]
  },
  {
    "slug": "bitcoin-price-on-february-5",
    "ticker": "will-the-price-of-bitcoin-be-between-92000-94000-on-february-5",
    "question": "92,000-94,000",
    "eventTitle": "Bitcoin price on February 5?",
    "prices": "Yes: 0.4% | No: 99.7%",
    "volume": 5516,
    "liquidity": 11130,
    "endDate": "2026-02-05",
    "dayChange": "-0.20%",
    "vol24h": 1662,
    "spread": "0.30%",
    "sortOrder": 9,
    "updatedAt": "2026-02-03T16:01:57.689244Z",
    "engine": "sniper",
    "core_topic": "Bitcoin price on {date}?",
    "category": "CRYPTO",
    "url": "https://polymarket.com/event/bitcoin-price-on-february-5",
    "strategy_tags": [
      "TAIL_RISK"
    ]
  },
  {
    "slug": "bitcoin-price-on-february-5",
    "ticker": "will-the-price-of-bitcoin-be-between-86000-88000-on-february-5",
    "question": "86,000-88,000",
    "eventTitle": "Bitcoin price on February 5?",
    "prices": "Yes: 1.1% | No: 99.0%",
    "volume": 3454,
    "liquidity": 9533,
    "endDate": "2026-02-05",
    "dayChange": "-2.65%",
    "vol24h": 1918,
    "spread": "0.70%",
    "sortOrder": 6,
    "updatedAt": "2026-02-03T16:01:58.475348Z",
    "engine": "sniper",
    "core_topic": "Bitcoin price on {date}?",
    "category": "CRYPTO",
    "url": "https://polymarket.com/event/bitcoin-price-on-february-5",
    "strategy_tags": [
      "TAIL_RISK"
    ]
  },
  {
    "slug": "bitcoin-price-on-february-5",
    "ticker": "will-the-price-of-bitcoin-be-between-88000-90000-on-february-5",
    "question": "88,000-90,000",
    "eventTitle": "Bitcoin price on February 5?",
    "prices": "Yes: 0.5% | No: 99.5%",
    "volume": 3167,
    "liquidity": 10025,
    "endDate": "2026-02-05",
    "dayChange": "0.00%",
    "vol24h": 1401,
    "spread": "0.50%",
    "sortOrder": 7,
    "updatedAt": "2026-02-03T16:01:14.055428Z",
    "engine": "sniper",
    "core_topic": "Bitcoin price on {date}?",
    "category": "CRYPTO",
    "url": "https://polymarket.com/event/bitcoin-price-on-february-5",
    "strategy_tags": [
      "TAIL_RISK"
    ]
  },
  {
    "slug": "bitcoin-price-on-february-5",
    "ticker": "will-the-price-of-bitcoin-be-between-82000-84000-on-february-5",
    "question": "82,000-84,000",
    "eventTitle": "Bitcoin price on February 5?",
    "prices": "Yes: 6.0% | No: 94.0%",
    "volume": 2109,
    "liquidity": 8980,
    "endDate": "2026-02-05",
    "dayChange": "-6.45%",
    "vol24h": 486,
    "spread": "2.80%",
    "sortOrder": 4,
    "updatedAt": "2026-02-03T16:01:35.200136Z",
    "engine": "sniper",
    "core_topic": "Bitcoin price on {date}?",
    "category": "CRYPTO",
    "url": "https://polymarket.com/event/bitcoin-price-on-february-5",
    "strategy_tags": [
      "RAW_MARKET"
    ]
  },
  {
    "slug": "bitcoin-price-on-february-5",
    "ticker": "will-the-price-of-bitcoin-be-between-80000-82000-on-february-5",
    "question": "80,000-82,000",
    "eventTitle": "Bitcoin price on February 5?",
    "prices": "Yes: 15.0% | No: 85.0%",
    "volume": 1869,
    "liquidity": 9215,
    "endDate": "2026-02-05",
    "dayChange": "-3.50%",
    "vol24h": 514,
    "spread": "2.00%",
    "sortOrder": 3,
    "updatedAt": "2026-02-03T16:01:41.664129Z",
    "engine": "sniper",
    "core_topic": "Bitcoin price on {date}?",
    "category": "CRYPTO",
    "url": "https://polymarket.com/event/bitcoin-price-on-february-5",
    "strategy_tags": [
      "RAW_MARKET"
    ]
  }
]