[
  {
    "slug": "fed-decision-in-march-885",
    "ticker": "will-the-fed-increase-interest-rates-by-25-bps-after-the-march-2026-meeting",
    "question": "25+ bps increase",
    "eventTitle": "Fed decision in March?",
    "prices": "Yes: 1.8% | No: 98.2%",
    "volume": 21795286,
    "liquidity": 743978,
    "endDate": "2026-03-18",
    "dayChange": "0.20%",
    "vol24h": 3439080,
    "spread": "0.10%",
    "sortOrder": 3,
    "updatedAt": "2026-02-03T07:51:56.239688Z",
    "engine": "sniper",
    "core_topic": "Fed decision in {month}?",
    "category": "ECONOMY",
    "url": "https://polymarket.com/event/fed-decision-in-march-885",
    "strategy_tags": [
      "TAIL_RISK",
      "HIGH_CERTAINTY"
    ]
  },
  {
    "slug": "fed-decision-in-march-885",
    "ticker": "will-the-fed-decrease-interest-rates-by-50-bps-after-the-march-2026-meeting",
    "question": "50+ bps decrease",
    "eventTitle": "Fed decision in March?",
    "prices": "Yes: 1.3% | No: 98.8%",
    "volume": 19389063,
    "liquidity": 1531765,
    "endDate": "2026-03-18",
    "dayChange": "-0.20%",
    "vol24h": 4728231,
    "spread": "0.10%",
    "sortOrder": 0,
    "updatedAt": "2026-02-03T07:51:32.956934Z",
    "engine": "sniper",
    "core_topic": "Fed decision in {month}?",
    "category": "ECONOMY",
    "url": "https://polymarket.com/event/fed-decision-in-march-885",
    "strategy_tags": [
      "TAIL_RISK",
      "HIGH_CERTAINTY"
    ]
  },
  {
    "slug": "fed-decision-in-march-885",
    "ticker": "will-there-be-no-change-in-fed-interest-rates-after-the-march-2026-meeting",
    "question": "No change",
    "eventTitle": "Fed decision in March?",
    "prices": "Yes: 89.5% | No: 10.5%",
    "volume": 4812389,
    "liquidity": 1110541,
    "endDate": "2026-03-18",
    "dayChange": "0.00%",
    "vol24h": 589251,
    "spread": "1.00%",
    "sortOrder": 2,
    "updatedAt": "2026-02-03T07:51:56.009244Z",
    "engine": "sniper",
    "core_topic": "Fed decision in {month}?",
    "category": "ECONOMY",
    "url": "https://polymarket.com/event/fed-decision-in-march-885",
    "strategy_tags": [
      "RAW_MARKET"
    ]
  },
  {
    "slug": "fed-decision-in-march-885",
    "ticker": "will-the-fed-decrease-interest-rates-by-25-bps-after-the-march-2026-meeting",
    "question": "25 bps decrease",
    "eventTitle": "Fed decision in March?",
    "prices": "Yes: 7.5% | No: 92.5%",
    "volume": 4307443,
    "liquidity": 768978,
    "endDate": "2026-03-18",
    "dayChange": "0.00%",
    "vol24h": 527607,
    "spread": "1.00%",
    "sortOrder": 1,
    "updatedAt": "2026-02-03T07:51:53.455518Z",
    "engine": "sniper",
    "core_topic": "Fed decision in {month}?",
    "category": "ECONOMY",
    "url": "https://polymarket.com/event/fed-decision-in-march-885",
    "strategy_tags": [
      "RAW_MARKET"
    ]
  },
  {
    "slug": "what-price-will-bitcoin-hit-in-february-2026",
    "ticker": "will-bitcoin-reach-150k-in-february-2026",
    "question": "↑ 150,000",
    "eventTitle": "What price will Bitcoin hit in February?",
    "prices": "Yes: 0.4% | No: 99.6%",
    "volume": 1672835,
    "liquidity": 549905,
    "endDate": "2026-03-01",
    "dayChange": "0.00%",
    "vol24h": 814199,
    "spread": "0.10%",
    "sortOrder": 0,
    "updatedAt": "2026-02-03T07:51:32.517676Z",
    "engine": "sniper",
    "core_topic": "What price will Bitcoin hit in {month}?",
    "category": "CRYPTO",
    "url": "https://polymarket.com/event/what-price-will-bitcoin-hit-in-february-2026",
    "strategy_tags": [
      "TAIL_RISK",
      "HIGH_CERTAINTY"
    ]
  },
  {
    "slug": "bitcoin-above-on-february-3",
    "ticker": "bitcoin-above-90k-on-february-3",
    "question": "90,000",
    "eventTitle": "Bitcoin above ___ on February 3?",
    "prices": "Yes: 0.1% | No: 100.0%",
    "volume": 1437355,
    "liquidity": 68039,
    "endDate": "2026-02-03",
    "dayChange": "-0.10%",
    "vol24h": 1326099,
    "spread": "0.10%",
    "sortOrder": 6,
    "updatedAt": "2026-02-03T07:51:47.153087Z",
    "engine": "sniper",
    "core_topic": "Bitcoin above ___ on {date}?",
    "category": "CRYPTO",
    "url": "https://polymarket.com/event/bitcoin-above-on-february-3",
    "strategy_tags": [
      "TAIL_RISK",
      "HIGH_CERTAINTY"
    ]
  },
  {
    "slug": "bitcoin-all-time-high-by",
    "ticker": "bitcoin-all-time-high-by-march-31-2026",
    "question": "March 31, 2026",
    "eventTitle": "Bitcoin all time high by ___?",
    "prices": "Yes: 2.6% | No: 97.4%",
    "volume": 958730,
    "liquidity": 57109,
    "endDate": "2026-04-01",
    "dayChange": "-0.45%",
    "vol24h": 14033,
    "spread": "0.30%",
    "sortOrder": 0,
    "updatedAt": "2026-02-03T07:54:40.489577Z",
    "engine": "sniper",
    "core_topic": "Bitcoin all time high by ___?",
    "category": "CRYPTO",
    "url": "https://polymarket.com/event/bitcoin-all-time-high-by",
    "strategy_tags": [
      "TAIL_RISK",
      "HIGH_CERTAINTY"
    ]
  },
  {
    "slug": "bitcoin-above-on-february-3",
    "ticker": "bitcoin-above-86k-on-february-3",
    "question": "86,000",
    "eventTitle": "Bitcoin above ___ on February 3?",
    "prices": "Yes: 0.1% | No: 99.9%",
    "volume": 713273,
    "liquidity": 76948,
    "endDate": "2026-02-03",
    "dayChange": "-0.30%",
    "vol24h": 47329,
    "spread": "0.10%",
    "sortOrder": 4,
    "updatedAt": "2026-02-03T07:51:46.187372Z",
    "engine": "sniper",
    "core_topic": "Bitcoin above ___ on {date}?",
    "category": "CRYPTO",
    "url": "https://polymarket.com/event/bitcoin-above-on-february-3",
    "strategy_tags": [
      "TAIL_RISK",
      "HIGH_CERTAINTY"
    ]
  },
  {
    "slug": "how-many-fed-rate-cuts-in-2026",
    "ticker": "will-no-fed-rate-cuts-happen-in-2026",
    "question": "0 (0 bps)",
    "eventTitle": "How many Fed rate cuts in 2026?",
    "prices": "Yes: 7.0% | No: 93.0%",
    "volume": 679251,
    "liquidity": 100124,
    "endDate": "2026-12-31",
    "dayChange": "1.25%",
    "vol24h": 47021,
    "spread": "0.10%",
    "sortOrder": 0,
    "updatedAt": "2026-02-03T07:51:28.358248Z",
    "engine": "sniper",
    "core_topic": "How many Fed rate cuts in {year}?",
    "category": "ECONOMY",
    "url": "https://polymarket.com/event/how-many-fed-rate-cuts-in-2026",
    "strategy_tags": [
      "HIGH_CERTAINTY"
    ]
  },
  {
    "slug": "what-price-will-bitcoin-hit-in-february-2026",
    "ticker": "will-bitcoin-dip-to-70k-in-february-2026",
    "question": "↓ 70,000",
    "eventTitle": "What price will Bitcoin hit in February?",
    "prices": "Yes: 37.5% | No: 62.5%",
    "volume": 644886,
    "liquidity": 94214,
    "endDate": "2026-03-01",
    "dayChange": "-9.00%",
    "vol24h": 403692,
    "spread": "1.00%",
    "sortOrder": 12,
    "updatedAt": "2026-02-03T07:51:29.278639Z",
    "engine": "sniper",
    "core_topic": "What price will Bitcoin hit in {month}?",
    "category": "CRYPTO",
    "url": "https://polymarket.com/event/what-price-will-bitcoin-hit-in-february-2026",
    "strategy_tags": [
      "REFLEXIVITY_TREND"
    ]
  },
  {
    "slug": "what-will-gold-gc-hit-by-end-of-february",
    "ticker": "will-gold-gc-hit-low-4700-by-end-of-february-339-735-643-246-799-559-292-611",
    "question": "↓ $4,700",
    "eventTitle": "What will Gold (GC) hit__ by end of February?",
    "prices": "Yes: 100.0% | No: 0.1%",
    "volume": 610441,
    "liquidity": 188835,
    "endDate": "2026-02-28",
    "dayChange": "9.45%",
    "vol24h": 232500,
    "spread": "0.10%",
    "sortOrder": 13,
    "updatedAt": "2026-02-03T07:54:56.858567Z",
    "engine": "sniper",
    "core_topic": "What will Gold (GC) hit__ by end of {month}?",
    "category": "FINANCE",
    "url": "https://polymarket.com/event/what-will-gold-gc-hit-by-end-of-february",
    "strategy_tags": [
      "TAIL_RISK",
      "REFLEXIVITY_TREND",
      "HIGH_CERTAINTY"
    ]
  },
  {
    "slug": "bitcoin-above-on-february-5",
    "ticker": "bitcoin-above-76k-on-february-5",
    "question": "76,000",
    "eventTitle": "Bitcoin above ___ on February 5?",
    "prices": "Yes: 82.0% | No: 18.1%",
    "volume": 609558,
    "liquidity": 16570,
    "endDate": "2026-02-05",
    "dayChange": "27.20%",
    "vol24h": 564114,
    "spread": "0.90%",
    "sortOrder": 0,
    "updatedAt": "2026-02-03T07:51:42.548731Z",
    "engine": "sniper",
    "core_topic": "Bitcoin above ___ on {date}?",
    "category": "CRYPTO",
    "url": "https://polymarket.com/event/bitcoin-above-on-february-5",
    "strategy_tags": [
      "REFLEXIVITY_TREND",
      "HIGH_CERTAINTY"
    ]
  },
  {
    "slug": "what-price-will-bitcoin-hit-in-february-2026",
    "ticker": "will-bitcoin-reach-100k-in-february-2026",
    "question": "↑ 100,000",
    "eventTitle": "What price will Bitcoin hit in February?",
    "prices": "Yes: 5.4% | No: 94.6%",
    "volume": 516643,
    "liquidity": 96796,
    "endDate": "2026-03-01",
    "dayChange": "0.90%",
    "vol24h": 280335,
    "spread": "0.20%",
    "sortOrder": 6,
    "updatedAt": "2026-02-03T07:51:28.454936Z",
    "engine": "sniper",
    "core_topic": "What price will Bitcoin hit in {month}?",
    "category": "CRYPTO",
    "url": "https://polymarket.com/event/what-price-will-bitcoin-hit-in-february-2026",
    "strategy_tags": [
      "HIGH_CERTAINTY"
    ]
  },
  {
    "slug": "bitcoin-above-on-february-3",
    "ticker": "bitcoin-above-78k-on-february-3",
    "question": "78,000",
    "eventTitle": "Bitcoin above ___ on February 3?",
    "prices": "Yes: 73.9% | No: 26.2%",
    "volume": 501879,
    "liquidity": 37553,
    "endDate": "2026-02-03",
    "dayChange": "40.90%",
    "vol24h": 174751,
    "spread": "1.50%",
    "sortOrder": 0,
    "updatedAt": "2026-02-03T07:51:47.200039Z",
    "engine": "sniper",
    "core_topic": "Bitcoin above ___ on {date}?",
    "category": "CRYPTO",
    "url": "https://polymarket.com/event/bitcoin-above-on-february-3",
    "strategy_tags": [
      "REFLEXIVITY_TREND"
    ]
  },
  {
    "slug": "what-price-will-bitcoin-hit-in-february-2026",
    "ticker": "will-bitcoin-dip-to-60k-in-february-2026",
    "question": "↓ 60,000",
    "eventTitle": "What price will Bitcoin hit in February?",
    "prices": "Yes: 9.0% | No: 91.0%",
    "volume": 441712,
    "liquidity": 42280,
    "endDate": "2026-03-01",
    "dayChange": "-3.00%",
    "vol24h": 151059,
    "spread": "2.00%",
    "sortOrder": 14,
    "updatedAt": "2026-02-03T07:51:28.781379Z",
    "engine": "sniper",
    "core_topic": "What price will Bitcoin hit in {month}?",
    "category": "CRYPTO",
    "url": "https://polymarket.com/event/what-price-will-bitcoin-hit-in-february-2026",
    "strategy_tags": [
      "RAW_MARKET"
    ]
  },
  {
    "slug": "what-price-will-bitcoin-hit-in-february-2026",
    "ticker": "will-bitcoin-reach-125k-in-february-2026",
    "question": "↑ 125,000",
    "eventTitle": "What price will Bitcoin hit in February?",
    "prices": "Yes: 0.4% | No: 99.6%",
    "volume": 413762,
    "liquidity": 179623,
    "endDate": "2026-03-01",
    "dayChange": "-0.10%",
    "vol24h": 221599,
    "spread": "0.10%",
    "sortOrder": 1,
    "updatedAt": "2026-02-03T07:51:35.149278Z",
    "engine": "sniper",
    "core_topic": "What price will Bitcoin hit in {month}?",
    "category": "CRYPTO",
    "url": "https://polymarket.com/event/what-price-will-bitcoin-hit-in-february-2026",
    "strategy_tags": [
      "TAIL_RISK",
      "HIGH_CERTAINTY"
    ]
  },
  {
    "slug": "what-price-will-bitcoin-hit-in-february-2026",
    "ticker": "will-bitcoin-reach-85k-in-february-2026",
    "question": "↑ 85,000",
    "eventTitle": "What price will Bitcoin hit in February?",
    "prices": "Yes: 53.5% | No: 46.5%",
    "volume": 412375,
    "liquidity": 56866,
    "endDate": "2026-03-01",
    "dayChange": "13.00%",
    "vol24h": 216737,
    "spread": "1.00%",
    "sortOrder": 9,
    "updatedAt": "2026-02-03T07:51:34.0639Z",
    "engine": "sniper",
    "core_topic": "What price will Bitcoin hit in {month}?",
    "category": "CRYPTO",
    "url": "https://polymarket.com/event/what-price-will-bitcoin-hit-in-february-2026",
    "strategy_tags": [
      "REFLEXIVITY_TREND"
    ]
  },
  {
    "slug": "bitcoin-above-on-february-3",
    "ticker": "bitcoin-above-88k-on-february-3",
    "question": "88,000",
    "eventTitle": "Bitcoin above ___ on February 3?",
    "prices": "Yes: 0.1% | No: 100.0%",
    "volume": 410936,
    "liquidity": 73366,
    "endDate": "2026-02-03",
    "dayChange": "-0.65%",
    "vol24h": 205901,
    "spread": "0.10%",
    "sortOrder": 5,
    "updatedAt": "2026-02-03T07:51:36.770594Z",
    "engine": "sniper",
    "core_topic": "Bitcoin above ___ on {date}?",
    "category": "CRYPTO",
    "url": "https://polymarket.com/event/bitcoin-above-on-february-3",
    "strategy_tags": [
      "TAIL_RISK",
      "HIGH_CERTAINTY"
    ]
  },
  {
    "slug": "what-price-will-bitcoin-hit-in-february-2026",
    "ticker": "will-bitcoin-reach-90k-in-february-2026",
    "question": "↑ 90,000",
    "eventTitle": "What price will Bitcoin hit in February?",
    "prices": "Yes: 25.5% | No: 74.5%",
    "volume": 399844,
    "liquidity": 114306,
    "endDate": "2026-03-01",
    "dayChange": "6.50%",
    "vol24h": 210684,
    "spread": "1.00%",
    "sortOrder": 8,
    "updatedAt": "2026-02-03T07:51:16.477871Z",
    "engine": "sniper",
    "core_topic": "What price will Bitcoin hit in {month}?",
    "category": "CRYPTO",
    "url": "https://polymarket.com/event/what-price-will-bitcoin-hit-in-february-2026",
    "strategy_tags": [
      "REFLEXIVITY_TREND"
    ]
  },
  {
    "slug": "what-price-will-bitcoin-hit-in-february-2026",
    "ticker": "will-bitcoin-reach-95k-in-february-2026",
    "question": "↑ 95,000",
    "eventTitle": "What price will Bitcoin hit in February?",
    "prices": "Yes: 11.5% | No: 88.5%",
    "volume": 381280,
    "liquidity": 73567,
    "endDate": "2026-03-01",
    "dayChange": "3.50%",
    "vol24h": 168760,
    "spread": "1.00%",
    "sortOrder": 7,
    "updatedAt": "2026-02-03T07:51:17.651938Z",
    "engine": "sniper",
    "core_topic": "What price will Bitcoin hit in {month}?",
    "category": "CRYPTO",
    "url": "https://polymarket.com/event/what-price-will-bitcoin-hit-in-february-2026",
    "strategy_tags": [
      "RAW_MARKET"
    ]
  },
  {
    "slug": "what-price-will-bitcoin-hit-in-february-2026",
    "ticker": "will-bitcoin-dip-to-55k-in-february-2026",
    "question": "↓ 55,000",
    "eventTitle": "What price will Bitcoin hit in February?",
    "prices": "Yes: 4.9% | No: 95.2%",
    "volume": 376905,
    "liquidity": 74775,
    "endDate": "2026-03-01",
    "dayChange": "-1.40%",
    "vol24h": 201442,
    "spread": "0.10%",
    "sortOrder": 15,
    "updatedAt": "2026-02-03T07:51:24.583899Z",
    "engine": "sniper",
    "core_topic": "What price will Bitcoin hit in {month}?",
    "category": "CRYPTO",
    "url": "https://polymarket.com/event/what-price-will-bitcoin-hit-in-february-2026",
    "strategy_tags": [
      "TAIL_RISK",
      "HIGH_CERTAINTY"
    ]
  },
  {
    "slug": "what-will-gold-gc-hit-by-end-of-february",
    "ticker": "will-gold-gc-hit-high-5500-by-end-of-february-743-796-985-593-523-417-437",
    "question": "↑ $5,500",
    "eventTitle": "What will Gold (GC) hit__ by end of February?",
    "prices": "Yes: 32.2% | No: 67.8%",
    "volume": 368459,
    "liquidity": 31272,
    "endDate": "2026-02-28",
    "dayChange": "3.35%",
    "vol24h": 91389,
    "spread": "1.20%",
    "sortOrder": 7,
    "updatedAt": "2026-02-03T07:55:01.276208Z",
    "engine": "sniper",
    "core_topic": "What will Gold (GC) hit__ by end of {month}?",
    "category": "FINANCE",
    "url": "https://polymarket.com/event/what-will-gold-gc-hit-by-end-of-february",
    "strategy_tags": [
      "RAW_MARKET"
    ]
  },
  {
    "slug": "bitcoin-above-on-february-3",
    "ticker": "bitcoin-above-80k-on-february-3",
    "question": "80,000",
    "eventTitle": "Bitcoin above ___ on February 3?",
    "prices": "Yes: 21.6% | No: 78.5%",
    "volume": 365250,
    "liquidity": 42610,
    "endDate": "2026-02-03",
    "dayChange": "7.75%",
    "vol24h": 158540,
    "spread": "1.10%",
    "sortOrder": 1,
    "updatedAt": "2026-02-03T07:51:19.092594Z",
    "engine": "sniper",
    "core_topic": "Bitcoin above ___ on {date}?",
    "category": "CRYPTO",
    "url": "https://polymarket.com/event/bitcoin-above-on-february-3",
    "strategy_tags": [
      "REFLEXIVITY_TREND"
    ]
  },
  {
    "slug": "how-many-fed-rate-cuts-in-2026",
    "ticker": "will-1-fed-rate-cut-happen-in-2026",
    "question": "1 (25 bps)",
    "eventTitle": "How many Fed rate cuts in 2026?",
    "prices": "Yes: 12.5% | No: 87.5%",
    "volume": 344889,
    "liquidity": 62055,
    "endDate": "2026-12-31",
    "dayChange": "-0.50%",
    "vol24h": 17747,
    "spread": "1.00%",
    "sortOrder": 1,
    "updatedAt": "2026-02-03T07:51:53.966585Z",
    "engine": "sniper",
    "core_topic": "How many Fed rate cuts in {year}?",
    "category": "ECONOMY",
    "url": "https://polymarket.com/event/how-many-fed-rate-cuts-in-2026",
    "strategy_tags": [
      "RAW_MARKET"
    ]
  },
  {
    "slug": "what-price-will-bitcoin-hit-in-february-2026",
    "ticker": "will-bitcoin-dip-to-50k-in-february-2026",
    "question": "↓ 50,000",
    "eventTitle": "What price will Bitcoin hit in February?",
    "prices": "Yes: 1.8% | No: 98.2%",
    "volume": 342303,
    "liquidity": 91881,
    "endDate": "2026-03-01",
    "dayChange": "-0.95%",
    "vol24h": 182170,
    "spread": "0.10%",
    "sortOrder": 16,
    "updatedAt": "2026-02-03T07:51:26.616936Z",
    "engine": "sniper",
    "core_topic": "What price will Bitcoin hit in {month}?",
    "category": "CRYPTO",
    "url": "https://polymarket.com/event/what-price-will-bitcoin-hit-in-february-2026",
    "strategy_tags": [
      "TAIL_RISK",
      "HIGH_CERTAINTY"
    ]
  },
  {
    "slug": "how-many-fed-rate-cuts-in-2026",
    "ticker": "will-2-fed-rate-cuts-happen-in-2026",
    "question": "2 (50 bps)",
    "eventTitle": "How many Fed rate cuts in 2026?",
    "prices": "Yes: 24.0% | No: 76.0%",
    "volume": 337904,
    "liquidity": 80492,
    "endDate": "2026-12-31",
    "dayChange": "0.50%",
    "vol24h": 1177,
    "spread": "2.00%",
    "sortOrder": 2,
    "updatedAt": "2026-02-03T07:51:46.092567Z",
    "engine": "sniper",
    "core_topic": "How many Fed rate cuts in {year}?",
    "category": "ECONOMY",
    "url": "https://polymarket.com/event/how-many-fed-rate-cuts-in-2026",
    "strategy_tags": [
      "RAW_MARKET"
    ]
  },
  {
    "slug": "bitcoin-above-on-february-3",
    "ticker": "bitcoin-above-82k-on-february-3",
    "question": "82,000",
    "eventTitle": "Bitcoin above ___ on February 3?",
    "prices": "Yes: 2.6% | No: 97.4%",
    "volume": 328726,
    "liquidity": 30646,
    "endDate": "2026-02-03",
    "dayChange": "-4.05%",
    "vol24h": 154410,
    "spread": "0.30%",
    "sortOrder": 2,
    "updatedAt": "2026-02-03T07:51:47.090364Z",
    "engine": "sniper",
    "core_topic": "Bitcoin above ___ on {date}?",
    "category": "CRYPTO",
    "url": "https://polymarket.com/event/bitcoin-above-on-february-3",
    "strategy_tags": [
      "TAIL_RISK",
      "HIGH_CERTAINTY"
    ]
  },
  {
    "slug": "how-many-fed-rate-cuts-in-2026",
    "ticker": "will-8-fed-rate-cuts-happen-in-2026",
    "question": "8 (200 bps)",
    "eventTitle": "How many Fed rate cuts in 2026?",
    "prices": "Yes: 1.6% | No: 98.4%",
    "volume": 312473,
    "liquidity": 54173,
    "endDate": "2026-12-31",
    "dayChange": "0.00%",
    "vol24h": 677,
    "spread": "0.20%",
    "sortOrder": 8,
    "updatedAt": "2026-02-03T07:51:54.452082Z",
    "engine": "sniper",
    "core_topic": "How many Fed rate cuts in {year}?",
    "category": "ECONOMY",
    "url": "https://polymarket.com/event/how-many-fed-rate-cuts-in-2026",
    "strategy_tags": [
      "TAIL_RISK",
      "HIGH_CERTAINTY"
    ]
  },
  {
    "slug": "what-price-will-bitcoin-hit-in-february-2026",
    "ticker": "will-bitcoin-reach-110k-in-february-2026",
    "question": "↑ 110,000",
    "eventTitle": "What price will Bitcoin hit in February?",
    "prices": "Yes: 1.5% | No: 98.6%",
    "volume": 296401,
    "liquidity": 124997,
    "endDate": "2026-03-01",
    "dayChange": "0.00%",
    "vol24h": 167772,
    "spread": "0.10%",
    "sortOrder": 4,
    "updatedAt": "2026-02-03T07:51:27.250492Z",
    "engine": "sniper",
    "core_topic": "What price will Bitcoin hit in {month}?",
    "category": "CRYPTO",
    "url": "https://polymarket.com/event/what-price-will-bitcoin-hit-in-february-2026",
    "strategy_tags": [
      "TAIL_RISK",
      "HIGH_CERTAINTY"
    ]
  },
  {
    "slug": "how-many-fed-rate-cuts-in-2026",
    "ticker": "will-12-or-more-fed-rate-cuts-happen-in-2026",
    "question": "12+ (300+ bps)",
    "eventTitle": "How many Fed rate cuts in 2026?",
    "prices": "Yes: 1.9% | No: 98.0%",
    "volume": 293556,
    "liquidity": 54333,
    "endDate": "2026-12-31",
    "dayChange": "-0.30%",
    "vol24h": 3346,
    "spread": "0.10%",
    "sortOrder": 12,
    "updatedAt": "2026-02-03T07:51:48.370782Z",
    "engine": "sniper",
    "core_topic": "How many Fed rate cuts in {year}?",
    "category": "ECONOMY",
    "url": "https://polymarket.com/event/how-many-fed-rate-cuts-in-2026",
    "strategy_tags": [
      "TAIL_RISK",
      "HIGH_CERTAINTY"
    ]
  },
  {
    "slug": "how-many-fed-rate-cuts-in-2026",
    "ticker": "will-6-fed-rate-cuts-happen-in-2026",
    "question": "6 (150 bps)",
    "eventTitle": "How many Fed rate cuts in 2026?",
    "prices": "Yes: 3.6% | No: 96.4%",
    "volume": 287436,
    "liquidity": 49942,
    "endDate": "2026-12-31",
    "dayChange": "-0.20%",
    "vol24h": 8961,
    "spread": "0.10%",
    "sortOrder": 6,
    "updatedAt": "2026-02-03T07:51:09.982224Z",
    "engine": "sniper",
    "core_topic": "How many Fed rate cuts in {year}?",
    "category": "ECONOMY",
    "url": "https://polymarket.com/event/how-many-fed-rate-cuts-in-2026",
    "strategy_tags": [
      "TAIL_RISK",
      "HIGH_CERTAINTY"
    ]
  },
  {
    "slug": "how-many-fed-rate-cuts-in-2026",
    "ticker": "will-11-fed-rate-cuts-happen-in-2026",
    "question": "11 (275 bps)",
    "eventTitle": "How many Fed rate cuts in 2026?",
    "prices": "Yes: 0.7% | No: 99.4%",
    "volume": 275915,
    "liquidity": 67562,
    "endDate": "2026-12-31",
    "dayChange": "-0.10%",
    "vol24h": 1175,
    "spread": "0.10%",
    "sortOrder": 11,
    "updatedAt": "2026-02-03T07:51:33.387302Z",
    "engine": "sniper",
    "core_topic": "How many Fed rate cuts in {year}?",
    "category": "ECONOMY",
    "url": "https://polymarket.com/event/how-many-fed-rate-cuts-in-2026",
    "strategy_tags": [
      "TAIL_RISK",
      "HIGH_CERTAINTY"
    ]
  },
  {
    "slug": "bitcoin-above-on-february-3",
    "ticker": "bitcoin-above-84k-on-february-3",
    "question": "84,000",
    "eventTitle": "Bitcoin above ___ on February 3?",
    "prices": "Yes: 0.4% | No: 99.7%",
    "volume": 269880,
    "liquidity": 59513,
    "endDate": "2026-02-03",
    "dayChange": "-2.00%",
    "vol24h": 69208,
    "spread": "0.10%",
    "sortOrder": 3,
    "updatedAt": "2026-02-03T07:51:36.171569Z",
    "engine": "sniper",
    "core_topic": "Bitcoin above ___ on {date}?",
    "category": "CRYPTO",
    "url": "https://polymarket.com/event/bitcoin-above-on-february-3",
    "strategy_tags": [
      "TAIL_RISK",
      "HIGH_CERTAINTY"
    ]
  },
  {
    "slug": "what-price-will-bitcoin-hit-in-february-2026",
    "ticker": "will-bitcoin-reach-105k-in-february-2026",
    "question": "↑ 105,000",
    "eventTitle": "What price will Bitcoin hit in February?",
    "prices": "Yes: 2.9% | No: 97.0%",
    "volume": 265003,
    "liquidity": 81412,
    "endDate": "2026-03-01",
    "dayChange": "0.30%",
    "vol24h": 121718,
    "spread": "0.10%",
    "sortOrder": 5,
    "updatedAt": "2026-02-03T07:51:47.687752Z",
    "engine": "sniper",
    "core_topic": "What price will Bitcoin hit in {month}?",
    "category": "CRYPTO",
    "url": "https://polymarket.com/event/what-price-will-bitcoin-hit-in-february-2026",
    "strategy_tags": [
      "TAIL_RISK",
      "HIGH_CERTAINTY"
    ]
  },
  {
    "slug": "how-many-fed-rate-cuts-in-2026",
    "ticker": "will-10-fed-rate-cuts-happen-in-2026",
    "question": "10 (250 bps)",
    "eventTitle": "How many Fed rate cuts in 2026?",
    "prices": "Yes: 0.7% | No: 99.4%",
    "volume": 259676,
    "liquidity": 51971,
    "endDate": "2026-12-31",
    "dayChange": "-0.05%",
    "vol24h": 118,
    "spread": "0.10%",
    "sortOrder": 10,
    "updatedAt": "2026-02-03T07:51:55.016475Z",
    "engine": "sniper",
    "core_topic": "How many Fed rate cuts in {year}?",
    "category": "ECONOMY",
    "url": "https://polymarket.com/event/how-many-fed-rate-cuts-in-2026",
    "strategy_tags": [
      "TAIL_RISK",
      "HIGH_CERTAINTY"
    ]
  },
  {
    "slug": "how-many-fed-rate-cuts-in-2026",
    "ticker": "will-3-fed-rate-cuts-happen-in-2026",
    "question": "3 (75 bps)",
    "eventTitle": "How many Fed rate cuts in 2026?",
    "prices": "Yes: 25.5% | No: 74.5%",
    "volume": 250759,
    "liquidity": 73872,
    "endDate": "2026-12-31",
    "dayChange": "-0.50%",
    "vol24h": 4045,
    "spread": "1.00%",
    "sortOrder": 3,
    "updatedAt": "2026-02-03T07:51:09.797062Z",
    "engine": "sniper",
    "core_topic": "How many Fed rate cuts in {year}?",
    "category": "ECONOMY",
    "url": "https://polymarket.com/event/how-many-fed-rate-cuts-in-2026",
    "strategy_tags": [
      "RAW_MARKET"
    ]
  },
  {
    "slug": "what-price-will-bitcoin-hit-in-february-2026",
    "ticker": "will-bitcoin-reach-115k-in-february-2026",
    "question": "↑ 115,000",
    "eventTitle": "What price will Bitcoin hit in February?",
    "prices": "Yes: 0.9% | No: 99.2%",
    "volume": 250100,
    "liquidity": 127717,
    "endDate": "2026-03-01",
    "dayChange": "-0.20%",
    "vol24h": 98875,
    "spread": "0.10%",
    "sortOrder": 3,
    "updatedAt": "2026-02-03T07:51:26.435966Z",
    "engine": "sniper",
    "core_topic": "What price will Bitcoin hit in {month}?",
    "category": "CRYPTO",
    "url": "https://polymarket.com/event/what-price-will-bitcoin-hit-in-february-2026",
    "strategy_tags": [
      "TAIL_RISK",
      "HIGH_CERTAINTY"
    ]
  },
  {
    "slug": "what-price-will-bitcoin-hit-in-february-2026",
    "ticker": "will-bitcoin-reach-120k-in-february-2026",
    "question": "↑ 120,000",
    "eventTitle": "What price will Bitcoin hit in February?",
    "prices": "Yes: 0.5% | No: 99.5%",
    "volume": 246159,
    "liquidity": 178023,
    "endDate": "2026-03-01",
    "dayChange": "-0.20%",
    "vol24h": 126048,
    "spread": "0.10%",
    "sortOrder": 2,
    "updatedAt": "2026-02-03T07:51:32.714697Z",
    "engine": "sniper",
    "core_topic": "What price will Bitcoin hit in {month}?",
    "category": "CRYPTO",
    "url": "https://polymarket.com/event/what-price-will-bitcoin-hit-in-february-2026",
    "strategy_tags": [
      "TAIL_RISK",
      "HIGH_CERTAINTY"
    ]
  },
  {
    "slug": "what-price-will-bitcoin-hit-in-february-2026",
    "ticker": "will-bitcoin-dip-to-65k-in-february-2026",
    "question": "↓ 65,000",
    "eventTitle": "What price will Bitcoin hit in February?",
    "prices": "Yes: 20.0% | No: 80.0%",
    "volume": 241109,
    "liquidity": 151093,
    "endDate": "2026-03-01",
    "dayChange": "-4.50%",
    "vol24h": 91086,
    "spread": "2.00%",
    "sortOrder": 13,
    "updatedAt": "2026-02-03T07:51:30.382827Z",
    "engine": "sniper",
    "core_topic": "What price will Bitcoin hit in {month}?",
    "category": "CRYPTO",
    "url": "https://polymarket.com/event/what-price-will-bitcoin-hit-in-february-2026",
    "strategy_tags": [
      "RAW_MARKET"
    ]
  },
  {
    "slug": "how-many-fed-rate-cuts-in-2026",
    "ticker": "will-7-fed-rate-cuts-happen-in-2026",
    "question": "7 (175 bps)",
    "eventTitle": "How many Fed rate cuts in 2026?",
    "prices": "Yes: 2.1% | No: 98.0%",
    "volume": 239444,
    "liquidity": 56126,
    "endDate": "2026-12-31",
    "dayChange": "-0.65%",
    "vol24h": 7586,
    "spread": "0.10%",
    "sortOrder": 7,
    "updatedAt": "2026-02-03T07:51:41.102237Z",
    "engine": "sniper",
    "core_topic": "How many Fed rate cuts in {year}?",
    "category": "ECONOMY",
    "url": "https://polymarket.com/event/how-many-fed-rate-cuts-in-2026",
    "strategy_tags": [
      "TAIL_RISK",
      "HIGH_CERTAINTY"
    ]
  },
  {
    "slug": "how-many-fed-rate-cuts-in-2026",
    "ticker": "will-9-fed-rate-cuts-happen-in-2026",
    "question": "9 (225 bps)",
    "eventTitle": "How many Fed rate cuts in 2026?",
    "prices": "Yes: 0.8% | No: 99.3%",
    "volume": 239012,
    "liquidity": 49454,
    "endDate": "2026-12-31",
    "dayChange": "-0.05%",
    "vol24h": 219,
    "spread": "0.10%",
    "sortOrder": 9,
    "updatedAt": "2026-02-03T07:51:32.76616Z",
    "engine": "sniper",
    "core_topic": "How many Fed rate cuts in {year}?",
    "category": "ECONOMY",
    "url": "https://polymarket.com/event/how-many-fed-rate-cuts-in-2026",
    "strategy_tags": [
      "TAIL_RISK",
      "HIGH_CERTAINTY"
    ]
  },
  {
    "slug": "what-will-gold-gc-hit-by-end-of-february",
    "ticker": "will-gold-gc-hit-high-10000-by-end-of-february",
    "question": "↑ $10,000",
    "eventTitle": "What will Gold (GC) hit__ by end of February?",
    "prices": "Yes: 0.4% | No: 99.7%",
    "volume": 237540,
    "liquidity": 74080,
    "endDate": "2026-02-28",
    "dayChange": "-0.30%",
    "vol24h": 72468,
    "spread": "0.10%",
    "sortOrder": 0,
    "updatedAt": "2026-02-03T07:54:30.508335Z",
    "engine": "sniper",
    "core_topic": "What will Gold (GC) hit__ by end of {month}?",
    "category": "FINANCE",
    "url": "https://polymarket.com/event/what-will-gold-gc-hit-by-end-of-february",
    "strategy_tags": [
      "TAIL_RISK",
      "HIGH_CERTAINTY"
    ]
  },
  {
    "slug": "how-many-fed-rate-cuts-in-2026",
    "ticker": "will-5-fed-rate-cuts-happen-in-2026",
    "question": "5 (125 bps)",
    "eventTitle": "How many Fed rate cuts in 2026?",
    "prices": "Yes: 6.0% | No: 94.0%",
    "volume": 232482,
    "liquidity": 83726,
    "endDate": "2026-12-31",
    "dayChange": "0.00%",
    "vol24h": 820,
    "spread": "2.00%",
    "sortOrder": 5,
    "updatedAt": "2026-02-03T07:51:26.183862Z",
    "engine": "sniper",
    "core_topic": "How many Fed rate cuts in {year}?",
    "category": "ECONOMY",
    "url": "https://polymarket.com/event/how-many-fed-rate-cuts-in-2026",
    "strategy_tags": [
      "RAW_MARKET"
    ]
  },
  {
    "slug": "what-price-will-bitcoin-hit-in-february-2026",
    "ticker": "will-bitcoin-dip-to-35k-in-february-2026",
    "question": "↓ 35,000",
    "eventTitle": "What price will Bitcoin hit in February?",
    "prices": "Yes: 0.4% | No: 99.6%",
    "volume": 225947,
    "liquidity": 120522,
    "endDate": "2026-03-01",
    "dayChange": "-0.30%",
    "vol24h": 118949,
    "spread": "0.30%",
    "sortOrder": 19,
    "updatedAt": "2026-02-03T07:51:26.41726Z",
    "engine": "sniper",
    "core_topic": "What price will Bitcoin hit in {month}?",
    "category": "CRYPTO",
    "url": "https://polymarket.com/event/what-price-will-bitcoin-hit-in-february-2026",
    "strategy_tags": [
      "TAIL_RISK",
      "HIGH_CERTAINTY"
    ]
  },
  {
    "slug": "how-many-fed-rate-cuts-in-2026",
    "ticker": "will-4-fed-rate-cuts-happen-in-2026",
    "question": "4 (100 bps)",
    "eventTitle": "How many Fed rate cuts in 2026?",
    "prices": "Yes: 15.0% | No: 85.0%",
    "volume": 220750,
    "liquidity": 84907,
    "endDate": "2026-12-31",
    "dayChange": "-1.50%",
    "vol24h": 1437,
    "spread": "2.00%",
    "sortOrder": 4,
    "updatedAt": "2026-02-03T07:51:12.361813Z",
    "engine": "sniper",
    "core_topic": "How many Fed rate cuts in {year}?",
    "category": "ECONOMY",
    "url": "https://polymarket.com/event/how-many-fed-rate-cuts-in-2026",
    "strategy_tags": [
      "RAW_MARKET"
    ]
  },
  {
    "slug": "bitcoin-all-time-high-by",
    "ticker": "bitcoin-all-time-high-by-december-31-2026",
    "question": "December 31, 2026",
    "eventTitle": "Bitcoin all time high by ___?",
    "prices": "Yes: 29.0% | No: 71.0%",
    "volume": 218862,
    "liquidity": 30399,
    "endDate": "2027-01-01",
    "dayChange": "0.50%",
    "vol24h": 3638,
    "spread": "2.00%",
    "sortOrder": 3,
    "updatedAt": "2026-02-03T07:54:58.740291Z",
    "engine": "sniper",
    "core_topic": "Bitcoin all time high by ___?",
    "category": "CRYPTO",
    "url": "https://polymarket.com/event/bitcoin-all-time-high-by",
    "strategy_tags": [
      "RAW_MARKET"
    ]
  },
  {
    "slug": "what-price-will-bitcoin-hit-in-february-2026",
    "ticker": "will-bitcoin-dip-to-45k-in-february-2026",
    "question": "↓ 45,000",
    "eventTitle": "What price will Bitcoin hit in February?",
    "prices": "Yes: 1.4% | No: 98.7%",
    "volume": 217030,
    "liquidity": 81754,
    "endDate": "2026-03-01",
    "dayChange": "-0.30%",
    "vol24h": 105449,
    "spread": "0.10%",
    "sortOrder": 17,
    "updatedAt": "2026-02-03T07:51:23.358644Z",
    "engine": "sniper",
    "core_topic": "What price will Bitcoin hit in {month}?",
    "category": "CRYPTO",
    "url": "https://polymarket.com/event/what-price-will-bitcoin-hit-in-february-2026",
    "strategy_tags": [
      "TAIL_RISK",
      "HIGH_CERTAINTY"
    ]
  },
  {
    "slug": "bitcoin-all-time-high-by",
    "ticker": "bitcoin-all-time-high-by-june-30-2026",
    "question": "June 30, 2026",
    "eventTitle": "Bitcoin all time high by ___?",
    "prices": "Yes: 12.0% | No: 88.0%",
    "volume": 186472,
    "liquidity": 21094,
    "endDate": "2026-07-01",
    "dayChange": "2.00%",
    "vol24h": 6267,
    "spread": "2.00%",
    "sortOrder": 1,
    "updatedAt": "2026-02-03T07:54:39.307951Z",
    "engine": "sniper",
    "core_topic": "Bitcoin all time high by ___?",
    "category": "CRYPTO",
    "url": "https://polymarket.com/event/bitcoin-all-time-high-by",
    "strategy_tags": [
      "RAW_MARKET"
    ]
  },
  {
    "slug": "bitcoin-above-on-february-3",
    "ticker": "bitcoin-above-92k-on-february-3",
    "question": "92,000",
    "eventTitle": "Bitcoin above ___ on February 3?",
    "prices": "Yes: 0.1% | No: 100.0%",
    "volume": 141099,
    "liquidity": 91746,
    "endDate": "2026-02-03",
    "dayChange": "-0.10%",
    "vol24h": 127681,
    "spread": "0.10%",
    "sortOrder": 7,
    "updatedAt": "2026-02-03T07:51:30.709855Z",
    "engine": "sniper",
    "core_topic": "Bitcoin above ___ on {date}?",
    "category": "CRYPTO",
    "url": "https://polymarket.com/event/bitcoin-above-on-february-3",
    "strategy_tags": [
      "TAIL_RISK",
      "HIGH_CERTAINTY"
    ]
  },
  {
    "slug": "what-will-gold-gc-hit-by-end-of-february",
    "ticker": "will-gold-gc-hit-low-3000-by-end-of-february-957-911-432-757-792-499",
    "question": "↓ $3,000",
    "eventTitle": "What will Gold (GC) hit__ by end of February?",
    "prices": "Yes: 1.6% | No: 98.4%",
    "volume": 140572,
    "liquidity": 65811,
    "endDate": "2026-02-28",
    "dayChange": "-2.55%",
    "vol24h": 75758,
    "spread": "0.20%",
    "sortOrder": 19,
    "updatedAt": "2026-02-03T07:54:29.632523Z",
    "engine": "sniper",
    "core_topic": "What will Gold (GC) hit__ by end of {month}?",
    "category": "FINANCE",
    "url": "https://polymarket.com/event/what-will-gold-gc-hit-by-end-of-february",
    "strategy_tags": [
      "TAIL_RISK",
      "HIGH_CERTAINTY"
    ]
  },
  {
    "slug": "bitcoin-price-on-february-3",
    "ticker": "will-the-price-of-bitcoin-be-between-86000-88000-on-february-3",
    "question": "86,000-88,000",
    "eventTitle": "Bitcoin price on February 3?",
    "prices": "Yes: 0.1% | No: 99.9%",
    "volume": 137469,
    "liquidity": 42312,
    "endDate": "2026-02-03",
    "dayChange": "-0.35%",
    "vol24h": 12836,
    "spread": "0.10%",
    "sortOrder": 4,
    "updatedAt": "2026-02-03T07:51:16.733563Z",
    "engine": "sniper",
    "core_topic": "Bitcoin price on {date}?",
    "category": "CRYPTO",
    "url": "https://polymarket.com/event/bitcoin-price-on-february-3",
    "strategy_tags": [
      "TAIL_RISK",
      "HIGH_CERTAINTY"
    ]
  },
  {
    "slug": "what-will-gold-gc-hit-by-end-of-february",
    "ticker": "will-gold-gc-hit-high-6400-by-end-of-february-581-221-834-595-555",
    "question": "↑ $6,400",
    "eventTitle": "What will Gold (GC) hit__ by end of February?",
    "prices": "Yes: 3.9% | No: 96.2%",
    "volume": 132526,
    "liquidity": 43754,
    "endDate": "2026-02-28",
    "dayChange": "-0.20%",
    "vol24h": 38597,
    "spread": "0.30%",
    "sortOrder": 3,
    "updatedAt": "2026-02-03T07:54:31.58856Z",
    "engine": "sniper",
    "core_topic": "What will Gold (GC) hit__ by end of {month}?",
    "category": "FINANCE",
    "url": "https://polymarket.com/event/what-will-gold-gc-hit-by-end-of-february",
    "strategy_tags": [
      "TAIL_RISK",
      "HIGH_CERTAINTY"
    ]
  },
  {
    "slug": "bitcoin-above-on-february-4",
    "ticker": "bitcoin-above-80k-on-february-4",
    "question": "80,000",
    "eventTitle": "Bitcoin above ___ on February 4?",
    "prices": "Yes: 31.8% | No: 68.3%",
    "volume": 131990,
    "liquidity": 16834,
    "endDate": "2026-02-04",
    "dayChange": "12.50%",
    "vol24h": 41533,
    "spread": "2.50%",
    "sortOrder": 0,
    "updatedAt": "2026-02-03T07:51:18.24023Z",
    "engine": "sniper",
    "core_topic": "Bitcoin above ___ on {date}?",
    "category": "CRYPTO",
    "url": "https://polymarket.com/event/bitcoin-above-on-february-4",
    "strategy_tags": [
      "REFLEXIVITY_TREND"
    ]
  },
  {
    "slug": "what-price-will-bitcoin-hit-in-february-2026",
    "ticker": "will-bitcoin-dip-to-40k-in-february-2026",
    "question": "↓ 40,000",
    "eventTitle": "What price will Bitcoin hit in February?",
    "prices": "Yes: 0.9% | No: 99.1%",
    "volume": 129850,
    "liquidity": 88238,
    "endDate": "2026-03-01",
    "dayChange": "-0.25%",
    "vol24h": 41469,
    "spread": "0.20%",
    "sortOrder": 18,
    "updatedAt": "2026-02-03T07:51:16.80444Z",
    "engine": "sniper",
    "core_topic": "What price will Bitcoin hit in {month}?",
    "category": "CRYPTO",
    "url": "https://polymarket.com/event/what-price-will-bitcoin-hit-in-february-2026",
    "strategy_tags": [
      "TAIL_RISK",
      "HIGH_CERTAINTY"
    ]
  },
  {
    "slug": "bitcoin-price-on-february-3",
    "ticker": "will-the-price-of-bitcoin-be-less-than-80000-on-february-3",
    "question": "<80,000",
    "eventTitle": "Bitcoin price on February 3?",
    "prices": "Yes: 79.2% | No: 20.8%",
    "volume": 129223,
    "liquidity": 6054,
    "endDate": "2026-02-03",
    "dayChange": "-4.60%",
    "vol24h": 29616,
    "spread": "1.00%",
    "sortOrder": 0,
    "updatedAt": "2026-02-03T07:51:45.566974Z",
    "engine": "sniper",
    "core_topic": "Bitcoin price on {date}?",
    "category": "CRYPTO",
    "url": "https://polymarket.com/event/bitcoin-price-on-february-3",
    "strategy_tags": [
      "RAW_MARKET"
    ]
  },
  {
    "slug": "what-will-gold-gc-hit-by-end-of-february",
    "ticker": "will-gold-gc-hit-high-6000-by-end-of-february-957-635-788-121-773-745-586",
    "question": "↑ $6,000",
    "eventTitle": "What will Gold (GC) hit__ by end of February?",
    "prices": "Yes: 10.5% | No: 89.5%",
    "volume": 125034,
    "liquidity": 99444,
    "endDate": "2026-02-28",
    "dayChange": "1.00%",
    "vol24h": 35344,
    "spread": "1.00%",
    "sortOrder": 5,
    "updatedAt": "2026-02-03T07:55:01.027222Z",
    "engine": "sniper",
    "core_topic": "What will Gold (GC) hit__ by end of {month}?",
    "category": "FINANCE",
    "url": "https://polymarket.com/event/what-will-gold-gc-hit-by-end-of-february",
    "strategy_tags": [
      "RAW_MARKET"
    ]
  },
  {
    "slug": "what-will-gold-gc-hit-by-end-of-february",
    "ticker": "will-gold-gc-hit-high-7000-by-end-of-february-271-168-354-381-713",
    "question": "↑ $7,000",
    "eventTitle": "What will Gold (GC) hit__ by end of February?",
    "prices": "Yes: 1.3% | No: 98.7%",
    "volume": 116500,
    "liquidity": 85799,
    "endDate": "2026-02-28",
    "dayChange": "-1.05%",
    "vol24h": 68086,
    "spread": "0.20%",
    "sortOrder": 1,
    "updatedAt": "2026-02-03T07:54:32.895088Z",
    "engine": "sniper",
    "core_topic": "What will Gold (GC) hit__ by end of {month}?",
    "category": "FINANCE",
    "url": "https://polymarket.com/event/what-will-gold-gc-hit-by-end-of-february",
    "strategy_tags": [
      "TAIL_RISK",
      "HIGH_CERTAINTY"
    ]
  },
  {
    "slug": "bitcoin-above-on-february-4",
    "ticker": "bitcoin-above-92k-on-february-4",
    "question": "92,000",
    "eventTitle": "Bitcoin above ___ on February 4?",
    "prices": "Yes: 0.2% | No: 99.8%",
    "volume": 97240,
    "liquidity": 21743,
    "endDate": "2026-02-04",
    "dayChange": "-0.45%",
    "vol24h": 10250,
    "spread": "0.20%",
    "sortOrder": 6,
    "updatedAt": "2026-02-03T07:51:42.805819Z",
    "engine": "sniper",
    "core_topic": "Bitcoin above ___ on {date}?",
    "category": "CRYPTO",
    "url": "https://polymarket.com/event/bitcoin-above-on-february-4",
    "strategy_tags": [
      "TAIL_RISK",
      "HIGH_CERTAINTY"
    ]
  },
  {
    "slug": "bitcoin-above-on-february-4",
    "ticker": "bitcoin-above-94k-on-february-4",
    "question": "94,000",
    "eventTitle": "Bitcoin above ___ on February 4?",
    "prices": "Yes: 0.1% | No: 100.0%",
    "volume": 95991,
    "liquidity": 45263,
    "endDate": "2026-02-04",
    "dayChange": "-0.30%",
    "vol24h": 9955,
    "spread": "0.10%",
    "sortOrder": 7,
    "updatedAt": "2026-02-03T07:51:17.297659Z",
    "engine": "sniper",
    "core_topic": "Bitcoin above ___ on {date}?",
    "category": "CRYPTO",
    "url": "https://polymarket.com/event/bitcoin-above-on-february-4",
    "strategy_tags": [
      "TAIL_RISK",
      "HIGH_CERTAINTY"
    ]
  },
  {
    "slug": "bitcoin-all-time-high-by",
    "ticker": "bitcoin-all-time-high-by-september-30-2026",
    "question": "September 30, 2026",
    "eventTitle": "Bitcoin all time high by ___?",
    "prices": "Yes: 17.5% | No: 82.5%",
    "volume": 95311,
    "liquidity": 18927,
    "endDate": "2026-10-01",
    "dayChange": "1.00%",
    "vol24h": 1706,
    "spread": "1.00%",
    "sortOrder": 2,
    "updatedAt": "2026-02-03T07:54:45.09635Z",
    "engine": "sniper",
    "core_topic": "Bitcoin all time high by ___?",
    "category": "CRYPTO",
    "url": "https://polymarket.com/event/bitcoin-all-time-high-by",
    "strategy_tags": [
      "RAW_MARKET"
    ]
  },
  {
    "slug": "what-will-gold-gc-hit-by-end-of-february",
    "ticker": "will-gold-gc-hit-low-4600-by-end-of-february-292-259-212-256-398-758-656-625",
    "question": "↓ $4,600",
    "eventTitle": "What will Gold (GC) hit__ by end of February?",
    "prices": "Yes: 51.7% | No: 48.3%",
    "volume": 90640,
    "liquidity": 5623,
    "endDate": "2026-02-28",
    "dayChange": "-34.05%",
    "vol24h": 31167,
    "spread": "3.20%",
    "sortOrder": 14,
    "updatedAt": "2026-02-03T07:54:33.222793Z",
    "engine": "sniper",
    "core_topic": "What will Gold (GC) hit__ by end of {month}?",
    "category": "FINANCE",
    "url": "https://polymarket.com/event/what-will-gold-gc-hit-by-end-of-february",
    "strategy_tags": [
      "REFLEXIVITY_TREND"
    ]
  },
  {
    "slug": "bitcoin-above-on-february-4",
    "ticker": "bitcoin-above-82k-on-february-4",
    "question": "82,000",
    "eventTitle": "Bitcoin above ___ on February 4?",
    "prices": "Yes: 9.5% | No: 90.5%",
    "volume": 89157,
    "liquidity": 16210,
    "endDate": "2026-02-04",
    "dayChange": "2.55%",
    "vol24h": 33396,
    "spread": "0.60%",
    "sortOrder": 1,
    "updatedAt": "2026-02-03T07:51:33.897112Z",
    "engine": "sniper",
    "core_topic": "Bitcoin above ___ on {date}?",
    "category": "CRYPTO",
    "url": "https://polymarket.com/event/bitcoin-above-on-february-4",
    "strategy_tags": [
      "HIGH_CERTAINTY"
    ]
  },
  {
    "slug": "bitcoin-above-on-february-5",
    "ticker": "bitcoin-above-80k-on-february-5",
    "question": "80,000",
    "eventTitle": "Bitcoin above ___ on February 5?",
    "prices": "Yes: 36.0% | No: 64.0%",
    "volume": 84126,
    "liquidity": 16084,
    "endDate": "2026-02-05",
    "dayChange": "13.00%",
    "vol24h": 10709,
    "spread": "2.00%",
    "sortOrder": 2,
    "updatedAt": "2026-02-03T07:51:33.783541Z",
    "engine": "sniper",
    "core_topic": "Bitcoin above ___ on {date}?",
    "category": "CRYPTO",
    "url": "https://polymarket.com/event/bitcoin-above-on-february-5",
    "strategy_tags": [
      "REFLEXIVITY_TREND"
    ]
  },
  {
    "slug": "bitcoin-above-on-february-3",
    "ticker": "bitcoin-above-94k-on-february-3",
    "question": "94,000",
    "eventTitle": "Bitcoin above ___ on February 3?",
    "prices": "Yes: 0.1% | No: 100.0%",
    "volume": 83701,
    "liquidity": 90266,
    "endDate": "2026-02-03",
    "dayChange": "0.00%",
    "vol24h": 76872,
    "spread": "0.10%",
    "sortOrder": 8,
    "updatedAt": "2026-02-03T07:51:23.830879Z",
    "engine": "sniper",
    "core_topic": "Bitcoin above ___ on {date}?",
    "category": "CRYPTO",
    "url": "https://polymarket.com/event/bitcoin-above-on-february-3",
    "strategy_tags": [
      "TAIL_RISK",
      "HIGH_CERTAINTY"
    ]
  },
  {
    "slug": "what-will-gold-gc-hit-by-end-of-february",
    "ticker": "will-gold-gc-hit-high-5800-by-end-of-february-759-378-429-713-662-579",
    "question": "↑ $5,800",
    "eventTitle": "What will Gold (GC) hit__ by end of February?",
    "prices": "Yes: 15.5% | No: 84.5%",
    "volume": 82959,
    "liquidity": 44944,
    "endDate": "2026-02-28",
    "dayChange": "4.50%",
    "vol24h": 21518,
    "spread": "1.00%",
    "sortOrder": 6,
    "updatedAt": "2026-02-03T07:54:30.296179Z",
    "engine": "sniper",
    "core_topic": "What will Gold (GC) hit__ by end of {month}?",
    "category": "FINANCE",
    "url": "https://polymarket.com/event/what-will-gold-gc-hit-by-end-of-february",
    "strategy_tags": [
      "RAW_MARKET"
    ]
  },
  {
    "slug": "bitcoin-price-on-february-3",
    "ticker": "will-the-price-of-bitcoin-be-between-84000-86000-on-february-3",
    "question": "84,000-86,000",
    "eventTitle": "Bitcoin price on February 3?",
    "prices": "Yes: 0.4% | No: 99.6%",
    "volume": 75662,
    "liquidity": 20464,
    "endDate": "2026-02-03",
    "dayChange": "-1.40%",
    "vol24h": 17760,
    "spread": "0.20%",
    "sortOrder": 3,
    "updatedAt": "2026-02-03T07:51:24.831531Z",
    "engine": "sniper",
    "core_topic": "Bitcoin price on {date}?",
    "category": "CRYPTO",
    "url": "https://polymarket.com/event/bitcoin-price-on-february-3",
    "strategy_tags": [
      "TAIL_RISK",
      "HIGH_CERTAINTY"
    ]
  },
  {
    "slug": "bitcoin-above-on-february-4",
    "ticker": "bitcoin-above-84k-on-february-4",
    "question": "84,000",
    "eventTitle": "Bitcoin above ___ on February 4?",
    "prices": "Yes: 2.5% | No: 97.5%",
    "volume": 73106,
    "liquidity": 18244,
    "endDate": "2026-02-04",
    "dayChange": "-1.50%",
    "vol24h": 29656,
    "spread": "0.20%",
    "sortOrder": 2,
    "updatedAt": "2026-02-03T07:51:45.002229Z",
    "engine": "sniper",
    "core_topic": "Bitcoin above ___ on {date}?",
    "category": "CRYPTO",
    "url": "https://polymarket.com/event/bitcoin-above-on-february-4",
    "strategy_tags": [
      "TAIL_RISK",
      "HIGH_CERTAINTY"
    ]
  },
  {
    "slug": "bitcoin-price-on-february-3",
    "ticker": "will-the-price-of-bitcoin-be-between-88000-90000-on-february-3",
    "question": "88,000-90,000",
    "eventTitle": "Bitcoin price on February 3?",
    "prices": "Yes: 0.1% | No: 100.0%",
    "volume": 70586,
    "liquidity": 22572,
    "endDate": "2026-02-03",
    "dayChange": "-0.35%",
    "vol24h": 26314,
    "spread": "0.10%",
    "sortOrder": 5,
    "updatedAt": "2026-02-03T07:51:27.478877Z",
    "engine": "sniper",
    "core_topic": "Bitcoin price on {date}?",
    "category": "CRYPTO",
    "url": "https://polymarket.com/event/bitcoin-price-on-february-3",
    "strategy_tags": [
      "TAIL_RISK",
      "HIGH_CERTAINTY"
    ]
  },
  {
    "slug": "bitcoin-price-on-february-3",
    "ticker": "will-the-price-of-bitcoin-be-between-90000-92000-on-february-3",
    "question": "90,000-92,000",
    "eventTitle": "Bitcoin price on February 3?",
    "prices": "Yes: 0.1% | No: 100.0%",
    "volume": 70002,
    "liquidity": 23626,
    "endDate": "2026-02-03",
    "dayChange": "-0.15%",
    "vol24h": 34555,
    "spread": "0.10%",
    "sortOrder": 6,
    "updatedAt": "2026-02-03T07:51:43.006726Z",
    "engine": "sniper",
    "core_topic": "Bitcoin price on {date}?",
    "category": "CRYPTO",
    "url": "https://polymarket.com/event/bitcoin-price-on-february-3",
    "strategy_tags": [
      "TAIL_RISK",
      "HIGH_CERTAINTY"
    ]
  },
  {
    "slug": "what-will-gold-gc-hit-by-end-of-february",
    "ticker": "will-gold-gc-hit-high-6600-by-end-of-february-828-163-164-179-126-514",
    "question": "↑ $6,600",
    "eventTitle": "What will Gold (GC) hit__ by end of February?",
    "prices": "Yes: 2.5% | No: 97.5%",
    "volume": 65026,
    "liquidity": 48457,
    "endDate": "2026-02-28",
    "dayChange": "0.55%",
    "vol24h": 30146,
    "spread": "0.40%",
    "sortOrder": 2,
    "updatedAt": "2026-02-03T07:54:55.981148Z",
    "engine": "sniper",
    "core_topic": "What will Gold (GC) hit__ by end of {month}?",
    "category": "FINANCE",
    "url": "https://polymarket.com/event/what-will-gold-gc-hit-by-end-of-february",
    "strategy_tags": [
      "TAIL_RISK",
      "HIGH_CERTAINTY"
    ]
  },
  {
    "slug": "bitcoin-above-on-february-5",
    "ticker": "bitcoin-above-84k-on-february-5",
    "question": "84,000",
    "eventTitle": "Bitcoin above ___ on February 5?",
    "prices": "Yes: 5.3% | No: 94.7%",
    "volume": 63850,
    "liquidity": 18656,
    "endDate": "2026-02-05",
    "dayChange": "0.40%",
    "vol24h": 13769,
    "spread": "0.30%",
    "sortOrder": 4,
    "updatedAt": "2026-02-03T07:54:39.455824Z",
    "engine": "sniper",
    "core_topic": "Bitcoin above ___ on {date}?",
    "category": "CRYPTO",
    "url": "https://polymarket.com/event/bitcoin-above-on-february-5",
    "strategy_tags": [
      "HIGH_CERTAINTY"
    ]
  },
  {
    "slug": "bitcoin-price-on-february-3",
    "ticker": "will-the-price-of-bitcoin-be-between-80000-82000-on-february-3",
    "question": "80,000-82,000",
    "eventTitle": "Bitcoin price on February 3?",
    "prices": "Yes: 17.3% | No: 82.7%",
    "volume": 63746,
    "liquidity": 11167,
    "endDate": "2026-02-03",
    "dayChange": "8.75%",
    "vol24h": 31332,
    "spread": "1.30%",
    "sortOrder": 1,
    "updatedAt": "2026-02-03T07:51:44.144366Z",
    "engine": "sniper",
    "core_topic": "Bitcoin price on {date}?",
    "category": "CRYPTO",
    "url": "https://polymarket.com/event/bitcoin-price-on-february-3",
    "strategy_tags": [
      "REFLEXIVITY_TREND"
    ]
  },
  {
    "slug": "bitcoin-above-on-february-5",
    "ticker": "bitcoin-above-96k-on-february-5",
    "question": "96,000",
    "eventTitle": "Bitcoin above ___ on February 5?",
    "prices": "Yes: 0.1% | No: 100.0%",
    "volume": 59996,
    "liquidity": 33034,
    "endDate": "2026-02-05",
    "dayChange": "-0.35%",
    "vol24h": 2641,
    "spread": "0.10%",
    "sortOrder": 10,
    "updatedAt": "2026-02-03T07:51:42.613487Z",
    "engine": "sniper",
    "core_topic": "Bitcoin above ___ on {date}?",
    "category": "CRYPTO",
    "url": "https://polymarket.com/event/bitcoin-above-on-february-5",
    "strategy_tags": [
      "TAIL_RISK",
      "HIGH_CERTAINTY"
    ]
  },
  {
    "slug": "bitcoin-above-on-february-3",
    "ticker": "bitcoin-above-96k-on-february-3",
    "question": "96,000",
    "eventTitle": "Bitcoin above ___ on February 3?",
    "prices": "Yes: 0.1% | No: 100.0%",
    "volume": 57624,
    "liquidity": 91910,
    "endDate": "2026-02-03",
    "dayChange": "0.00%",
    "vol24h": 26806,
    "spread": "0.10%",
    "sortOrder": 9,
    "updatedAt": "2026-02-03T07:51:24.140274Z",
    "engine": "sniper",
    "core_topic": "Bitcoin above ___ on {date}?",
    "category": "CRYPTO",
    "url": "https://polymarket.com/event/bitcoin-above-on-february-3",
    "strategy_tags": [
      "TAIL_RISK",
      "HIGH_CERTAINTY"
    ]
  },
  {
    "slug": "gc-settle-jun-2026",
    "ticker": "gc-settle-above-6200-jun-2026",
    "question": ">$6,200",
    "eventTitle": "What will Gold (GC) settle at in June?",
    "prices": "Yes: 22.1% | No: 77.8%",
    "volume": 55206,
    "liquidity": 7800,
    "endDate": "2026-06-30",
    "dayChange": "2.75%",
    "vol24h": 3296,
    "spread": "0.90%",
    "sortOrder": 7,
    "updatedAt": "2026-02-03T07:51:14.222758Z",
    "engine": "sniper",
    "core_topic": "What will Gold (GC) settle at in {month}?",
    "category": "FINANCE",
    "url": "https://polymarket.com/event/gc-settle-jun-2026",
    "strategy_tags": [
      "HIGH_CERTAINTY"
    ]
  },
  {
    "slug": "bitcoin-price-on-february-3",
    "ticker": "will-the-price-of-bitcoin-be-between-82000-84000-on-february-3",
    "question": "82,000-84,000",
    "eventTitle": "Bitcoin price on February 3?",
    "prices": "Yes: 2.1% | No: 97.9%",
    "volume": 54498,
    "liquidity": 14402,
    "endDate": "2026-02-03",
    "dayChange": "-1.00%",
    "vol24h": 18650,
    "spread": "1.30%",
    "sortOrder": 2,
    "updatedAt": "2026-02-03T07:51:16.821771Z",
    "engine": "sniper",
    "core_topic": "Bitcoin price on {date}?",
    "category": "CRYPTO",
    "url": "https://polymarket.com/event/bitcoin-price-on-february-3",
    "strategy_tags": [
      "TAIL_RISK"
    ]
  },
  {
    "slug": "what-will-gold-gc-hit-by-end-of-february",
    "ticker": "will-gold-gc-hit-low-4450-by-end-of-february-844-276-171-389-959-616-957-814",
    "question": "↓ $4,450",
    "eventTitle": "What will Gold (GC) hit__ by end of February?",
    "prices": "Yes: 34.5% | No: 65.5%",
    "volume": 52478,
    "liquidity": 9780,
    "endDate": "2026-02-28",
    "dayChange": "-27.00%",
    "vol24h": 21963,
    "spread": "3.00%",
    "sortOrder": 15,
    "updatedAt": "2026-02-03T07:54:33.718991Z",
    "engine": "sniper",
    "core_topic": "What will Gold (GC) hit__ by end of {month}?",
    "category": "FINANCE",
    "url": "https://polymarket.com/event/what-will-gold-gc-hit-by-end-of-february",
    "strategy_tags": [
      "REFLEXIVITY_TREND"
    ]
  },
  {
    "slug": "what-will-gold-gc-hit-by-end-of-february",
    "ticker": "will-gold-gc-hit-low-3600-by-end-of-february-767-713-548-338-651-365-876-463",
    "question": "↓ $3,600",
    "eventTitle": "What will Gold (GC) hit__ by end of February?",
    "prices": "Yes: 3.6% | No: 96.4%",
    "volume": 48175,
    "liquidity": 30326,
    "endDate": "2026-02-28",
    "dayChange": "-3.35%",
    "vol24h": 19984,
    "spread": "0.90%",
    "sortOrder": 18,
    "updatedAt": "2026-02-03T07:54:54.939935Z",
    "engine": "sniper",
    "core_topic": "What will Gold (GC) hit__ by end of {month}?",
    "category": "FINANCE",
    "url": "https://polymarket.com/event/what-will-gold-gc-hit-by-end-of-february",
    "strategy_tags": [
      "TAIL_RISK"
    ]
  },
  {
    "slug": "bitcoin-above-on-february-4",
    "ticker": "bitcoin-above-86k-on-february-4",
    "question": "86,000",
    "eventTitle": "Bitcoin above ___ on February 4?",
    "prices": "Yes: 1.3% | No: 98.8%",
    "volume": 47810,
    "liquidity": 22389,
    "endDate": "2026-02-04",
    "dayChange": "0.05%",
    "vol24h": 8398,
    "spread": "0.30%",
    "sortOrder": 3,
    "updatedAt": "2026-02-03T07:51:26.462679Z",
    "engine": "sniper",
    "core_topic": "Bitcoin above ___ on {date}?",
    "category": "CRYPTO",
    "url": "https://polymarket.com/event/bitcoin-above-on-february-4",
    "strategy_tags": [
      "TAIL_RISK"
    ]
  },
  {
    "slug": "bitcoin-above-on-february-5",
    "ticker": "bitcoin-above-82k-on-february-5",
    "question": "82,000",
    "eventTitle": "Bitcoin above ___ on February 5?",
    "prices": "Yes: 15.0% | No: 85.0%",
    "volume": 47270,
    "liquidity": 14949,
    "endDate": "2026-02-05",
    "dayChange": "3.50%",
    "vol24h": 13333,
    "spread": "2.00%",
    "sortOrder": 3,
    "updatedAt": "2026-02-03T07:54:33.911716Z",
    "engine": "sniper",
    "core_topic": "Bitcoin above ___ on {date}?",
    "category": "CRYPTO",
    "url": "https://polymarket.com/event/bitcoin-above-on-february-5",
    "strategy_tags": [
      "RAW_MARKET"
    ]
  },
  {
    "slug": "bitcoin-price-on-february-4",
    "ticker": "will-the-price-of-bitcoin-be-less-than-80000-on-february-4",
    "question": "<80,000",
    "eventTitle": "Bitcoin price on February 4?",
    "prices": "Yes: 67.4% | No: 32.6%",
    "volume": 43997,
    "liquidity": 5791,
    "endDate": "2026-02-04",
    "dayChange": "-11.05%",
    "vol24h": 6280,
    "spread": "3.80%",
    "sortOrder": 0,
    "updatedAt": "2026-02-03T07:54:45.584049Z",
    "engine": "sniper",
    "core_topic": "Bitcoin price on {date}?",
    "category": "CRYPTO",
    "url": "https://polymarket.com/event/bitcoin-price-on-february-4",
    "strategy_tags": [
      "RAW_MARKET"
    ]
  },
  {
    "slug": "bitcoin-above-on-february-3",
    "ticker": "bitcoin-above-98k-on-february-3",
    "question": "98,000",
    "eventTitle": "Bitcoin above ___ on February 3?",
    "prices": "Yes: 0.1% | No: 100.0%",
    "volume": 42602,
    "liquidity": 128591,
    "endDate": "2026-02-03",
    "dayChange": "0.00%",
    "vol24h": 21734,
    "spread": "0.10%",
    "sortOrder": 10,
    "updatedAt": "2026-02-03T07:51:46.879768Z",
    "engine": "sniper",
    "core_topic": "Bitcoin above ___ on {date}?",
    "category": "CRYPTO",
    "url": "https://polymarket.com/event/bitcoin-above-on-february-3",
    "strategy_tags": [
      "TAIL_RISK"
    ]
  },
  {
    "slug": "what-will-gold-gc-hit-by-end-of-february",
    "ticker": "will-gold-gc-hit-high-6200-by-end-of-february-882-138-877-117-343-764-976",
    "question": "↑ $6,200",
    "eventTitle": "What will Gold (GC) hit__ by end of February?",
    "prices": "Yes: 6.3% | No: 93.8%",
    "volume": 40641,
    "liquidity": 27710,
    "endDate": "2026-02-28",
    "dayChange": "-1.10%",
    "vol24h": 14985,
    "spread": "0.30%",
    "sortOrder": 4,
    "updatedAt": "2026-02-03T07:54:28.870037Z",
    "engine": "sniper",
    "core_topic": "What will Gold (GC) hit__ by end of {month}?",
    "category": "FINANCE",
    "url": "https://polymarket.com/event/what-will-gold-gc-hit-by-end-of-february",
    "strategy_tags": [
      "RAW_MARKET"
    ]
  },
  {
    "slug": "gc-settle-jun-2026",
    "ticker": "gc-settle-below-3800-jun-2026",
    "question": "<$3,800",
    "eventTitle": "What will Gold (GC) settle at in June?",
    "prices": "Yes: 9.8% | No: 90.1%",
    "volume": 40602,
    "liquidity": 6244,
    "endDate": "2026-06-30",
    "dayChange": "-4.10%",
    "vol24h": 421,
    "spread": "1.50%",
    "sortOrder": 0,
    "updatedAt": "2026-02-03T07:49:32.759958Z",
    "engine": "sniper",
    "core_topic": "What will Gold (GC) settle at in {month}?",
    "category": "FINANCE",
    "url": "https://polymarket.com/event/gc-settle-jun-2026",
    "strategy_tags": [
      "RAW_MARKET"
    ]
  },
  {
    "slug": "bitcoin-above-on-february-5",
    "ticker": "bitcoin-above-86k-on-february-5",
    "question": "86,000",
    "eventTitle": "Bitcoin above ___ on February 5?",
    "prices": "Yes: 2.0% | No: 98.0%",
    "volume": 39588,
    "liquidity": 18310,
    "endDate": "2026-02-05",
    "dayChange": "-1.30%",
    "vol24h": 9124,
    "spread": "0.20%",
    "sortOrder": 5,
    "updatedAt": "2026-02-03T07:51:47.651136Z",
    "engine": "sniper",
    "core_topic": "Bitcoin above ___ on {date}?",
    "category": "CRYPTO",
    "url": "https://polymarket.com/event/bitcoin-above-on-february-5",
    "strategy_tags": [
      "TAIL_RISK"
    ]
  },
  {
    "slug": "bitcoin-above-on-february-4",
    "ticker": "bitcoin-above-88k-on-february-4",
    "question": "88,000",
    "eventTitle": "Bitcoin above ___ on February 4?",
    "prices": "Yes: 0.3% | No: 99.8%",
    "volume": 36105,
    "liquidity": 20581,
    "endDate": "2026-02-04",
    "dayChange": "-1.00%",
    "vol24h": 3955,
    "spread": "0.10%",
    "sortOrder": 4,
    "updatedAt": "2026-02-03T07:51:29.324226Z",
    "engine": "sniper",
    "core_topic": "Bitcoin above ___ on {date}?",
    "category": "CRYPTO",
    "url": "https://polymarket.com/event/bitcoin-above-on-february-4",
    "strategy_tags": [
      "TAIL_RISK"
    ]
  },
  {
    "slug": "bitcoin-above-on-february-4",
    "ticker": "bitcoin-above-90k-on-february-4",
    "question": "90,000",
    "eventTitle": "Bitcoin above ___ on February 4?",
    "prices": "Yes: 0.3% | No: 99.7%",
    "volume": 34650,
    "liquidity": 29866,
    "endDate": "2026-02-04",
    "dayChange": "-0.35%",
    "vol24h": 6674,
    "spread": "0.20%",
    "sortOrder": 5,
    "updatedAt": "2026-02-03T07:51:09.575364Z",
    "engine": "sniper",
    "core_topic": "Bitcoin above ___ on {date}?",
    "category": "CRYPTO",
    "url": "https://polymarket.com/event/bitcoin-above-on-february-4",
    "strategy_tags": [
      "TAIL_RISK"
    ]
  },
  {
    "slug": "bitcoin-above-on-february-5",
    "ticker": "bitcoin-above-92k-on-february-5",
    "question": "92,000",
    "eventTitle": "Bitcoin above ___ on February 5?",
    "prices": "Yes: 0.3% | No: 99.7%",
    "volume": 34454,
    "liquidity": 19201,
    "endDate": "2026-02-05",
    "dayChange": "-1.35%",
    "vol24h": 2924,
    "spread": "0.20%",
    "sortOrder": 8,
    "updatedAt": "2026-02-03T07:54:44.651751Z",
    "engine": "sniper",
    "core_topic": "Bitcoin above ___ on {date}?",
    "category": "CRYPTO",
    "url": "https://polymarket.com/event/bitcoin-above-on-february-5",
    "strategy_tags": [
      "TAIL_RISK"
    ]
  },
  {
    "slug": "bitcoin-above-on-february-5",
    "ticker": "bitcoin-above-90k-on-february-5",
    "question": "90,000",
    "eventTitle": "Bitcoin above ___ on February 5?",
    "prices": "Yes: 0.9% | No: 99.1%",
    "volume": 34100,
    "liquidity": 18260,
    "endDate": "2026-02-05",
    "dayChange": "-1.55%",
    "vol24h": 11103,
    "spread": "0.70%",
    "sortOrder": 7,
    "updatedAt": "2026-02-03T07:51:47.270677Z",
    "engine": "sniper",
    "core_topic": "Bitcoin above ___ on {date}?",
    "category": "CRYPTO",
    "url": "https://polymarket.com/event/bitcoin-above-on-february-5",
    "strategy_tags": [
      "TAIL_RISK"
    ]
  },
  {
    "slug": "bitcoin-above-on-february-5",
    "ticker": "bitcoin-above-78k-on-february-5",
    "question": "78,000",
    "eventTitle": "Bitcoin above ___ on February 5?",
    "prices": "Yes: 61.5% | No: 38.5%",
    "volume": 31317,
    "liquidity": 16770,
    "endDate": "2026-02-05",
    "dayChange": "22.00%",
    "vol24h": 10837,
    "spread": "1.00%",
    "sortOrder": 1,
    "updatedAt": "2026-02-03T07:51:44.760099Z",
    "engine": "sniper",
    "core_topic": "Bitcoin above ___ on {date}?",
    "category": "CRYPTO",
    "url": "https://polymarket.com/event/bitcoin-above-on-february-5",
    "strategy_tags": [
      "REFLEXIVITY_TREND"
    ]
  },
  {
    "slug": "bitcoin-price-on-february-4",
    "ticker": "will-the-price-of-bitcoin-be-greater-than-98000-on-february-4",
    "question": ">98,000",
    "eventTitle": "Bitcoin price on February 4?",
    "prices": "Yes: 0.1% | No: 99.9%",
    "volume": 28313,
    "liquidity": 20132,
    "endDate": "2026-02-04",
    "dayChange": "-0.10%",
    "vol24h": 27239,
    "spread": "0.30%",
    "sortOrder": 10,
    "updatedAt": "2026-02-03T07:54:46.153425Z",
    "engine": "sniper",
    "core_topic": "Bitcoin price on {date}?",
    "category": "CRYPTO",
    "url": "https://polymarket.com/event/bitcoin-price-on-february-4",
    "strategy_tags": [
      "TAIL_RISK"
    ]
  },
  {
    "slug": "bitcoin-above-on-february-4",
    "ticker": "bitcoin-above-100k-on-february-4",
    "question": "100,000",
    "eventTitle": "Bitcoin above ___ on February 4?",
    "prices": "Yes: 0.1% | No: 100.0%",
    "volume": 28151,
    "liquidity": 67404,
    "endDate": "2026-02-04",
    "dayChange": "-0.10%",
    "vol24h": 20865,
    "spread": "0.10%",
    "sortOrder": 10,
    "updatedAt": "2026-02-03T07:51:19.954734Z",
    "engine": "sniper",
    "core_topic": "Bitcoin above ___ on {date}?",
    "category": "CRYPTO",
    "url": "https://polymarket.com/event/bitcoin-above-on-february-4",
    "strategy_tags": [
      "TAIL_RISK"
    ]
  },
  {
    "slug": "bitcoin-above-on-february-4",
    "ticker": "bitcoin-above-96k-on-february-4",
    "question": "96,000",
    "eventTitle": "Bitcoin above ___ on February 4?",
    "prices": "Yes: 0.1% | No: 100.0%",
    "volume": 27950,
    "liquidity": 31345,
    "endDate": "2026-02-04",
    "dayChange": "-0.25%",
    "vol24h": 17964,
    "spread": "0.10%",
    "sortOrder": 8,
    "updatedAt": "2026-02-03T07:51:19.115306Z",
    "engine": "sniper",
    "core_topic": "Bitcoin above ___ on {date}?",
    "category": "CRYPTO",
    "url": "https://polymarket.com/event/bitcoin-above-on-february-4",
    "strategy_tags": [
      "TAIL_RISK"
    ]
  },
  {
    "slug": "bitcoin-price-on-february-5",
    "ticker": "will-the-price-of-bitcoin-be-less-than-76000-on-february-5",
    "question": "<76,000",
    "eventTitle": "Bitcoin price on February 5?",
    "prices": "Yes: 19.8% | No: 80.2%",
    "volume": 26012,
    "liquidity": 9445,
    "endDate": "2026-02-05",
    "dayChange": "-21.45%",
    "vol24h": 2763,
    "spread": "1.60%",
    "sortOrder": 0,
    "updatedAt": "2026-02-03T07:51:28.963289Z",
    "engine": "sniper",
    "core_topic": "Bitcoin price on {date}?",
    "category": "CRYPTO",
    "url": "https://polymarket.com/event/bitcoin-price-on-february-5",
    "strategy_tags": [
      "RAW_MARKET"
    ]
  },
  {
    "slug": "bitcoin-above-on-february-4",
    "ticker": "bitcoin-above-98k-on-february-4",
    "question": "98,000",
    "eventTitle": "Bitcoin above ___ on February 4?",
    "prices": "Yes: 0.1% | No: 100.0%",
    "volume": 25452,
    "liquidity": 29088,
    "endDate": "2026-02-04",
    "dayChange": "-0.10%",
    "vol24h": 18316,
    "spread": "0.10%",
    "sortOrder": 9,
    "updatedAt": "2026-02-03T07:51:44.699183Z",
    "engine": "sniper",
    "core_topic": "Bitcoin above ___ on {date}?",
    "category": "CRYPTO",
    "url": "https://polymarket.com/event/bitcoin-above-on-february-4",
    "strategy_tags": [
      "TAIL_RISK"
    ]
  },
  {
    "slug": "gc-settle-jun-2026",
    "ticker": "gc-settle-5800-6200-jun-2026",
    "question": "$5,800-$6,200",
    "eventTitle": "What will Gold (GC) settle at in June?",
    "prices": "Yes: 9.0% | No: 91.0%",
    "volume": 25206,
    "liquidity": 2431,
    "endDate": "2026-06-30",
    "dayChange": "-1.30%",
    "vol24h": 1021,
    "spread": "3.60%",
    "sortOrder": 6,
    "updatedAt": "2026-02-03T07:51:13.174307Z",
    "engine": "sniper",
    "core_topic": "What will Gold (GC) settle at in {month}?",
    "category": "FINANCE",
    "url": "https://polymarket.com/event/gc-settle-jun-2026",
    "strategy_tags": [
      "RAW_MARKET"
    ]
  },
  {
    "slug": "what-will-gold-gc-hit-by-end-of-february",
    "ticker": "will-gold-gc-hit-low-4000-by-end-of-february-542-564-882-215-825-637-559-654-593",
    "question": "↓ $4,000",
    "eventTitle": "What will Gold (GC) hit__ by end of February?",
    "prices": "Yes: 12.4% | No: 87.6%",
    "volume": 24782,
    "liquidity": 8030,
    "endDate": "2026-02-28",
    "dayChange": "-10.55%",
    "vol24h": 10972,
    "spread": "0.80%",
    "sortOrder": 17,
    "updatedAt": "2026-02-03T07:54:28.719334Z",
    "engine": "sniper",
    "core_topic": "What will Gold (GC) hit__ by end of {month}?",
    "category": "FINANCE",
    "url": "https://polymarket.com/event/what-will-gold-gc-hit-by-end-of-february",
    "strategy_tags": [
      "REFLEXIVITY_TREND"
    ]
  },
  {
    "slug": "bitcoin-price-on-february-4",
    "ticker": "will-the-price-of-bitcoin-be-between-92000-94000-on-february-4",
    "question": "92,000-94,000",
    "eventTitle": "Bitcoin price on February 4?",
    "prices": "Yes: 0.1% | No: 100.0%",
    "volume": 24375,
    "liquidity": 31226,
    "endDate": "2026-02-04",
    "dayChange": "-1.70%",
    "vol24h": 2577,
    "spread": "0.10%",
    "sortOrder": 7,
    "updatedAt": "2026-02-03T07:54:42.726278Z",
    "engine": "sniper",
    "core_topic": "Bitcoin price on {date}?",
    "category": "CRYPTO",
    "url": "https://polymarket.com/event/bitcoin-price-on-february-4",
    "strategy_tags": [
      "TAIL_RISK"
    ]
  },
  {
    "slug": "gc-settle-jun-2026",
    "ticker": "gc-settle-5000-5400-jun-2026",
    "question": "$5,000-$5,400",
    "eventTitle": "What will Gold (GC) settle at in June?",
    "prices": "Yes: 13.6% | No: 86.5%",
    "volume": 23767,
    "liquidity": 6691,
    "endDate": "2026-06-30",
    "dayChange": "-0.75%",
    "vol24h": 480,
    "spread": "3.50%",
    "sortOrder": 4,
    "updatedAt": "2026-02-03T07:49:11.367341Z",
    "engine": "sniper",
    "core_topic": "What will Gold (GC) settle at in {month}?",
    "category": "FINANCE",
    "url": "https://polymarket.com/event/gc-settle-jun-2026",
    "strategy_tags": [
      "RAW_MARKET"
    ]
  },
  {
    "slug": "what-will-gold-gc-hit-by-end-of-february",
    "ticker": "will-gold-gc-hit-low-4200-by-end-of-february-891-227-734-585-416-787-933-185-752",
    "question": "↓ $4,200",
    "eventTitle": "What will Gold (GC) hit__ by end of February?",
    "prices": "Yes: 21.5% | No: 78.5%",
    "volume": 23611,
    "liquidity": 3898,
    "endDate": "2026-02-28",
    "dayChange": "-22.00%",
    "vol24h": 9440,
    "spread": "1.00%",
    "sortOrder": 16,
    "updatedAt": "2026-02-03T07:55:01.928161Z",
    "engine": "sniper",
    "core_topic": "What will Gold (GC) hit__ by end of {month}?",
    "category": "FINANCE",
    "url": "https://polymarket.com/event/what-will-gold-gc-hit-by-end-of-february",
    "strategy_tags": [
      "RAW_MARKET"
    ]
  },
  {
    "slug": "bitcoin-price-on-february-3",
    "ticker": "will-the-price-of-bitcoin-be-between-92000-94000-on-february-3",
    "question": "92,000-94,000",
    "eventTitle": "Bitcoin price on February 3?",
    "prices": "Yes: 0.1% | No: 100.0%",
    "volume": 21889,
    "liquidity": 55810,
    "endDate": "2026-02-03",
    "dayChange": "-0.10%",
    "vol24h": 16876,
    "spread": "0.10%",
    "sortOrder": 7,
    "updatedAt": "2026-02-03T07:51:41.769672Z",
    "engine": "sniper",
    "core_topic": "Bitcoin price on {date}?",
    "category": "CRYPTO",
    "url": "https://polymarket.com/event/bitcoin-price-on-february-3",
    "strategy_tags": [
      "TAIL_RISK"
    ]
  },
  {
    "slug": "bitcoin-price-on-february-3",
    "ticker": "will-the-price-of-bitcoin-be-between-94000-96000-on-february-3",
    "question": "94,000-96,000",
    "eventTitle": "Bitcoin price on February 3?",
    "prices": "Yes: 0.1% | No: 100.0%",
    "volume": 20341,
    "liquidity": 54906,
    "endDate": "2026-02-03",
    "dayChange": "-0.10%",
    "vol24h": 17509,
    "spread": "0.10%",
    "sortOrder": 8,
    "updatedAt": "2026-02-03T07:51:41.671054Z",
    "engine": "sniper",
    "core_topic": "Bitcoin price on {date}?",
    "category": "CRYPTO",
    "url": "https://polymarket.com/event/bitcoin-price-on-february-3",
    "strategy_tags": [
      "TAIL_RISK"
    ]
  },
  {
    "slug": "gc-settle-jun-2026",
    "ticker": "gc-settle-4600-5000-jun-2026",
    "question": "$4,600-$5,000",
    "eventTitle": "What will Gold (GC) settle at in June?",
    "prices": "Yes: 13.0% | No: 87.0%",
    "volume": 20285,
    "liquidity": 8573,
    "endDate": "2026-06-30",
    "dayChange": "-0.50%",
    "vol24h": 145,
    "spread": "2.00%",
    "sortOrder": 3,
    "updatedAt": "2026-02-03T07:51:13.409025Z",
    "engine": "sniper",
    "core_topic": "What will Gold (GC) settle at in {month}?",
    "category": "FINANCE",
    "url": "https://polymarket.com/event/gc-settle-jun-2026",
    "strategy_tags": [
      "RAW_MARKET"
    ]
  },
  {
    "slug": "gc-settle-jun-2026",
    "ticker": "gc-settle-3800-4200-jun-2026",
    "question": "$3,800-$4,200",
    "eventTitle": "What will Gold (GC) settle at in June?",
    "prices": "Yes: 9.2% | No: 90.8%",
    "volume": 19036,
    "liquidity": 6291,
    "endDate": "2026-06-30",
    "dayChange": "0.05%",
    "vol24h": 668,
    "spread": "0.70%",
    "sortOrder": 1,
    "updatedAt": "2026-02-03T07:49:31.881146Z",
    "engine": "sniper",
    "core_topic": "What will Gold (GC) settle at in {month}?",
    "category": "FINANCE",
    "url": "https://polymarket.com/event/gc-settle-jun-2026",
    "strategy_tags": [
      "RAW_MARKET"
    ]
  },
  {
    "slug": "bitcoin-price-on-february-5",
    "ticker": "will-the-price-of-bitcoin-be-between-76000-78000-on-february-5",
    "question": "76,000-78,000",
    "eventTitle": "Bitcoin price on February 5?",
    "prices": "Yes: 20.3% | No: 79.8%",
    "volume": 18648,
    "liquidity": 9699,
    "endDate": "2026-02-05",
    "dayChange": "2.85%",
    "vol24h": 4036,
    "spread": "2.30%",
    "sortOrder": 1,
    "updatedAt": "2026-02-03T07:51:46.201852Z",
    "engine": "sniper",
    "core_topic": "Bitcoin price on {date}?",
    "category": "CRYPTO",
    "url": "https://polymarket.com/event/bitcoin-price-on-february-5",
    "strategy_tags": [
      "RAW_MARKET"
    ]
  },
  {
    "slug": "gc-settle-jun-2026",
    "ticker": "gc-settle-4200-4600-jun-2026",
    "question": "$4,200-$4,600",
    "eventTitle": "What will Gold (GC) settle at in June?",
    "prices": "Yes: 11.2% | No: 88.8%",
    "volume": 18621,
    "liquidity": 3419,
    "endDate": "2026-06-30",
    "dayChange": "0.50%",
    "vol24h": 85,
    "spread": "1.60%",
    "sortOrder": 2,
    "updatedAt": "2026-02-03T07:49:16.134411Z",
    "engine": "sniper",
    "core_topic": "What will Gold (GC) settle at in {month}?",
    "category": "FINANCE",
    "url": "https://polymarket.com/event/gc-settle-jun-2026",
    "strategy_tags": [
      "RAW_MARKET"
    ]
  },
  {
    "slug": "gc-settle-jun-2026",
    "ticker": "gc-settle-5400-5800-jun-2026",
    "question": "$5,400-$5,800",
    "eventTitle": "What will Gold (GC) settle at in June?",
    "prices": "Yes: 11.0% | No: 89.0%",
    "volume": 18223,
    "liquidity": 2662,
    "endDate": "2026-06-30",
    "dayChange": "-1.50%",
    "vol24h": 298,
    "spread": "2.00%",
    "sortOrder": 5,
    "updatedAt": "2026-02-03T07:51:11.216294Z",
    "engine": "sniper",
    "core_topic": "What will Gold (GC) settle at in {month}?",
    "category": "FINANCE",
    "url": "https://polymarket.com/event/gc-settle-jun-2026",
    "strategy_tags": [
      "RAW_MARKET"
    ]
  },
  {
    "slug": "bitcoin-price-on-february-4",
    "ticker": "will-the-price-of-bitcoin-be-between-80000-82000-on-february-4",
    "question": "80,000-82,000",
    "eventTitle": "Bitcoin price on February 4?",
    "prices": "Yes: 21.0% | No: 79.0%",
    "volume": 17061,
    "liquidity": 10786,
    "endDate": "2026-02-04",
    "dayChange": "11.50%",
    "vol24h": 5926,
    "spread": "2.00%",
    "sortOrder": 1,
    "updatedAt": "2026-02-03T07:54:54.332524Z",
    "engine": "sniper",
    "core_topic": "Bitcoin price on {date}?",
    "category": "CRYPTO",
    "url": "https://polymarket.com/event/bitcoin-price-on-february-4",
    "strategy_tags": [
      "RAW_MARKET"
    ]
  },
  {
    "slug": "bitcoin-price-on-february-3",
    "ticker": "will-the-price-of-bitcoin-be-greater-than-98000-on-february-3",
    "question": ">98,000",
    "eventTitle": "Bitcoin price on February 3?",
    "prices": "Yes: 0.1% | No: 100.0%",
    "volume": 17039,
    "liquidity": 67600,
    "endDate": "2026-02-03",
    "dayChange": "-0.10%",
    "vol24h": 6969,
    "spread": "0.10%",
    "sortOrder": 10,
    "updatedAt": "2026-02-03T07:51:28.540466Z",
    "engine": "sniper",
    "core_topic": "Bitcoin price on {date}?",
    "category": "CRYPTO",
    "url": "https://polymarket.com/event/bitcoin-price-on-february-3",
    "strategy_tags": [
      "TAIL_RISK"
    ]
  },
  {
    "slug": "bitcoin-price-on-february-4",
    "ticker": "will-the-price-of-bitcoin-be-between-96000-98000-on-february-4",
    "question": "96,000-98,000",
    "eventTitle": "Bitcoin price on February 4?",
    "prices": "Yes: 0.1% | No: 100.0%",
    "volume": 17031,
    "liquidity": 23716,
    "endDate": "2026-02-04",
    "dayChange": "-0.30%",
    "vol24h": 16473,
    "spread": "0.10%",
    "sortOrder": 9,
    "updatedAt": "2026-02-03T07:54:41.932866Z",
    "engine": "sniper",
    "core_topic": "Bitcoin price on {date}?",
    "category": "CRYPTO",
    "url": "https://polymarket.com/event/bitcoin-price-on-february-4",
    "strategy_tags": [
      "TAIL_RISK"
    ]
  },
  {
    "slug": "bitcoin-price-on-february-4",
    "ticker": "will-the-price-of-bitcoin-be-between-86000-88000-on-february-4",
    "question": "86,000-88,000",
    "eventTitle": "Bitcoin price on February 4?",
    "prices": "Yes: 1.4% | No: 98.6%",
    "volume": 15145,
    "liquidity": 11452,
    "endDate": "2026-02-04",
    "dayChange": "-1.40%",
    "vol24h": 2114,
    "spread": "1.00%",
    "sortOrder": 4,
    "updatedAt": "2026-02-03T07:54:42.672893Z",
    "engine": "sniper",
    "core_topic": "Bitcoin price on {date}?",
    "category": "CRYPTO",
    "url": "https://polymarket.com/event/bitcoin-price-on-february-4",
    "strategy_tags": [
      "TAIL_RISK"
    ]
  },
  {
    "slug": "bitcoin-above-on-february-5",
    "ticker": "bitcoin-above-88k-on-february-5",
    "question": "88,000",
    "eventTitle": "Bitcoin above ___ on February 5?",
    "prices": "Yes: 1.2% | No: 98.8%",
    "volume": 14777,
    "liquidity": 17409,
    "endDate": "2026-02-05",
    "dayChange": "-1.55%",
    "vol24h": 3247,
    "spread": "0.40%",
    "sortOrder": 6,
    "updatedAt": "2026-02-03T07:51:47.26047Z",
    "engine": "sniper",
    "core_topic": "Bitcoin above ___ on {date}?",
    "category": "CRYPTO",
    "url": "https://polymarket.com/event/bitcoin-above-on-february-5",
    "strategy_tags": [
      "TAIL_RISK"
    ]
  },
  {
    "slug": "bitcoin-price-on-february-5",
    "ticker": "will-the-price-of-bitcoin-be-between-78000-80000-on-february-5",
    "question": "78,000-80,000",
    "eventTitle": "Bitcoin price on February 5?",
    "prices": "Yes: 25.0% | No: 75.0%",
    "volume": 14010,
    "liquidity": 10097,
    "endDate": "2026-02-05",
    "dayChange": "7.00%",
    "vol24h": 1131,
    "spread": "2.00%",
    "sortOrder": 2,
    "updatedAt": "2026-02-03T07:51:37.229505Z",
    "engine": "sniper",
    "core_topic": "Bitcoin price on {date}?",
    "category": "CRYPTO",
    "url": "https://polymarket.com/event/bitcoin-price-on-february-5",
    "strategy_tags": [
      "RAW_MARKET"
    ]
  },
  {
    "slug": "bitcoin-price-on-february-4",
    "ticker": "will-the-price-of-bitcoin-be-between-82000-84000-on-february-4",
    "question": "82,000-84,000",
    "eventTitle": "Bitcoin price on February 4?",
    "prices": "Yes: 8.0% | No: 92.0%",
    "volume": 13472,
    "liquidity": 10597,
    "endDate": "2026-02-04",
    "dayChange": "3.70%",
    "vol24h": 9008,
    "spread": "2.20%",
    "sortOrder": 2,
    "updatedAt": "2026-02-03T07:54:36.271496Z",
    "engine": "sniper",
    "core_topic": "Bitcoin price on {date}?",
    "category": "CRYPTO",
    "url": "https://polymarket.com/event/bitcoin-price-on-february-4",
    "strategy_tags": [
      "RAW_MARKET"
    ]
  },
  {
    "slug": "bitcoin-price-on-february-5",
    "ticker": "will-the-price-of-bitcoin-be-greater-than-94000-on-february-5",
    "question": ">94,000",
    "eventTitle": "Bitcoin price on February 5?",
    "prices": "Yes: 0.1% | No: 99.9%",
    "volume": 13180,
    "liquidity": 12379,
    "endDate": "2026-02-05",
    "dayChange": "-0.55%",
    "vol24h": 827,
    "spread": "0.10%",
    "sortOrder": 10,
    "updatedAt": "2026-02-03T07:51:27.168676Z",
    "engine": "sniper",
    "core_topic": "Bitcoin price on {date}?",
    "category": "CRYPTO",
    "url": "https://polymarket.com/event/bitcoin-price-on-february-5",
    "strategy_tags": [
      "TAIL_RISK"
    ]
  },
  {
    "slug": "bitcoin-price-on-february-3",
    "ticker": "will-the-price-of-bitcoin-be-between-96000-98000-on-february-3",
    "question": "96,000-98,000",
    "eventTitle": "Bitcoin price on February 3?",
    "prices": "Yes: 0.1% | No: 100.0%",
    "volume": 12097,
    "liquidity": 56757,
    "endDate": "2026-02-03",
    "dayChange": "-0.05%",
    "vol24h": 7313,
    "spread": "0.10%",
    "sortOrder": 9,
    "updatedAt": "2026-02-03T07:51:43.565983Z",
    "engine": "sniper",
    "core_topic": "Bitcoin price on {date}?",
    "category": "CRYPTO",
    "url": "https://polymarket.com/event/bitcoin-price-on-february-3",
    "strategy_tags": [
      "TAIL_RISK"
    ]
  },
  {
    "slug": "bitcoin-price-on-february-4",
    "ticker": "will-the-price-of-bitcoin-be-between-94000-96000-on-february-4",
    "question": "94,000-96,000",
    "eventTitle": "Bitcoin price on February 4?",
    "prices": "Yes: 0.1% | No: 99.9%",
    "volume": 10824,
    "liquidity": 17430,
    "endDate": "2026-02-04",
    "dayChange": "-0.30%",
    "vol24h": 5361,
    "spread": "0.10%",
    "sortOrder": 8,
    "updatedAt": "2026-02-03T07:54:58.83551Z",
    "engine": "sniper",
    "core_topic": "Bitcoin price on {date}?",
    "category": "CRYPTO",
    "url": "https://polymarket.com/event/bitcoin-price-on-february-4",
    "strategy_tags": [
      "TAIL_RISK"
    ]
  },
  {
    "slug": "bitcoin-price-on-february-4",
    "ticker": "will-the-price-of-bitcoin-be-between-90000-92000-on-february-4",
    "question": "90,000-92,000",
    "eventTitle": "Bitcoin price on February 4?",
    "prices": "Yes: 0.1% | No: 99.9%",
    "volume": 10690,
    "liquidity": 11367,
    "endDate": "2026-02-04",
    "dayChange": "-0.20%",
    "vol24h": 2496,
    "spread": "0.10%",
    "sortOrder": 6,
    "updatedAt": "2026-02-03T07:54:54.680656Z",
    "engine": "sniper",
    "core_topic": "Bitcoin price on {date}?",
    "category": "CRYPTO",
    "url": "https://polymarket.com/event/bitcoin-price-on-february-4",
    "strategy_tags": [
      "TAIL_RISK"
    ]
  },
  {
    "slug": "bitcoin-above-on-february-5",
    "ticker": "bitcoin-above-94k-on-february-5",
    "question": "94,000",
    "eventTitle": "Bitcoin above ___ on February 5?",
    "prices": "Yes: 0.3% | No: 99.7%",
    "volume": 8736,
    "liquidity": 10586,
    "endDate": "2026-02-05",
    "dayChange": "0.05%",
    "vol24h": 384,
    "spread": "0.40%",
    "sortOrder": 9,
    "updatedAt": "2026-02-03T07:54:36.484008Z",
    "engine": "sniper",
    "core_topic": "Bitcoin above ___ on {date}?",
    "category": "CRYPTO",
    "url": "https://polymarket.com/event/bitcoin-above-on-february-5",
    "strategy_tags": [
      "TAIL_RISK"
    ]
  },
  {
    "slug": "bitcoin-price-on-february-4",
    "ticker": "will-the-price-of-bitcoin-be-between-84000-86000-on-february-4",
    "question": "84,000-86,000",
    "eventTitle": "Bitcoin price on February 4?",
    "prices": "Yes: 1.5% | No: 98.5%",
    "volume": 8682,
    "liquidity": 11199,
    "endDate": "2026-02-04",
    "dayChange": "-1.80%",
    "vol24h": 2034,
    "spread": "1.20%",
    "sortOrder": 3,
    "updatedAt": "2026-02-03T07:54:46.069603Z",
    "engine": "sniper",
    "core_topic": "Bitcoin price on {date}?",
    "category": "CRYPTO",
    "url": "https://polymarket.com/event/bitcoin-price-on-february-4",
    "strategy_tags": [
      "TAIL_RISK"
    ]
  },
  {
    "slug": "bitcoin-price-on-february-4",
    "ticker": "will-the-price-of-bitcoin-be-between-88000-90000-on-february-4",
    "question": "88,000-90,000",
    "eventTitle": "Bitcoin price on February 4?",
    "prices": "Yes: 0.4% | No: 99.7%",
    "volume": 7339,
    "liquidity": 11396,
    "endDate": "2026-02-04",
    "dayChange": "-2.65%",
    "vol24h": 3159,
    "spread": "0.30%",
    "sortOrder": 5,
    "updatedAt": "2026-02-03T07:54:37.90563Z",
    "engine": "sniper",
    "core_topic": "Bitcoin price on {date}?",
    "category": "CRYPTO",
    "url": "https://polymarket.com/event/bitcoin-price-on-february-4",
    "strategy_tags": [
      "TAIL_RISK"
    ]
  },
  {
    "slug": "bitcoin-price-on-february-5",
    "ticker": "will-the-price-of-bitcoin-be-between-90000-92000-on-february-5",
    "question": "90,000-92,000",
    "eventTitle": "Bitcoin price on February 5?",
    "prices": "Yes: 0.4% | No: 99.6%",
    "volume": 5755,
    "liquidity": 10016,
    "endDate": "2026-02-05",
    "dayChange": "-2.55%",
    "vol24h": 1259,
    "spread": "0.40%",
    "sortOrder": 8,
    "updatedAt": "2026-02-03T07:51:26.996052Z",
    "engine": "sniper",
    "core_topic": "Bitcoin price on {date}?",
    "category": "CRYPTO",
    "url": "https://polymarket.com/event/bitcoin-price-on-february-5",
    "strategy_tags": [
      "TAIL_RISK"
    ]
  },
  {
    "slug": "bitcoin-price-on-february-5",
    "ticker": "will-the-price-of-bitcoin-be-between-84000-86000-on-february-5",
    "question": "84,000-86,000",
    "eventTitle": "Bitcoin price on February 5?",
    "prices": "Yes: 3.9% | No: 96.2%",
    "volume": 5451,
    "liquidity": 10284,
    "endDate": "2026-02-05",
    "dayChange": "-0.20%",
    "vol24h": 3391,
    "spread": "2.10%",
    "sortOrder": 5,
    "updatedAt": "2026-02-03T07:51:35.8048Z",
    "engine": "sniper",
    "core_topic": "Bitcoin price on {date}?",
    "category": "CRYPTO",
    "url": "https://polymarket.com/event/bitcoin-price-on-february-5",
    "strategy_tags": [
      "TAIL_RISK"
    ]
  },
  {
    "slug": "bitcoin-price-on-february-5",
    "ticker": "will-the-price-of-bitcoin-be-between-92000-94000-on-february-5",
    "question": "92,000-94,000",
    "eventTitle": "Bitcoin price on February 5?",
    "prices": "Yes: 0.4% | No: 99.7%",
    "volume": 5246,
    "liquidity": 10382,
    "endDate": "2026-02-05",
    "dayChange": "-0.35%",
    "vol24h": 1292,
    "spread": "0.30%",
    "sortOrder": 9,
    "updatedAt": "2026-02-03T07:51:46.548231Z",
    "engine": "sniper",
    "core_topic": "Bitcoin price on {date}?",
    "category": "CRYPTO",
    "url": "https://polymarket.com/event/bitcoin-price-on-february-5",
    "strategy_tags": [
      "TAIL_RISK"
    ]
  },
  {
    "slug": "bitcoin-price-on-february-5",
    "ticker": "will-the-price-of-bitcoin-be-between-86000-88000-on-february-5",
    "question": "86,000-88,000",
    "eventTitle": "Bitcoin price on February 5?",
    "prices": "Yes: 0.8% | No: 99.3%",
    "volume": 2703,
    "liquidity": 9408,
    "endDate": "2026-02-05",
    "dayChange": "-2.60%",
    "vol24h": 1205,
    "spread": "0.10%",
    "sortOrder": 6,
    "updatedAt": "2026-02-03T07:51:13.691445Z",
    "engine": "sniper",
    "core_topic": "Bitcoin price on {date}?",
    "category": "CRYPTO",
    "url": "https://polymarket.com/event/bitcoin-price-on-february-5",
    "strategy_tags": [
      "TAIL_RISK"
    ]
  },
  {
    "slug": "bitcoin-price-on-february-5",
    "ticker": "will-the-price-of-bitcoin-be-between-88000-90000-on-february-5",
    "question": "88,000-90,000",
    "eventTitle": "Bitcoin price on February 5?",
    "prices": "Yes: 0.4% | No: 99.6%",
    "volume": 1842,
    "liquidity": 9456,
    "endDate": "2026-02-05",
    "dayChange": "-1.40%",
    "vol24h": 843,
    "spread": "0.40%",
    "sortOrder": 7,
    "updatedAt": "2026-02-03T07:51:48.126847Z",
    "engine": "sniper",
    "core_topic": "Bitcoin price on {date}?",
    "category": "CRYPTO",
    "url": "https://polymarket.com/event/bitcoin-price-on-february-5",
    "strategy_tags": [
      "TAIL_RISK"
    ]
  },
  {
    "slug": "bitcoin-price-on-february-5",
    "ticker": "will-the-price-of-bitcoin-be-between-80000-82000-on-february-5",
    "question": "80,000-82,000",
    "eventTitle": "Bitcoin price on February 5?",
    "prices": "Yes: 20.5% | No: 79.5%",
    "volume": 1284,
    "liquidity": 9467,
    "endDate": "2026-02-05",
    "dayChange": "9.00%",
    "vol24h": 60,
    "spread": "3.00%",
    "sortOrder": 3,
    "updatedAt": "2026-02-03T07:51:37.008272Z",
    "engine": "sniper",
    "core_topic": "Bitcoin price on {date}?",
    "category": "CRYPTO",
    "url": "https://polymarket.com/event/bitcoin-price-on-february-5",
    "strategy_tags": [
      "RAW_MARKET"
    ]
  },
  {
    "slug": "bitcoin-price-on-february-5",
    "ticker": "will-the-price-of-bitcoin-be-between-82000-84000-on-february-5",
    "question": "82,000-84,000",
    "eventTitle": "Bitcoin price on February 5?",
    "prices": "Yes: 8.8% | No: 91.1%",
    "volume": 875,
    "liquidity": 9282,
    "endDate": "2026-02-05",
    "dayChange": "3.55%",
    "vol24h": 29,
    "spread": "3.30%",
    "sortOrder": 4,
    "updatedAt": "2026-02-03T07:51:21.592904Z",
    "engine": "sniper",
    "core_topic": "Bitcoin price on {date}?",
    "category": "CRYPTO",
    "url": "https://polymarket.com/event/bitcoin-price-on-february-5",
    "strategy_tags": [
      "RAW_MARKET"
    ]
  }
]